Workbook

Sheet Control Panel
A1: ⚙ NO DICE BOROUGH LTD · CONTROL PANEL · Central Input Hub
A2: 🔵 Blue cells = editable inputs 🟢 Green cells = live outputs (read only) ⚠ Password to unlock other sheets: NoDice2026
B4: 1. DEAL STRUCTURE | E4: LIVE OUTPUTS (auto-update) | H4: QUICK NAVIGATION
B5: Investment Amount (£) | C5: ='Investment Valuation 1'!D7 | E5: Pre-Money Valuation | F5: ='Investment Valuation 1'!C7 | H5: 📊 Investor Summary | I5: =HYPERLINK("#'Investor Summary'!A1","→ Open")
B6: EBITDA Multiple (×) | C6: ='Investment Valuation 1'!B7 | E6: Post-Money Valuation | F6: ='Investment Valuation 1'!E7 | H6: 💰 Cash Flow Forecast | I6: =HYPERLINK("#'Cash Flow Forecast'!A1","→ Open")
B7: Investor Equity % (auto — set by multiple) | C7: ='Investment Valuation 1'!G7 | E7: Founder Equity % (auto) | F7: ='Investment Valuation 1'!F7 | H7: 📋 Dividend & Distribution | I7: =HYPERLINK("#'Dividend & Distribution Model'!A1","→ Open")
B9: 2. SCENARIO SELECTION | E9: REVENUE & PROFIT | H9: 📈 Scenario Planning
B10: Active Scenario | C10: =Inputs!C6 | E10: Forecast Revenue (base) | F10: ='Base Case Forecast'!N6 | H10: 🏦 Investment Valuation | I10: =HYPERLINK("#'Investment Valuation 1'!A1","→ Open")
B11: ↑ Changes this cell updates entire model via Inputs!C6 | E11: Forecast Profit (base) | F11: ='Dividend & Distribution Model'!B14
B12: Conservative Growth % | C12: ='Scenario Planning'!B93 | E12: Active Growth Rate (auto) | F12: =Inputs!C7 | H12: 📈 Scenario Planning | I12: =HYPERLINK("#'Scenario Planning'!A1","→ Open")
B13: Optimistic Growth % | C13: ='Scenario Planning'!B95 | E13: Profit Margin % | F13: ='Base Case Forecast'!N17 | H13: ⬇ Downside Scenario | I13: =HYPERLINK("#'Downside Scenario'!A1","→ Open")
B15: 3. DIVIDEND & RETURNS | E15: INVESTOR RETURN OUTPUTS | H15: 📉 Investor Returns
B16: Preferred Return % (default 8%) | C16: ='Dividend & Distribution Model'!B23 | E16: Preferred Return (£) | F16: ='Dividend & Distribution Model'!B28 | H16: 💸 Dividend & Distribution | I16: =HYPERLINK("#'Dividend & Distribution Model'!A1","→ Open")
B17: A-Share Priority — Quarterly (£) | C17: ='Dividend & Distribution Model'!B17 | E17: A-Share Priority — Annual (£) | F17: ='Dividend & Distribution Model'!B18 | H17: 📊 Investor Returns sheet | I17: =HYPERLINK("#'Investor Returns'!A1","→ Open")
B18: Remaining Profit Pool | C18: ='Dividend & Distribution Model'!B29 | E18: Total → Investor (Year 1) | F18: ='Dividend & Distribution Model'!B41 | H18: 📋 Base Case Forecast | I18: =HYPERLINK("#'Base Case Forecast'!A1","→ Open")
B19: Total → Investor (Year 1) | C19: ='Dividend & Distribution Model'!B41 | E19: Cash-on-Cash Return (Year 1) | F19: ='Dividend & Distribution Model'!B41/'Investment Valuation 1'!D7 | H19: 🔑 Inputs Hub | I19: =HYPERLINK("#'Inputs'!A1","→ Open")
B20: Simple Payback Period | C20: ='Investment Valuation 1'!D7/'Dividend & Distribution Model'!B41 | E20: 5-Year IRR (estimated) | F20: ='Investor Returns'!B36 | H20: 📣 Marketing / Google Ads | I20: =HYPERLINK("#'Google Budget'!A1","→ Open")
B22: 4. COST & CASH ASSUMPTIONS | E22: CASH POSITION OUTPUTS | H22: 💵 Base Case Forecast
B23: Director Salary — Annual (£) | C23: ='Base Case Forecast'!B54 | E23: Peak Cash Balance | F23: =MAX('Cash Flow Forecast'!B30:M30) | H23: 💵 Cash Flow Forecast | I23: =HYPERLINK("#'Cash Flow Forecast'!A1","→ Open")
B24: Fixed Cost Uplift % | C24: ='Base Case Forecast'!B53 | E24: Minimum Cash Balance | F24: =MIN('Cash Flow Forecast'!B30:M30) | H24: 📉 Downside Scenario | I24: =HYPERLINK("#'Downside Scenario'!A1","→ Open")
B25: Variable Cost Cap (% of rev) | C25: ='Base Case Forecast'!B55 | E25: 3-Month Reserve Target | F25: =('Base Case Forecast'!N8+'Base Case Forecast'!N9+'Base Case Forecast'!N13+'Base Case Forecast'!B54)/12*3 | H25: 📅 Monthly Summary | I25: =HYPERLINK("#'Monthly Summary'!A1","→ Open")
B26: Rent % of Quarterly Revenue | C26: ='Base Case Forecast'!B56 | E26: Cash Safety Floor (model) | F26: ='Cash Flow Forecast'!G39 | H26: 🔢 Capacity Model | I26: =HYPERLINK("#'Capacity Model'!A1","→ Open")
B27: Cash Safety Floor Target (£) | C27: ='Cash Flow Forecast'!G39 | E27: Annual Net VAT Payable (est.) | F27: ='Base Case Forecast'!N14 | H27: 💻 Tech Optimisation | I27: =HYPERLINK("#'Tech Optimisation'!A1","→ Open")
B29: 5. MARKETING SPEND | E29: MARKETING RETURNS | H29: 📣 Google Budget
B30: Google Ads — Weekly Budget (£) | C30: =Inputs!C56 | E30: Google Ads — Annual Budget | F30: ='Google Budget'!F63 | H30: 🌐 Google Budget sheet | I30: =HYPERLINK("#'Google Budget'!A1","→ Open")
B31: Adjusted CPC (GA4 verified) | C31: ='Google Budget'!F65 | E31: Annual Clicks (estimated) | F31: ='Google Budget'!F75 | H31: 📊 Marketing Budget | I31: =HYPERLINK("#'Marketing Budget'!A1","→ Open")
B32: Marketing ROAS (5.62× verified) | C32: ='Google Budget'!F87 | E32: Net Profit from Ads | F32: ='Google Budget'!F81 | H32: 🎯 Events Strategy | I32: =HYPERLINK("#'Events Strategy'!A1","→ Open")
B34: 6. 5-YEAR PROJECTION | E34: LONG-TERM OUTPUTS | H34: 📅 Investor Returns (5yr)
B35: Annual Growth Rate (Years 2–5) | C35: ='Investor Returns'!B47 | E35: 5-Year IRR | F35: ='Investor Returns'!B36 | H35: 📉 Investor Returns sheet | I35: =HYPERLINK("#'Investor Returns'!A1","→ Open")
A36: The EBITDA multiplier controls the entire deal valuation. Change Founder Tools!C5 to test alternative pricing (current 0.76× = distressed entry). | B36: Year 5 Exit Multiple (×) | C36: ='Investor Returns'!B48 | E36: Year 5 Investor Exit Value | F36: ='Investor Returns'!B33 | H36: 📊 Investment Rounds | I36: =HYPERLINK("#'Investment Rounds Model'!A1","→ Open")
A38: ★ All blue cells update the full model in real time. Green cells are read-only outputs. Password to unlock other sheets: NoDice2026 · No Dice Borough LTD · Confidential
A41: 🔐 FOUNDER TOOLS — EBITDA Multiplier & Valuation Control (Password protected — investor password does not apply here)
A42: The EBITDA multiplier controls the entire deal valuation. Changing it updates pre-money, post-money, equity %, investor returns and all downstream calculations automatically. To adjust: unprotect the "Founder Tools" sheet using password ND_FOUNDER_2026, change the multiplier, then re-protect.
B43: A Shares (50% equity > 5% threshold) | C43: ='Investment Valuation 1'!B7 | E43: A/B Threshold (5% of post-money) | F43: £7,900 | H43: → Founder Tools sheet | I43: =HYPERLINK("#'Founder Tools'!A1","→ Open")
B44: 3.0× → | C44: ='Investment Valuation 1'!A7*3+'Investment Valuation 1'!D7 | E44: 3.5× → | F44: ='Investment Valuation 1'!A7*3.5+'Investment Valuation 1'!D7 | H44: Scenarios below show post-money at each multiple
B45: 4.0× → | C45: ='Investment Valuation 1'!A7*4+'Investment Valuation 1'!D7 | E45: 4.5× → | F45: ='Investment Valuation 1'!A7*4.5+'Investment Valuation 1'!D7 | H45: (All post-money = EBITDA × multiple + £150k investment)
B47: Current Investor Share Class | C47: A Shares (31.79% > 10% threshold) | E47: A/B Threshold (10% of post-money) | F47: £47,182
B48: ⚡ A Shares = investor equity ≥10% · voting rights included | B Shares = <10% · non-voting · all economic rights identical

Sheet Founder Tools
A1: 🔐 FOUNDER TOOLS — NO DICE BOROUGH LTD · EBITDA Multiplier & Valuation Control · Password: ND_FOUNDER_2026
A2: ⚠ This sheet is for the founder only. The EBITDA multiplier is the only editable cell. All other values update automatically. Investor password (NoDice2026) does NOT unlock this sheet.
B4: EBITDA MULTIPLE — THE ONLY EDITABLE CELL | E4: LIVE VALUATION OUTPUT (auto-updates)
B5: EBITDA Multiple (×) | C5: 0.8592 | E5: EBITDA 2025 (verified) | F5: ='Monthly Summary'!I15
B6: ↑ Change this value to update the entire model. Try: 0.5× · 0.86× · 1.0× · 1.5× · 2.0× | E6: Pre-Money Valuation | F6: ='Investment Valuation 1'!C7
E7: Post-Money Valuation | F7: ='Investment Valuation 1'!E7
E8: Investor Equity % | F8: ='Investment Valuation 1'!G7
E9: Founder Equity % | F9: ='Investment Valuation 1'!F7
B11: MULTIPLE SCENARIO COMPARISON — All figures live (update when you change cell C5)
B12: Multiple | C12: Pre-Money | D12: Post-Money | E12: Inv. Equity % | F12: Founder Equity % | G12: Total→Investor | H12: Cash-on-Cash | I12: Payback
B13: 0.5× | C13: 0.5× | D13: 45975 | E13: 124975 | F13: 0.6321 | G13: 0.3679 | H13: ='Dividend & Distribution Model'!B41 | I13: =79000/'Dividend & Distribution Model'!B41
B14: 0.86× ← CURRENT | C14: 0.86× | D14: 79077 | E14: 158077 | F14: 0.4998 | G14: 0.5002 | H14: ='Dividend & Distribution Model'!B41 | I14: =79000/'Dividend & Distribution Model'!B41
B15: 1.0× | C15: 1.0× | D15: 91950 | E15: 170950 | F15: 0.4621 | G15: 0.5379 | H15: ='Dividend & Distribution Model'!B41 | I15: =79000/'Dividend & Distribution Model'!B41
B16: 1.5× | C16: 1.5× | D16: 137925 | E16: 216925 | F16: 0.3642 | G16: 0.6358 | H16: ='Dividend & Distribution Model'!B41 | I16: =79000/'Dividend & Distribution Model'!B41
B17: 2.0× | C17: 2.0× | D17: 183900 | E17: 262900 | F17: 0.3005 | G17: 0.6995 | H17: ='Dividend & Distribution Model'!B41 | I17: =79000/'Dividend & Distribution Model'!B41
B19: KEY IMPACT OF MULTIPLIER CHANGE — What changes, what stays the same
B20: ✓ Changes: | C20: Pre-money valuation · Post-money valuation · Investor equity % · Founder equity %
B21: ✓ Changes: | C21: All equity-based calculations in Investor Returns and DDM sheets
B22: ✗ Stays same: | C22: EBITDA profit figures · Revenue forecasts · Operating costs · Cash flow
B23: ✗ Stays same: | C23: Preferred return (£0 — pure pro-rata) · A-share priority (£0 — pure pro-rata) — both removed
B24: ⚠ Note: | C24: Changing the multiple changes the investor's equity stake — discuss with investor before finalising
A26: ★ FOUNDER ONLY · Password: ND_FOUNDER_2026 · Investor password (NoDice2026) will NOT unprotect this sheet · No Dice Borough Ltd · Confidential

Sheet Investor Summary
A1: NO DICE BOROUGH LTD · INVESTOR SUMMARY
A2: =UPPER("Active Scenario: "&Inputs!C6&" · Revenue Growth: "&TEXT(Inputs!C7,"0%")&" · Trading Period: May 2026 – Apr 2027") | J2: =TEXT(TODAY(),"DD MMM YYYY")
A3: ⭐ TOP 3 INVESTMENT HIGHLIGHTS
A4: =" 1. £"&TEXT('Dividend & Distribution Model'!B41,"#,##0")&" Year 1 investor return · "&TEXT('Dividend & Distribution Model'!B41/79000,"0.0%")&" cash-on-cash on £79,000 invested — pure pro-rata distribution" | E4: =" "&TEXT('Dividend & Distribution Model'!B41/79000,"0.0%")&" cash-on-cash on £79,000 invested — pure pro-rata, all shareholders paid by equity %"
A5: 2. Proven Borough Market venue | E5: £741,644 verified 2025 revenue · 90,475 venue page views · 58% organic search share — proven trading history
A6: 3. Founder-controlled growth plan | E6: DJ nights, corporate bookings & SEO programme — upside drivers not in the base case (£124k operating profit)
B9: 🏢 INVESTMENT SNAPSHOT | E9: 📊 FINANCIAL PERFORMANCE | H9: 💰 INVESTOR RETURNS | K9: 🏦 CASH & LIQUIDITY
B10: Investment Required | C10: ='Investment Valuation 1'!C13 | E10: 2025 Actual Revenue | F10: ='Monthly Summary'!C15 | H10: Year 1 Total Return | I10: ='Dividend & Distribution Model'!B41 | K10: Peak Cash Balance | L10: =MAX('Cash Flow Forecast'!B30:M30)
B11: Investor Equity | C11: ='Investment Valuation 1'!C19 | E11: Forecast Revenue | F11: ='Base Case Forecast'!N6 | H11: Preferred Return | I11: ='Dividend & Distribution Model'!B28 | K11: Minimum Cash Balance | L11: =MIN('Cash Flow Forecast'!B30:M30)
B12: Founder Equity | C12: ='Investment Valuation 1'!C18 | E12: Revenue Growth vs 25 | F12: =Inputs!C7 | H12: Pro-Rata Dividend | I12: ='Dividend & Distribution Model'!B30 | K12: Month of Lowest Cash | L12: ='Cash Flow Forecast'!G41
B13: Pre-Money Valuation | H13: Cash-on-Cash (Yr 1)
B14: Post-Money Valuation | E14: Forecast Profit | F14: ='Dividend & Distribution Model'!B14 | H14: Payback Period | K14: Cash Buffer vs Floor
B15: EBITDA (2025 actual) | E15: Op Costs (excl sal) | F15: ='Base Case Forecast'!N11 | H15: 5-Year IRR | K15: Cash-Positive Months
B16: Valuation Multiple | E16: Director Salary | F16: ='Base Case Forecast'!B54 | H16: Investor Equity % | K16: Day 1 Cash Position
B17: Share Class
B18: A/B Threshold | H18: 📣 MARKETING ENGINE (Google Ads — Base Case)
B19: Operating Profit | E19: ='Dividend & Distribution Model'!B26 | H19: Annual Ad Budget | K19: ='Google Budget'!F63
B20: − A-Share Priority Return | E20: =-'Dividend & Distribution Model'!B27 | H20: Weekly Budget | K20: ='Google Budget'!D62
B21: − Investor Preferred Ret. | E21: =-'Dividend & Distribution Model'!B28 | H21: Adjusted CPC (verified) | K21: ='Google Budget'!F65
B22: = Remaining Pool | E22: ='Dividend & Distribution Model'!B29 | H22: Annual Clicks | K22: ='Google Budget'!F75
B23: Investor Dividend | E23: ='Dividend & Distribution Model'!B30 | H23: Actual Paying Customers | K23: ='Google Budget'!F77
B24: Founder Dividend | E24: ='Dividend & Distribution Model'!B31 | H24: Incremental Revenue | K24: ='Google Budget'!F79
B25: ━ Total → Investor | E25: ='Dividend & Distribution Model'!B41 | H25: Net Profit from Ads | K25: ='Google Budget'!F81
B26: ━ Total → Founder | E26: ='Dividend & Distribution Model'!B40 | H26: Marketing ROAS | K26: ='Google Budget'!F87
B29: May | C29: Jun | D29: Jul | E29: Aug | F29: Sep | G29: Oct | H29: Nov | I29: Dec | J29: Jan | K29: Feb | L29: Mar | M29: Apr | N29: Founder Repayment | O29: ='Dividend & Distribution Model'!B27
B30: ='Base Case Forecast'!B6 | C30: ='Base Case Forecast'!C6 | D30: ='Base Case Forecast'!D6 | E30: ='Base Case Forecast'!E6 | F30: ='Base Case Forecast'!F6 | G30: ='Base Case Forecast'!G6 | H30: ='Base Case Forecast'!H6 | I30: ='Base Case Forecast'!I6 | ... M30: ='Base Case Forecast'!M6 | N30: Preferred Return | O30: ='Dividend & Distribution Model'!B28
B31: ='Base Case Forecast'!B16 | C31: ='Base Case Forecast'!C16 | D31: ='Base Case Forecast'!D16 | E31: ='Base Case Forecast'!E16 | F31: ='Base Case Forecast'!F16 | G31: ='Base Case Forecast'!G16 | H31: ='Base Case Forecast'!H16 | I31: ='Base Case Forecast'!I16 | ... M31: ='Base Case Forecast'!M16 | N31: Investor Dividend | O31: ='Dividend & Distribution Model'!B30
N32: Founder Dividend | O32: ='Dividend & Distribution Model'!B31
A33: Cumulative Cash Balance | B33: ='Cash Flow Forecast'!B30 | C33: ='Cash Flow Forecast'!C30 | D33: ='Cash Flow Forecast'!D30 | E33: ='Cash Flow Forecast'!E30 | F33: ='Cash Flow Forecast'!F30 | G33: ='Cash Flow Forecast'!G30 | H33: ='Cash Flow Forecast'!H30 | I33: ='Cash Flow Forecast'!I30 | ... M33: ='Cash Flow Forecast'!M30 | N33: 3-Month Reserve Target | O33: 142334
A34: ★ RESERVE NOTE: Red = below 2-month minimum. Amber = above 2-month, below 3-month target. Green = 3-month target met. The £11,022 working-capital residual + early-month trading cash flow fund the reserve. Year 1 distributions are payable from operating profit per the pure pro-rata waterfall above.
B54: 📈 KEY GROWTH DRIVERS | H54: ⚠ RISKS & MITIGATIONS
B55: ▶ Borough Market venue — 90,475 page views (2025) | H55: Marketing variability | J55: ✓ Conservative CPC/CVR; 3 verified scenarios modelled
B56: ▶ December peak month: £144k forecast revenue | H56: Seasonality (May–Jul) | J56: ✓ Cash buffer built in; deposit covers first 3 months
B57: ▶ DJ nights & live events (Fri/Sat) | H57: Cost overruns | J57: ✓ 30% hard cap on variable costs in all scenarios
B59: ▶ Corporate & private hire bookings | H59: Competitor risk | J59: ✓ Plonk IP and goodwill acquired; strong SEO moat
B60: ▶ Gaming repricing uplift (+£1 per game) | H60: Cash dip (Feb) | J60: ✓ Largest rent payment (Nov+Dec+Jan); modelled explicitly
B61: ▶ Organic search: 58% of all traffic — zero cost | H61: Profit concentration | J61: ✓ December = 28% of profit; mitigated by events programme
A63: ="No Dice Borough LTD · Investor Summary · All figures live-linked to financial model · Generated: "&TEXT(TODAY(),"DD MMM YYYY")&" · Confidential"
A66: 📋 INVESTMENT CASE & MARKET CONTEXT — Valuation rationale & investment thesis
A67: Market data: CLFI M&A Monitor H1 2025 · Houlihan Lokey Hospitality H1 2025 · UKHospitality · Moore Kingston Smith 2025 · UK Government Budget Factsheet
A69: A. MARKET BENCHMARKS | H69: HOW THIS DEAL IS POSITIONED
A70: UK mid-market average (all sectors) | E70: ~5.3× | H70: ✓ Above distressed range — not priced as a troubled asset
A71: Hospitality & leisure sector avg | E71: ~4.1× | H71: ✓ In line with hospitality sector — defensible sector benchmark
A72: Small single-site (<£200k EBITDA) | E72: ~2–4× | H72: ✓ At top of small-site range — reflects Borough Market premium
A73: Distressed / liquidation range | E73: ~2–3× | H73: ✓ Entry compensates investors for reopening risk with upside
A74: No Dice Borough — this deal | E74: 3.5× | H74: ✓ Investor-aligned: preferred return + equity participation
A75: → 3.5× entry reflects distressed acquisition pricing — below the hospitality sector average (4.1×) and well below the broader UK mid-market (5.3×). Priced to reflect reopening risk with equity upside for the investor.
A77: B. SECTOR REALITY (honest context) | H77: INVESTOR IMPLICATION
A78: ▪ Employer NICs: 13.8% → 15% (April 2025) | H78: → Full cost increase built into 2025 actual wage base — not a future risk
A79: ▪ NMW: £11.44 → £12.21/hr (+6.7%, April 2025) | H79: → Wage inflation already in the model — no optimistic assumption applied
A80: ▪ Business rates relief: 75% → 40% (2025/26) | H80: → Higher rates cost baked into forecast — baseline is post-shock, not pre
A81: ▪ ~2 UK hospitality closures per day (2025) | H81: → Sector distress creates realistic acquisition pricing — not a red flag
A82: ▪ Consumer shift: experience-led, lower alcohol spend | H82: → No Dice Borough format is aligned with this trend — activity-first model
A83: ▪ PE cautious on single-country consumer exposure | H83: → Less institutional competition at this deal size — wider margin for terms
A84: → Sector conditions favour efficient, cash-generative and differentiated operators. All headwinds are modelled — this is not a pre-cost-shock baseline.
A86: C. WHY THIS BUSINESS IS DIFFERENT — Asset-specific strengths
A87: ▶ Proven revenue base — £741,644 verified 2025 actuals. Real trading history, not a projection. | H87: ▶ Google Ads engine — £0.32 CPC · 5.6× ROAS verified in GA4. Scalable paid acquisition.
A88: ▶ Borough Market SE1 — Prime Central London location. East London posting highest revenue growth 2025. | H88: ▶ December peak — £144k single-month forecast. 17% of annual revenue from one repeatable month.
A89: ▶ Experience-led format — Pool · ping pong · mini golf · DJ nights. Fastest-growing sub-sector. | H89: ▶ Gaming repricing upside — +£1 per game across all activities. Zero capex, immediate margin gain.
A90: ▶ Multiple revenue streams — Bar + activities + events + corporate hire. Not alcohol-dependent. | H90: ▶ DJ & events programme — Fri/Sat DJ nights + seasonal events on highest-footfall days.
A91: ▶ Brand IP acquired — Plonk trading name, customer data and goodwill. Not starting from zero. | H91: ▶ Corporate hire potential — Venue format suited to private bookings. Higher margin than walk-in.
A92: ▶ 90,475 venue page views — 2025 GA4 verified. 58% organic — zero paid acquisition cost. | H92: ▶ Low-alcohol alignment — Activity-led concept works sober. Less exposed to declining alcohol trend.
A94: D. HOW INVESTORS MAKE MONEY — Investment structure & return mechanics
A95: ★ Not a multiple expansion bet Returns are driven by operating cash flow — not by the valuation rising at exit. | H95: Distribution model: pure pro-rata on operating profit. No preferred return, no priority tiers — investor and founder receive 50/50 of operating profit.
A96: ▸ Cash-yielding from Day 1 Distributable profit generated from first full trading month. No waiting for an exit event. | H96: ▸ 28.97% equity participation Pro-rata share of remaining profit after preferred return and A-share priority return. Base case adds £40,830 on top.
A97: ▸ Payback via cash flow At base case: £62,000/yr investor return on £79,000 invested | H97: ▸ ~78.5% cash-on-cash Year 1 Total return £62,000 ÷ £79,000 invested. Investor and founder share operating profit 50/50.
A98: ▸ Upside is real but not required Marketing scale, corporate events, potential second site — all additive to the base case return. | H98: ▸ A-share priority return disclosed No Dice Bars Ltd (A-share holder) receives £44,000/yr priority equity return — fully modelled and disclosed. Investor preferred return comes first.
A99: ★ THE DEAL IN ONE LINE: A proven Borough Market experience venue, acquired at distressed pricing (3.5× EBITDA), with 8% guaranteed preferred return paid first, 28.97% equity, and payback driven by operating cash flow — not exit dependency. All headwinds modelled. Full A-share structure disclosed.
A100: Sources: CLFI M&A Monitor H1 2025 · Houlihan Lokey Hospitality H1 2025 · Moore Kingston Smith 2025 · UKHospitality Business Rates Analysis 2025 · UK Government Autumn Budget 2024 & 2025 · IBISWorld Pubs & Bars UK 2026
A103: 💷 INVESTOR RETURNS — SIMPLE BREAKDOWN · What you put in · What you own · What you earn
A104: Invest £79,000 for 50% ownership in a cash-generating London experience venue — with a working business and proven trading history.
A106: 1. WHAT YOU INVEST | H106: WHAT YOU OWN
A107: ▪ You invest | D107: £79,000 inc VAT — a single cash payment on Day 1 | H107: ▪ You own ~32% | K107: of every £1 of profit the business generates
A108: ▪ You receive | D108: ~32% equity stake in No Dice Borough Ltd | H108: ▪ You earn first | K108: 8% guaranteed annual return before others — £12,000/yr
A109: ▪ Share class | D109: B shares (non-voting) — standard investor structure | H109: ▪ You share profits | K109: Your ~32% of remaining pool adds further annual income
A110: ▪ Your shares are backed by | D110: A real, trading business with £741,644 verified revenue | H110: ▪ Your stake grows in value | K110: as the business grows — more profit = higher valuation
A111: ▪ This is equity | D111: Not a loan. You own part of the business. | H111: ▪ No exit required | K111: You earn income every year — no sale needed to benefit
A113: 2. HOW YOU GET PAID — 3 steps, in priority order
A114: STEP 1 | C114: Priority Return — You get paid first
A115: ▪ Every year, you receive 50% of operating profit as a pro-rata dividend (no preferred return, no tiers — same time as the founder)
A116: ▪ That is £12,000 per year — guaranteed before anything else is paid
A117: ▪ This is paid before the founding entity takes any distribution
A118: ▪ Even in a lower-profit year, you receive this first
A120: STEP 2 | C120: Share of Profits — Your ~32% equity earns more
A121: ▪ After Step 1 and the A-share priority (£44,000), remaining profit is split
A122: ▪ You receive ~32% of whatever is left in the pool
A123: ▪ At base case: ~£44,808 additional on top of your priority return
A124: ▪ More profit = more money for you at this step
A126: STEP 3 | C126: Ongoing Annual Income — This repeats every year
A127: ▪ Steps 1 and 2 happen every year the business is profitable
A128: ▪ You do not need to sell your shares to receive income
A129: ▪ The business is designed to generate cash from its first trading year
A130: ▪ Returns increase as the business grows
A133: 3. WHAT YOU EARN — Three scenarios, all showing positive returns
A134: Conservative (cautious) | E134: Base Case (expected) | I134: Optimistic (upside)
A135: Revenue assumption
A136: Annual investor return
A137: As % of £150k invested
A138: Priority return
A139: Equity share
...

Sheet Investment Valuation 1
A1: ⚠ EDIT ONLY YELLOW CELLS — ALL OTHER CELLS ARE LOCKED AND PROTECTED
A2: NO DICE BOROUGH — INVESTMENT VALUATION | SHEET 1
A3: No Dice Borough LTD | Purchase from Liquidation | Prepared for Investor & Stakeholder Discussions | Confidential
A5: SECTION 1 — HEADLINE VALUATION SUMMARY
A6: Annual EBITDA | B6: EBITDA × 3.5 | C6: Pre-Money Value | D6: + Investment | E6: Post-Money Value | F6: Founder Retains | G6: Investor Receives
A7: ='Monthly Summary'!I15 | B7: ='Founder Tools'!C5 | C7: =A7*B7 | D7: 79000 | E7: =C7+D7 | F7: =C7/E7 | G7: =1-F7
A9: SECTION 2 — VALUATION BUILD
A10: Component | C10: £ Amount | E10: Cumulative | G10: Notes
A11: 2025 Annual Profit (EBITDA) | C11: ='Monthly Summary'!I15 | E11: ='Monthly Summary'!I15 | G11: Verified 52-week trading profit, exc. VAT
A12: × 0.86 EBITDA Multiple — Pre-Money (distressed entry) | C12: =C11*B7 | E12: =C11 | G12: 0.86× reflects distressed acquisition pricing. Sectoral comp is 4.1×.
A13: + £79,000 Investment | C13: 79000 | E13: =C11+C12 | G13: Investor capital injected into business on reopening Day 1 (May 2026). Inc VAT.
A14: POST-MONEY VALUATION | C14: =C13+C12 | E14: =C13+C12 | G14: Total company value at close — basis for shareholding
A16: SECTION 3 — SHAREHOLDING CALCULATION
A17: Party | C17: Shareholding % | E17: Basis | G17: Notes
A18: No Dice Borough LTD (Founder) | C18: =C12/C14 | E18: Pre-money ÷ Post-money (updates with multiple) | G18: Founder retains 50% controlling stake
A19: Investor | C19: =C13/C14 | E19: £70,000 ÷ Post-money valuation (updates with multiple) | G19: Investor — 50% equity. A Shares (≥5% threshold = £7,900). Below £7,900 = B Shares (economic only).
A20: TOTAL | C20: =C18+C19 | E20: Sum of both parties = 100%
A21: 📋 SHARE CLASS NOTE: At £79,000 investment (50% equity), the investor holds A Shares (full voting rights). A/B threshold is £7,900 (5% of post-money). Below £7,900 → B Shares (economic only).
A22: SECTION 4 — USE OF INVESTMENT FUNDS (£79,000 inc VAT)
A23: Item | B23: VAT | C23: Amount (inc VAT) | D23: % of Investment
A24: Hardware — Purchased from Liquidators | B24: inc VAT | C24: 24000 | D24: =C24/C13 | E24: Physical bar & kitchen equipment. Operational from Day 1.
A25: IP License Fee | B25: inc VAT | C25: 12000 | D25: =C25/C13 | E25: One-off licensing fee paid to No Dice Bars LTD — grants indefinite use of the Plonk name. No Dice Bars LTD also runs online sales campaigns and platform maintenance under an ongoing commission, replacing the old Design My Night bookings provider. See the Plonk tab for full IP & Licensing breakdown.
A26: Stock & Operational Setup | B26: inc VAT | C26: 4900 | D26: =C26/C13 | E26: Itemised £4,900 — opening alcohol stock, software subs, internet, cleaning restart, business rates (first month, VAT-exempt) + alcohol licence change (VAT-exempt). See breakdown rows 33-49.
A27: Landlord — 3 Months Rent in Advance | B27: inc VAT | C27: 27078 | D27: =C27/C13 | E27: 3 months rent paid up front — covers May, Jun, Jul 2026 at the contractual 15% of 2025 turnover rate. NO deposit required. From August 2026 rent reverts to 15% of actual quarterly turnover (variable, scales with trading).
A28: Working Capital Buffer | B28: — | C28: =C13-C24-C25-C26-C27 | D28: =C28/C13 | E28: Staged into business per cash flow model. Covers early trading before revenue covers costs.
A29: TOTAL INVESTMENT DEPLOYED | C29: =SUM(C24:C28) | D29: =C29/C13 | E29: All funds deployed on reopening day or staged per cash flow forecast.
A32: SECTION 4a — STOCK & OPERATIONAL SETUP DETAIL (£4,900 — inc VAT items + VAT-exempt regulatory costs)
A33: Item | B33: VAT basis | C33: Amount | D33: % of £4,900 | E33: Note
A34: Alcohol stock (opening fill) | B34: inc VAT | C34: 1500 | D34: =C34/4900 | E34: Wines, spirits, beer for Day 1 trading
A35: Soft drinks, mixers & non-alcohol stock | B35: inc VAT | C35: 300 | D35: =C35/4900 | E35: Mixers, juices, soft drinks opening fill
A36: Ice supplies (first delivery) | B36: inc VAT | C36: 30 | D36: =C36/4900 | E36: Daily delivery — first delivery only
A37: Cleaning contracts restart | B37: inc VAT | C37: 250 | D37: =C37/4900 | E37: Deep clean + first month commercial cleaning
A38: Internet — Starlink / BT Business (setup + 1 mo) | B38: inc VAT | C38: 300 | D38: =C38/4900 | E38: Hardware setup + first month connectivity
A39: App & booking platform setup | B39: inc VAT | C39: 200 | D39: =C39/4900 | E39: Plonk Golf booking + delivery app integrations
A40: Xero accounting (3 months) | B40: inc VAT | C40: 75 | D40: =C40/4900 | E40: £25/mth × 3 — cloud accounting
A41: Rota Cloud — staff scheduling (3 months) | B41: inc VAT | C41: 75 | D41: =C41/4900 | E41: £25/mth × 3 — rota & timesheet system
A42: Google Workspace (3 months) | B42: inc VAT | C42: 75 | D42: =C42/4900 | E42: Email + Drive + collab tools, 2 users
A43: Spotify Business (3 months) | B43: inc VAT | C43: 60 | D43: =C43/4900 | E43: £20/mth × 3 — bar music licensing
A44: Supplier contract deposits | B44: inc VAT | C44: 135 | D44: =C44/4900 | E44: Water, refuse, gas/electricity meter deposits
A45: Business rates (first month) | B45: VAT-exempt | C45: 1800 | D45: =C45/4900 | E45: First month UK business rates — Southwark Council, post-relief
A46: Alcohol licence change (DPS) | B46: VAT-exempt | C46: 100 | D46: =C46/4900 | E46: Designated Premises Supervisor change fee — Southwark Licensing
A47: TOTAL — STOCK & OPERATIONAL SETUP | C47: =SUM(C34:C46) | D47: =C47/4900 | E47: Cross-check: must equal C26 (£4,900) on the headline use-of-funds line.
A49: ★ Mix of inc-VAT items (alcohol, software subs, internet, cleaning) and VAT-exempt regulatory costs (business rates, alcohol licence). The two VAT-exempt items are pre-trading obligations — first month rates due to Southwark Council before opening, alcohol licence change required before trading begins.
A52: SECTION 4b — HARDWARE FROM LIQUIDATORS DETAIL (£20,000 ex VAT · £24,000 inc VAT)
A53: Item | B53: VAT basis | C53: Amount (ex VAT) | D53: % of £20,000 | E53: Note
A54: Mini golf course | B54: ex VAT | C54: 4000 | D54: =C54/20000 | E54: Holes, putting surfaces, course fittings & feature props
A55: Bar equipment across site | B55: ex VAT | C55: 10000 | D55: =C55/20000 | E55: Beer lines, fridges, glasswash, bar tops, taps, ice machine, POS hardware
A56: Wet stock consumables & tools | B56: ex VAT | C56: 2000 | D56: =C56/20000 | E56: Glassware, cleaning chemicals, repair tools, hand-trolleys, small wares
A57: Arcade machines, furniture & fittings | B57: ex VAT | C57: 4000 | D57: =C57/20000 | E57: Arcade cabinets, pool tables, board game stock, seating, lighting fittings
A59: SUBTOTAL — ex VAT | C59: =SUM(C54:C57) | D59: =C59/20000 | E59: Sum of the four equipment categories.
A60: VAT (20%) | C60: =C59*0.2 | E60: 20% UK standard rate VAT applied to the £20,000 ex-VAT subtotal.
A61: TOTAL — HARDWARE FROM LIQUIDATORS (inc VAT) | C61: =C59+C60 | E61: Cross-check: must equal C24 (£24,000) on the headline use-of-funds line.
A63: ★ All four equipment categories purchased from the liquidation auction at distressed pricing — operational from Day 1 of reopening.

Sheet Investment Rounds Model
A1: NO DICE BOROUGH LTD — INVESTMENT STRUCTURE MODEL | Share Classes · Dilution · Buyback · Returns
A2: ⚠ Yellow cells are editable inputs. All other cells are formula-driven. Live-linked to Investment Valuation 1 and Base Case Forecast.
A4: SECTION 1 — SHARE CLASS STRUCTURE
A5: Share Class | B5: Holder | C5: Voting Rights | D5: Economic Rights | E5: Transferability | F5: Drag-Along | G5: Tag-Along | H5: Anti-Dilution | I5: Notes
A6: A Shares | B6: No Dice Borough LTD (Founder / Elliot Scott) | C6: ✓ Full voting | D6: ✓ Full economic | E6: Restricted — founder consent required | F6: ✓ Can drag investors | G6: ✗ No tag-along | H6: N/A — protected class | I6: Ordinary shares with full control rights. Founder holds all A shares.
A7: B Shares | B7: Investor(s) | C7: ✗ No voting rights | D7: ✓ Full economic | E7: Restricted — board approval | F7: ✓ Subject to drag | G7: ✓ Tag-along on exit | H7: ✓ Broad-based weighted avg | I7: Preference shares, economic rights only. Issued exclusively to investors.
A8: ⚡ A/B SHARE THRESHOLD: Investors holding ≥5% of post-money (£7,900+) hold A Shares (voting rights). Below 5% → B Shares (economic rights only).
A9: Investment Amount | B9: Equity % | C9: Share Class | D9: Voting Rights | E9: Economic Rights
A10: ✓ Full economic
A11: £7,900 | B11: 5.00% | C11: ← A/B THRESHOLD | H11: Gain / (Loss) | I11: Status
A12: £10,000 | B12: 6.33% | C12: A Shares | D12: ✓ Full voting | E12: ✓ Full economic | H12: =ROUND('Investment Valuation 1'!C12*'Investment Valuation 1'!C18,2) | I12: Founder — controlling shareholder
A13: £25,000 | B13: 15.82% | C13: A Shares | D13: ✓ Full voting | E13: ✓ Full economic | H13: =ROUND('Investment Valuation 1'!C12*'Investment Valuation 1'!C19-'Investment Valuation 1'!C13,2) | I13: Seed investor — B shares, economic rights only
A14: £50,000 | B14: 31.65% | C14: A Shares | D14: ✓ Full voting | E14: ✓ Full economic | H14: =H12+H13 | I14: ✓ OK
A15: £79,000 | B15: 50.00% | C15: A Shares | D15: ✓ Full voting | E15: ✓ Full economic
A18: Founder Ownership % | B18: ='Investment Valuation 1'!C18
A19: Investor Ownership % | B19: ='Investment Valuation 1'!C19
A20: Voting Control | B20: 50/50 split — Founder and Investor both hold A Shares (≥5% threshold each)
A21: Total Shares in Issue | B21: =C14
A22: Founder Shares (A) | B22: =C12
A23: Investor Shares (B) | B23: =C13
A24: Pre-Money Valuation | B24: ='Investment Valuation 1'!C12
A25: Post-Money Valuation | B25: ='Investment Valuation 1'!C14
A26: Ownership Validation | B26: ✓ OK
A29: SECTION 4 — DILUTION MODEL | New rounds are B shares only | Toggle founder participation below
A30: INPUTS — Round 2 parameters
A31: Founder Participates in Round 2? | B31: No | C31: If Yes → Founder invests pro-rata to maintain %. If No → Founder dilutes.
A32: New Investment (Round 2) — £ | B32: 1000000 | C32: New cash injected. Issued as B shares only.
A33: Pre-Money Valuation — Round 2 | B33: 2000000 | C33: Agreed pre-money valuation at Round 2. Edit this cell.
A34: Founder Top-Up (if participates) | B34: 0 | C34: Amount founder invests if toggle = Yes. Set to 0 if No.
A36: DILUTION CALCULATIONS
A37: Metric | B37: Round 1 (Seed) | C37: Round 2 (New) | D37: Change | E37: Notes
A38: Pre-Money Valuation | B38: ='Investment Valuation 1'!C12 | C38: =B33 | D38: =C38-B38 | E38: Agreed company value before new money enters
A39: New Investment | B39: ='Investment Valuation 1'!C13 | C39: =B32 | D39: =C38-B38 | E39: Cash injected in this round (B shares)
A40: Post-Money Valuation | B40: ='Investment Valuation 1'!C14 | C40: =B33+B32+IF(B31="Yes",B34,0) | D40: =C38-B38 | E40: Pre-money + total investment including founder top-up
A41: Founder Ownership % | B41: ='Investment Valuation 1'!C18 | C41: =IF(B31="Yes",('Investment Valuation 1'!C18*B33+B34)/(B33+B32+B34),'Investment Valuation 1'!C18*B33/(B33+B32)) | D41: =C38-B38 | E41: Dilutes if no participation; maintained if founder tops up pro-rata
A42: Investor (R1) Ownership % | B42: ='Investment Valuation 1'!C19 | C42: ='Investment Valuation 1'!C19*B33/(B33+B32+IF(B31="Yes",B34,0)) | D42: =C38-B38 | E42: R1 investor always dilutes proportionally by new money
A43: New Investor (R2) Ownership % | B43: 0% | C43: =B32/(B33+B32+IF(B31="Yes",B34,0)) | D43: =C38-B38 | E43: New B shares issued to Round 2 investor
A44: OWNERSHIP TOTAL (must = 100%) | B44: =B41+B42 | C44: =C41+C42+C43 | E44: =IF(ABS(C44-1)<0.001,"✓ Valid — sums to 100%","✗ ERROR — check inputs")
A47: SECTION 5 — PRE-EMPTION RIGHTS MODEL
A48: The Founder holds statutory pre-emption rights on all future share issuances. If the Founder exercises these rights in a new round, they invest pro-rata to maintain their ownership percentage. If waived, the Founder dilutes proportionally with all other existing shareholders. B shares issued in future rounds carry no voting rights regardless of holder.
A49: Scenario | B49: Founder Exercises? | C49: Founder % Maintained | D49: Founder Investment Required | E49: Outcome
A50: Exercises rights (maintains %) | B50: Yes | C50: ='Investment Valuation 1'!C18 | D50: =B32*'Investment Valuation 1'!C18/(1-'Investment Valuation 1'!C18) | E50: Founder invests pro-rata. Ownership % preserved. New money dilutes R1 investor only.
A51: Waives rights (dilutes normally) | B51: No | C51: ='Investment Valuation 1'!C18*B33/(B33+B32) | D51: — | E51: Founder dilutes alongside R1 investor. No cash required. Control maintained via A shares.
A54: SECTION 6 — BUYBACK MECHANISM | Inputs below drive the scenarios table
A55: BUYBACK INPUTS
A56: EBITDA for Buyback Calculation | B56: ='Dividend & Distribution Model'!B14 | C56: Live-linked to Base Case Forecast Year 1 profit after salary. Edit to override.
A57: Exit / Buyback Multiple | B57: 4 | C57: 3.5× entry (distressed acquisition). Hospitality sector average: 4.1× (Houlihan Lokey H1 2025). UK mid-market: 5.3×.
A58: Investor Ownership % (for buyback) | B58: ='Investment Valuation 1'!C19 | C58: Live-linked to current investor equity. Adjust if round 2 has occurred.
A60: BUYBACK CALCULATION
A61: Company Valuation | B61: =IFERROR(RATE(5,0,-('Investment Valuation 1'!C13),ROUND(B56*B57*B58,2)),0) | C61: EBITDA × Multiple
A62: Investor Buyback Price | B62: =ROUND(B56*B57*B58,2) | C62: Valuation × Investor Ownership %
A63: Founder Retains (post-buyback) | B63: =ROUND(B56*B57*(1-B58),2) | C63: Valuation × Founder Ownership % — value accruing to founder
A64: Original Investment | B64: ='Investment Valuation 1'!C13 | C64: Capital invested by investor
A65: Investor Return Multiple (MoM) | B65: =ROUND(B56*B57*B58/'Investment Valuation 1'!C13,2) | C65: Buyback price ÷ original investment
A66: Investor IRR (approx, 5-year) | B66: =IFERROR(RATE(5,0,-'Investment Valuation 1'!C13,ROUND(B56*B57*B58,2)),0) | C66: Approximate annualised return over 5-year hold
A69: SECTION 7 — BUYBACK SCENARIOS (EBITDA × multiple, investor return by scenario)
A70: Scenario | B70: EBITDA | C70: Multiple | D70: Valuation | E70: Investor Value | F70: Investment In | G70: Investor MoM | H70: Investor IRR (5yr) | I70: Status
A71: Conservative Exit | B71: =B56 | C71: 3 | D71: =ROUND(B71*C71,2) | E71: =ROUND(D71*B58,2) | F71: ='Investment Valuation 1'!C13 | G71: =ROUND(E71/F71,2) | H71: =IFERROR(RATE(5,0,-F71,E71),0) | I71: =IF(G71>=2,"✓ Attractive",IF(G71>=1,"⚠ Marginal","✗ Below cost"))
A72: Base Case Exit | B72: =B56 | C72: 4 | D72: =ROUND(B72*C72,2) | E72: =ROUND(D72*B58,2) | F72: ='Investment Valuation 1'!C13 | G72: =ROUND(E72/F72,2) | H72: =IFERROR(RATE(5,0,-F72,E72),0) | I72: =IF(G72>=2,"✓ Attractive",IF(G72>=1,"⚠ Marginal","✗ Below cost"))
A73: Strong Exit | B73: =B56 | C73: 5 | D73: =ROUND(B73*C73,2) | E73: =ROUND(D73*B58,2) | F73: ='Investment Valuation 1'!C13 | G73: =ROUND(E73/F73,2) | H73: =IFERROR(RATE(5,0,-F73,E73),0) | I73: =IF(G73>=2,"✓ Attractive",IF(G73>=1,"⚠ Marginal","✗ Below cost"))
A74: Premium Exit | B74: =B56 | C74: 6 | D74: =ROUND(B74*C74,2) | E74: =ROUND(D74*B58,2) | F74: ='Investment Valuation 1'!C13 | G74: =ROUND(E74/F74,2) | H74: =IFERROR(RATE(5,0,-F74,E74),0) | I74: =IF(G74>=2,"✓ Attractive",IF(G74>=1,"⚠ Marginal","✗ Below cost"))
A75: Stress Test (2×) | B75: =B56 | C75: 2 | D75: =ROUND(B75*C75,2) | E75: =ROUND(D75*B58,2) | F75: ='Investment Valuation 1'!C13 | G75: =ROUND(E75/F75,2) | H75: =IFERROR(RATE(5,0,-F75,E75),0) | I75: =IF(G75>=2,"✓ Attractive",IF(G75>=1,"⚠ Marginal","✗ Below cost"))
A78: SECTION 8 — INVESTOR RETURNS BY ROUND
A79: Round | B79: Investment | C79: Pre-Money | D79: Post-Money | E79: Ownership % | F79: Exit Value @ 3.5× | G79: Exit Value @ 6× | H79: MoM @ 3.5× | I79: MoM @ 6×
A80: Round 1 — Seed (Current) | B80: ='Investment Valuation 1'!C13 | C80: ='Investment Valuation 1'!C12 | D80: ='Investment Valuation 1'!C14 | E80: ='Investment Valuation 1'!C19 | F80: =ROUND('Dividend & Distribution Model'!B14*4*E80,2) | G80: =ROUND('Dividend & Distribution Model'!B14*6*E80,2) | H80: =ROUND(F80/B80,2) | I80: =ROUND(G80/B80,2)
A81: Round 2 — Projected | B81: =B32 | C81: =B33 | D81: =B33+B32 | E81: =ROUND(B32/(B33+B32),4) | F81: =ROUND('Dividend & Distribution Model'!B14*4*E80,2) | G81: =ROUND('Dividend & Distribution Model'!B14*6*E80,2) | H81: =ROUND(F80/B80,2) | I81: =ROUND(G80/B80,2)
A84: SECTION 9 — MODEL VALIDATION
A85: Ownership totals 100% (Current) | B85: ✓ OK | C85: =D14 | D85: =100% | E85: Founder + Investor must sum to exactly 100%.
A86: Ownership totals 100% (Post-Round 2) | B86: =IF(ABS(C44-1)<0.001,"✓ OK","✗ ERROR") | C86: =C44 | D86: =100% | E86: Founder + R1 investor + R2 investor must sum to 100%.
A87: Investor MoM ≥ 2× (Base buyback) | B87: =IF(ROUND(B56*B57*B58/'Investment Valuation 1'!C13,2)>=2,"✓ OK","⚠ BELOW 2×") | C87: =ROUND(B56*B57*B58/'Investment Valuation 1'!C13,2) | D87: ≥ 2× | E87: Industry threshold for attractive returns.
A88: Founder retains majority post-R2 | B88: =IF(C41>0.5,"✓ OK","⚠ MINORITY") | C88: =C41 | D88: > 50% | E88: Founder must hold majority for A-share control to be meaningful.
A89: Founder retains voting control | B89: "✓ Always (A Shares)" | C89: "100%" | D89: =100% | E89: A shares carry all voting rights regardless of % ownership.
A90: Working capital buffer > £0 | B90: =IF('Investment Valuation 1'!C28>0,"✓ OK","✗ INSUFFICIENT") | C90: ='Investment Valuation 1'!C28 | D90: > £0 | E90: Investment must cover all startup costs and leave positive working capital.

Sheet Investor Returns
A1: ⚠ EDIT ONLY YELLOW CELLS — ALL OTHER CELLS ARE LOCKED AND PROTECTED
A2: NO DICE BOROUGH LTD — INVESTOR RETURNS ANALYSIS | Base Case (+15%) with Marketing
A3: Investment: £79,000 | Equity: 50% | Distribution: pure pro-rata (no preferred, no priority tiers)
A5: SECTION A — YEAR 1 INVESTOR RETURNS (Base Case, May 2026 – Apr 2027)
A6: Base Case Forecast profit after director salary = 'Base Case Forecast'!N15. Investor equity = 'Investment Valuation 1'!C18. All calculations are formula-driven.
A7: Metric | D7: Value | F7: Notes
A8: Forecast Revenue (Year 1, Base +15%) | D8: ='Base Case Forecast'!N6 | F8: Total revenue forecast May 2026–Apr 2027 from Base Case Forecast
A9: Forecast Profit after Director Salary | D9: ='Dividend & Distribution Model'!B14 | F9: Operating profit after £30,000 director salary
A10: Investor Equity % | D10: ='Investment Valuation 1'!C19 | F10: £79,000 ÷ £158,000 post-money valuation = 50.00%
A11: Investor Share of Year 1 Profit | D11: =ROUND('Dividend & Distribution Model'!B14*'Investment Valuation 1'!C19,2) | F11: Profit × equity %. Assumes profit distributed in full
A12: Investment Amount | D12: ='Investment Valuation 1'!C12 | F12: Total investment received May 2026
A13: Year 1 Cash-on-Cash Return | D13: =ROUND('Dividend & Distribution Model'!B14*'Investment Valuation 1'!C19/'Investment Valuation 1'!C12,4) | F13: Investor Year 1 profit share ÷ investment. Simple cash return.
A14: Simple Payback Period (years) | D14: =ROUND('Investment Valuation 1'!C12/('Dividend & Distribution Model'!B14*'Investment Valuation 1'!C19),2) | F14: Investment ÷ annual investor share. Assumes consistent profit.
A16: SECTION B — 5-YEAR INVESTOR PROJECTION (Revenue growth 7.5% pa, stable margins)
A17: Growth assumption: 7.5% revenue growth per year (conservative — between DJ nights scaling and corporate season maturing). Margin held at Year 1 Base Case level. Exit at Year 5 on 4× EBITDA multiple. Edit growth rate in the Assumptions block below.
A18: Metric | B18: Year 1 2026/27 | C18: Year 2 2027/28 | D18: Year 3 2028/29 | E18: Year 4 2029/30 | F18: Year 5 2030/31 | G18: 5-Year Total | H18: Notes
A19: Revenue | B19: ='Base Case Forecast'!N6 | C19: =ROUND(B19*(1+$B$47),2) | D19: =ROUND(C19*(1+$B$47),2) | E19: =ROUND(D19*(1+$B$47),2) | F19: =ROUND(E19*(1+$B$47),2) | G19: =SUM(B19:F19) | H19: Annual trading revenue
A20: Profit (after dir. salary) | B20: ='Dividend & Distribution Model'!B14 | C20: =ROUND(C19*(B20/B19),2) | D20: =ROUND(D19*(C20/C19),2) | E20: =ROUND(E19*(D20/D19),2) | F20: =ROUND(F19*(E20/E19),2) | G20: =SUM(B20:F20) | H20: Operating profit at Year 1 margin %
A21: Profit Margin % | B21: =IF(B19<>0,B20/B19,0) | C21: =IF(C19<>0,C20/C19,0) | D21: =IF(D19<>0,D20/D19,0) | E21: =IF(E19<>0,E20/E19,0) | F21: =IF(F19<>0,F20/F19,0) | G21: =IF(G19<>0,G20/G19,0) | H21: Held at Year 1 Base Case margin
A22: Investor Share of Profit | B22: =ROUND(B20*'Investment Valuation 1'!C19,2) | C22: =ROUND(C20*'Investment Valuation 1'!C19,2) | D22: =ROUND(D20*'Investment Valuation 1'!C19,2) | E22: =ROUND(E20*'Investment Valuation 1'!C19,2) | F22: =ROUND(F20*'Investment Valuation 1'!C19,2) | G22: =SUM(B22:F22) | H22: Profit × 'Investment Valuation 1'!C18 investor equity
A23: Cumulative Cash Received | B23: =B22 | C23: =B23+C22 | D23: =C23+D22 | E23: =D23+E22 | F23: =E23+F22 | H23: Running total of investor profit shares
A25: SECTION C — YEAR 5 EXIT ANALYSIS (4× EBITDA Exit (entry at 3.5×))
A26: Year 5 EBITDA (Profit) | D26: =F20 | F26: Year 5 operating profit used as EBITDA proxy
A27: Exit Valuation Multiple | D27: =$B$48 | F27: 4× EBITDA for Year 5 exit — normalised going concern multiple. Entry multiple 3.5× (distressed). Exit at 4× reflects stabilised trading.
A28: Year 5 Business Valuation | D28: =ROUND(F20*$B$48,2) | F28: EBITDA × multiple = total business sale value
A29: Investor Exit Proceeds (equity share) | D29: =ROUND(F20*$B$48*'Investment Valuation 1'!C19,2) | F29: Business value × investor equity %
A30: Total Cash Returned (dividends + exit) | D30: =F22+ROUND(F20*$B$48*'Investment Valuation 1'!C19,2) | F30: 5 years of profit shares + exit proceeds
A31: Multiple of Money (MoM) | D31: =ROUND((F22+ROUND(F20*$B$48*'Investment Valuation 1'!C19,2))/'Investment Valuation 1'!C12,2) | F31: Total returned ÷ £79,000 invested. Target: positive cash-on-cash from Year 1.
A33: IRR CALCULATION — Internal Rate of Return
A34: Cash flows: Year 0 = -£79,000 (investment). Years 1-4 = investor profit share (50% pro-rata). Year 5 = profit share + exit proceeds at exit multiple. | B34: =-'Investment Valuation 1'!C12 | C34: =B22 | D34: =C22 | E34: =D22 | F34: =E22+ROUND(F20*$B$48*'Investment Valuation 1'!C19,2)
A35: Cash Flows for IRR | D35: =D21 | F35: =F21+ROUND(F19*$B$47*'Investment Valuation 1'!C19,2)
A36: INTERNAL RATE OF RETURN (IRR) | D36: =IRR(B34:F34) | F36: IRR of ~49% reflects high Year 1 returns and strong exit value. Hospitality sector IRR benchmark: 25-40%. This model comfortably exceeds it.
A46: SECTION D — PROJECTION ASSUMPTIONS (Edit these cells to update the model)
A47: Annual Revenue Growth Rate (Years 2-5) | B47: 0.075 | C47: Conservative: 7.5% pa. Edit to test different scenarios.
A48: Exit EBITDA Multiple (Year 5) | B48: 4 | C48: 4× EBITDA — Year 5 exit assumption (normalised). Entry: 3.5× (distressed). Range: 3× distressed to 5–6× premium.
A49: Year 1 Base Profit (from BCF) | B49: ='Base Case Forecast'!N15 | C49: Links live to Base Case Forecast — do not edit.
A50: Investor Equity (from valuation) | B50: ='Investment Valuation 1'!C19 | C50: Links live to Investment Valuation — do not edit.
A51: Investment Amount | B51: ='Investment Valuation 1'!C12 | C51: Links live to Investment Valuation — do not edit.
A53: 📋 SHARE CLASS NOTE: At £79,000 investment (50% equity), the investor holds A Shares (full voting). A/B threshold is £7,900 (5% of post-money). Below £7,900 → B Shares (economic only).

Sheet Dividend & Distribution Model
A1: NO DICE BOROUGH LTD · PROFIT DISTRIBUTION & INVESTOR RETURNS
A3: 📋 WHAT DOES THE INVESTOR RECEIVE? (Base Case)
A4: Investment Amount
A5: Total Year 1 Return | E5: =B40
A6: Cash-on-Cash Yr 1 | E6: ='Investor Returns'!D13
A7: Payback Period | E7: =ROUND('Investor Returns'!D14,1)
A9: NO DICE BOROUGH LTD — DIVIDEND & DISTRIBUTION MODEL | Founder Repayment · Investor Returns · Profit Waterfall
A10: ⚠ Yellow cells are editable inputs. All other cells are formula-driven and live-linked to the model.
A12: ⚙ MODEL INPUTS — Edit yellow cells to change assumptions
A13: ANNUAL PROFIT | B13: Value | C13: Source / Formula
A14: Annual Profit (Base Case — live) | B14: 124000 | C14: 124000 | E14: Hardcoded to £124,000 — presentation's 2026 base case under new cost model (wages +10%, fixed +10%, drinks = 30% of bar, hosting £3,492 fixed, everything else scales).
A15: Annual Revenue (Base Case — live) | B15: ='Base Case Forecast'!N6 | C15: ='Base Case Forecast'!N6 | E15: Live-linked to Base Case Forecast N6. Total forecast revenue.
A16: FOUNDER REPAYMENT
A17: Quarterly Founder Repayment | B17: 0 | E17: Removed — pure pro-rata distribution. All shareholders paid by equity % at the same time.
A18: Annual Founder Repayment (derived) | B18: =B17*4 | C18: B9 × 4 | E18: Quarterly repayment × 4. Auto-calculated. Edit quarterly figure above.
A19: OWNERSHIP & RETURNS
A20: Founder Ownership % | B20: ='Investment Valuation 1'!C18 | C20: ='Investment Valuation 1'!C18 | E20: Live-linked to Investment Valuation 1. Updates automatically if shareholding changes.
A21: Investor Ownership % | B21: ='Investment Valuation 1'!C19 | C21: ='Investment Valuation 1'!C19 | E21: Investor B-share equity %. Note: at 31.79% the investor holds A Shares (voting). The A/B threshold is 10% of post-money (£47,182). Economic returns are identical for A and B shares — only voting rights differ.
A22: Total Investment Raised | B22: ='Investment Valuation 1'!C13 | C22: ='Investment Valuation 1'!C13 | E22: Live-linked to Investment Valuation 1. £70,000 seed investment.
A23: Investor Preferred Return % (optional) | B23: 0 | C23: Editable input | E23: Removed — pure pro-rata. No preferred floor; investor return = profit × equity %.
A25: 💸 PROFIT DISTRIBUTION WATERFALL (in priority order)
A26: STEP 1 ↓ TOTAL PROFIT | B26: =B14 | C26: =B26 | D26: =IF(B26<>0,B26/B26,0) | E26: Full year operating profit — after all costs, VAT and director salary
A27: STEP 2 ↓ FOUNDER REPAYMENT (first, capped at profit) | B27: =MIN(ROUND(B22*B23,2),MAX(B26,0)) | C27: =B26-B27 | D27: =IF(B26<>0,B27/B26,0) | E27: Removed under pure pro-rata model. Set to 0.
A28: STEP 3 ↓ INVESTOR PREFERRED RETURN (guaranteed floor) | B28: =MIN(B18,MAX(B26-B27,0)) | C28: =C27-B28 | D28: =IF(B26<>0,B28/B26,0) | E28: Removed under pure pro-rata model. No preferred floor.
A29: STEP 4 ↓ REMAINING PROFIT AVAILABLE FOR DISTRIBUTION | B29: =MAX(B26-B27-B28,0) | C29: =B29 | D29: =IF(B26<>0,B29/B26,0) | E29: Profit − founder repayment − preferred return. This pool is split by share %
A30: STEP 5a → INVESTOR DIVIDEND (50% of profit) | B30: =ROUND(B29*B21,2) | C30: =B29-B30 | D30: =IF(B26<>0,B30/B26,0) | E30: Investor 50% equity stake applied to operating profit (pure pro-rata, no tiers).
A31: STEP 5b → FOUNDER DIVIDEND (50% of profit) | B31: =ROUND(B29*B20,2) | C31: — | D31: =IF(B26<>0,B31/B26,0) | E31: Founder 50% equity stake applied to operating profit (pure pro-rata, no tiers).
A33: 📊 DISTRIBUTION SUMMARY — Where every £ of profit goes
A34: Total Operating Profit | B34: =B26 | C34: =IF(B26<>0,B34/B26,0) | D34: — | E34: Starting profit pool. All distributions drawn from here.
A35: Investor Preferred Return (Step 2) | B35: =B27 | C35: =IF(B26<>0,B35/B26,0) | D35: Investor(s)
A36: Founder Repayment (Step 3) | B36: =B28 | C36: =IF(B26<>0,B36/B26,0) | D36: Founder (Elliot Scott)
A37: Investor Pro-Rata Dividend (Step 5a) | B37: =B30 | C37: =IF(B26<>0,B37/B26,0) | D37: Investor(s)
A38: Founder Pro-Rata Dividend (Step 5b) | B38: =B31 | C38: =IF(B26<>0,B38/B26,0) | D38: Founder (Elliot Scott)
A39: TOTAL DISTRIBUTED | B39: =B35+B36+B37+B38 | C39: =IF(B26<>0,B39/B26,0) | D39: All parties
A40: Total to Founder (Steps 2 + 5b) | B40: =B35+B37 | C40: =IF(B26<>0,B40/B26,0) | D40: Founder (Elliot Scott)
A41: Total to Investor (Steps 3 + 5a) | B41: =B36+B38 | C41: =IF(B26<>0,B41/B26,0) | D41: Investor(s) | E41: Preferred return + pro-rata dividend combined.
A42: Retained in Business (Profit − Distributed)
A43: ✅ CASH FLOW SAFETY CHECKS — Model validation
A44: Profit covers full founder repayment? | B44: =IF(B26>=B18,"✓ YES — full £"&TEXT(B18,"#,##0")&" payable","⚠ PARTIAL — only £"&TEXT(B27,"#,##0")&" of £"&TEXT(B18,"#,##0")&" payable") | C44: =B27 | D44: Founder repayment capped at available profit. No negative cash possible.
A45: Profit remaining after founder repayment | B45: =IF(MAX(B26-B27,0)>0,"✓ £"&TEXT(MAX(B26-B27,0),"#,##0")&" available for distributions","⚠ No profit remaining after repayment") | C45: =MAX(B26-B27,0) | D45: Profit left to fund preferred return and pro-rata dividends.
A46: Investor receives preferred return in full? | B46: =IF(B23=0,"ℹ Preferred return disabled (0%)",IF(B26-B27>=ROUND(B22*B23,2),"✓ YES — full preferred return covered","⚠ PARTIAL — only £"&TEXT(B28,"#,##0")&" of £"&TEXT(ROUND(B22*B23,2),"#,##0")&" payable")) | C46: =B28 | D46: Preferred return capped at remaining balance after founder repayment.
A47: No distribution exceeds available profit? | B47: =IF(B39<=B26+0.5,"✓ VALID — no over-distribution","✗ ERROR — distributions exceed profit") | C47: =B26-B39 | D47: Hard constraint: total distributions cannot exceed operating profit.
A48: Profit margin sufficient for distributions? | B48: =IF(B26/B15>0.15,"✓ HEALTHY — margin supports distributions",IF(B26>0,"⚠ LOW MARGIN — monitor cash carefully","✗ LOSS — no distributions possible")) | C48: =IF(B15<>0,B26/B15,0) | D48: Profit as % of revenue. Below 15% warrants caution on distribution size.
A50: SECTION 5 — SCENARIO TESTING (Conservative · Base Case · Optimistic)
A51: Operating Profit | B51: ='Scenario Planning'!P39 | C51: ='Dividend & Distribution Model'!B14 | D51: ='Scenario Planning'!P73 | E51: Conservative=SP!P39, Base=BCF!N16, Optimistic=SP!P73. All inputs from Section 1.
A52: Investor Preferred Return
A53: Founder Repayment | B53: =MIN(ROUND(B22*B23,2),MAX('Scenario Planning'!P39-MIN(B18,MAX('Scenario Planning'!P39,0)),0)) | C53: =MIN(ROUND(B22*B23,2),MAX('Dividend & Distribution Model'!B14-MIN(B18,MAX('Dividend & Distribution Model'!B14,0)),0))
A54: Remaining Pool | B54: =MAX('Scenario Planning'!P39-MIN(B18,MAX('Scenario Planning'!P39,0))-MIN(ROUND(B22*B23,2),MAX('Scenario Planning'!P39-MIN(B18,MAX('Scenario Planning'!P39,0)),0)),0) | C54: =MAX('Dividend & Distribution Model'!B14-MIN(B18,MAX('Dividend & Distribution Model'!B14,0))-MIN(ROUND(B22*B23,2),MAX('Dividend & Distribution Model'!B14-MIN(B18,MAX('Dividend & Distribution Model'!B14,0)),0)),0)
A55: Investor Dividend | B55: =ROUND(MAX('Scenario Planning'!P39-MIN(B18,MAX('Scenario Planning'!P39,0))-MIN(ROUND(B22*B23,2),MAX('Scenario Planning'!P39-MIN(B18,MAX('Scenario Planning'!P39,0)),0)),0)*B21,2) | C55: =ROUND(MAX('Dividend & Distribution Model'!B14-MIN(B18,MAX('Dividend & Distribution Model'!B14,0))-MIN(ROUND(B22*B23,2),MAX('Dividend & Distribution Model'!B14-MIN(B18,MAX('Dividend & Distribution Model'!B14,0)),0)),0)*B21,2)
A56: Founder Dividend | B56: =ROUND(MAX('Scenario Planning'!P39-MIN(B18,MAX('Scenario Planning'!P39,0))-MIN(ROUND(B22*B23,2),MAX('Scenario Planning'!P39-MIN(B18,MAX('Scenario Planning'!P39,0)),0)),0)*B20,2) | C56: =ROUND(MAX('Dividend & Distribution Model'!B14-MIN(B18,MAX('Dividend & Distribution Model'!B14,0))-MIN(ROUND(B22*B23,2),MAX('Dividend & Distribution Model'!B14-MIN(B18,MAX('Dividend & Distribution Model'!B14,0)),0)),0)*B20,2)
A57: Total → Investor | B57: =ROUND(MAX('Scenario Planning'!P39-MIN(B18,MAX('Scenario Planning'!P39,0))-MIN(ROUND(B22*B23,2),MAX('Scenario Planning'!P39-MIN(B18,MAX('Scenario Planning'!P39,0)),0)),0)*B21,2)+MIN(ROUND(B22*B23,2),MAX('Scenario Planning'!P39-MIN(B18,MAX('Scenario Planning'!P39,0)),0)) | C57: =ROUND(MAX('Dividend & Distribution Model'!B14-MIN(B18,MAX('Dividend & Distribution Model'!B14,0))-MIN(ROUND(B22*B23,2),MAX('Dividend & Distribution Model'!B14-MIN(B18,MAX('Dividend & Distribution Model'!B14,0)),0)),0)*B21,2)+MIN(ROUND(B22*B23,2),MAX('Dividend & Distribution Model'!B14-MIN(B18,MAX('Dividend & Distribution Model'!B14,0)),0))
A58: Total → Founder | B58: =MIN(B18,MAX('Scenario Planning'!P39,0))+ROUND(MAX('Scenario Planning'!P39-MIN(B18,MAX('Scenario Planning'!P39,0))-MIN(ROUND(B22*B23,2),MAX('Scenario Planning'!P39-MIN(B18,MAX('Scenario Planning'!P39,0)),0)),0)*B20,2) | C58: =MIN(B18,MAX('Dividend & Distribution Model'!B14,0))+ROUND(MAX('Dividend & Distribution Model'!B14-MIN(B18,MAX('Dividend & Distribution Model'!B14,0))-MIN(ROUND(B22*B23,2),MAX('Dividend & Distribution Model'!B14-MIN(B18,MAX('Dividend & Distribution Model'!B14,0)),0)),0)*B20,2)
A60: SECTION 6 — INVESTOR RETURN METRICS (Base Case)
A61: Investment Amount | B61: =B22 | C61: Total capital invested.
A62: Total Annual Return to Investor | B62: =B40 | C62: Preferred return + pro-rata dividend (base case).
A63: Cash-on-Cash Return (Year 1) | B63: =IF(B22<>0,B40/B22,0) | C63: Annual investor return ÷ investment. Year 1 cash yield.
A64: Simple Payback Period | B64: =IF(B40<>0,ROUND(B22/B40,1),"N/A") | C64: Years to recover investment at base case distribution rate.
A65: Investor Preferred Return (£) | B65: =ROUND(B22*B23,2) | C65: Investment × preferred %. Set preferred % to 0% to disable.
A66: Investor Pro-Rata Dividend (£) | B66: =B30 | C66: Share of remaining profit pool by ownership %.
A68: SECTION 7 — MODEL VALIDATION
A69: Total distributed = Operating Profit | B69: =IF(ABS(B39-B26)<0.5,"✓ OK","✗ ERROR") | C69: =ABS(B39-B26) | D69: < £0.50 rounding tolerance | E69: All profit accounted for.
A70: No distribution is negative | B70: =IF(MIN(B27,B28,B30,B31)>=0,"✓ OK","✗ NEGATIVE DISTRIBUTION") | C70: =MIN(B27,B28,B30,B31) | D70: ≥ £0 | E70: All distributions non-negative.
A71: Founder repayment ≤ profit | B71: =IF(B27<=B26+0.01,"✓ OK","✗ EXCEEDS PROFIT") | C71: =B26-B27 | D71: ≥ £0 | E71: Repayment capped at available profit.
A72: Investor + Founder % sum to 100% | B72: =IF(ABS(B21+B20-1)<0.0001,"✓ OK","✗ ERROR — check IV1 shareholding") | C72: =B21+B20 | D72: =100% | E72: Ownership must sum to exactly 100%.
A74: SECTION 8 — CASH RESERVE STRATEGY (2–3 months fixed cost target · Reserve funded from Day 1 investment capital · Year 1 distributions fully payable)
A75: IMPORTANT: The £79,000 investor capital funds the £67,978 of startup costs on Day 1. The £11,022 residual is staged into the business as working capital per the cash flow forecast.
A77: COST COMPONENT | E77: ANNUAL £ | G77: MONTHLY £ | I77: NOTE
A78: Wages & Payroll | E78: ='Base Case Forecast'!N8 | G78: ='Base Case Forecast'!N8/12 | I78: Fixed staff cost — largest monthly obligation
A79: Fixed Overheads | E79: ='Base Case Forecast'!N9 | G79: ='Base Case Forecast'!N9/12 | I79: Insurance, utilities, subscriptions
A80: Rent (annual avg) | E80: ='Base Case Forecast'!N13 | G80: ='Base Case Forecast'!N13/12 | I80: Quarterly landlord payment — annualised
A81: Director Salary | E81: ='Base Case Forecast'!B54 | G81: ='Base Case Forecast'!B54/12 | I81: Fixed monthly draw — Elliot Scott
A82: TOTAL MONTHLY FIXED OBLIGATIONS | E82: =SUM('Base Case Forecast'!N8,'Base Case Forecast'!N9,'Base Case Forecast'!N13,'Base Case Forecast'!B54) | G82: =SUM('Base Case Forecast'!N8,'Base Case Forecast'!N9,'Base Case Forecast'!N13,'Base Case Forecast'!B54)/12 | I82: ← Reserve basis — this is the monthly cost the business must always be able to cover
A84: RESERVE TARGETS (cash held in business before distributions begin)
A85: Minimum Reserve (2 months) | G85: =G82*2 | I85: ≥ £90k · Minimum viable buffer for Feb cash dip
A86: Target Reserve (3 months) ← RECOMMENDED | G86: =G82*3 | I86: ≥ £135k · Covers any 3-month trading trough without credit exposure
A88: RESERVE ADEQUACY (vs current cash flow model)
A89: Year-end cash position (April) | G89: =MAX('Cash Flow Forecast'!B30:M30) | I89: £157,700 peak — above 3-month target ✓ Reserve fully funded by April
A90: Lowest cash month (February) | G90: =MIN('Cash Flow Forecast'!B30:M30) | I90: £23,098 ← Below 2-month reserve target. Feb is the critical risk month.
A91: Gap: Feb cash vs 2-month reserve | G91: =MIN('Cash Flow Forecast'!B30:M30)-G82*2 | I91: Negative = reserve not yet built at this point in year. Funded from Dec surplus.
A92: Profit available after 3-month reserve met | G92: =MAX('Dividend & Distribution Model'!B14-G82*3,0) | I92: Fully distributable once £135k reserve threshold is reached.
A94: INVESTOR IMPACT (reserve does not reduce preferred return)
A95: Pure pro-rata distribution (no preferred return): Operating profit splits 50/50 by equity. No floor, no priority — investor and founder receive their share at the same time. | E95: Paid first — reserve does not affect this. Guaranteed before any other distribution.
A96: A-share priority return (£44,000) | E96: Paid second — also protected. Reserve applies only to the remaining distributable pool.
A97: Investor pro-rata dividend | E97: Paid from remaining pool AFTER reserve confirmed. May reduce in low-profit years.
A98: Effect on total investor return (base case) | E98: Reserve built from Dec/Jan surplus — no impact on Year 1 base case distributions.
A99: ★ RESERVE PRINCIPLE: The business holds the equivalent of 2–3 months fixed operating costs as a standing cash reserve before distributions are made. The investor preferred return (£12,000) and A-share priority return (£44,000) are paid before any reserve deduction applies to dividends.
A101: 📋 A SHARE vs B SHARE — WHAT IT MEANS FOR DISTRIBUTIONS: A Shares (investor equity ≥5% of post-money, i.e. ≥£7,900): full voting + economic rights. B Shares (below £7,900): economic rights only, no voting. Distribution itself is identical for both classes — pure pro-rata on operating profit.

Sheet Cash Flow Forecast
A1: ⚠ EDIT ONLY YELLOW CELLS — ALL OTHER CELLS ARE LOCKED AND PROTECTED
A2: NO DICE BOROUGH — CASH FLOW FORECAST | May 2026 – April 2027 (Base Case +15%)
A3: Investment: £79,000 inc VAT | Startup: £67,978 inc VAT | Rent in Advance: £27,078 (3 months — May, Jun, Jul 2026) | Working Capital residual: £11,022
A4: ITEM | O4: Balance Check | P4: Status
A5: CASH IN | B5: May | C5: Jun | D5: Jul | E5: Aug | F5: Sep | G5: Oct | H5: Nov | I5: Dec | J5: Jan | K5: Feb | L5: Mar | M5: Apr | N5: TOTAL
A6: Investment Received (day 1 — May 2026) | B6: ='Investment Valuation 1'!C13 | N6: ='Investment Valuation 1'!C13
A7: Trading Income (inc VAT, +15% on 2025 equiv month) | B7: ='Base Case Forecast'!B6 | C7: ='Base Case Forecast'!C6 | D7: ='Base Case Forecast'!D6 | E7: ='Base Case Forecast'!E6 | F7: ='Base Case Forecast'!F6 | G7: ='Base Case Forecast'!G6 | H7: ='Base Case Forecast'!H6 | I7: ='Base Case Forecast'!I6 | ... N7: ='Base Case Forecast'!N6
A8: VAT Reclaim — Startup Costs (credited against Q1 return, Aug 2026) | B8: =ROUND(('Investment Valuation 1'!C24+'Investment Valuation 1'!C25+'Investment Valuation 1'!C26)/6,2) | N8: =ROUND(('Investment Valuation 1'!C24+'Investment Valuation 1'!C25+'Investment Valuation 1'!C26)/6,2)
A9: TOTAL CASH IN | B9: =B6+B7+B8 | C9: =C6+C7+C8 | D9: =D6+D7+D8 | E9: =E6+E7+E8 | F9: =F6+F7+F8 | G9: =G6+G7+G8 | H9: =H6+H7+H8 | I9: =I6+I7+I8 | ... M9: =M6+M7+M8 | N9: =SUM(B9:M9)
A11: ONE-OFF STARTUP COSTS (paid from investment — May 2026) | B11: May | C11: Jun | D11: Jul | E11: Aug | F11: Sep | G11: Oct | H11: Nov | I11: Dec | J11: Jan | K11: Feb | L11: Mar | M11: Apr | N11: TOTAL
A12: Hardware from Liquidators (£20k + VAT) | B12: ='Investment Valuation 1'!C24 | N12: ='Investment Valuation 1'!C24
A13: IP License Fee (paid to No Dice Bars LTD — £10k + VAT) | B13: ='Investment Valuation 1'!C25 | N13: ='Investment Valuation 1'!C25
A14: Stock & Operational Setup (£4,900 — alcohol, software subs, internet, cleaning, rates first month, alcohol licence) | B14: ='Investment Valuation 1'!C26 | N14: ='Investment Valuation 1'!C26
A15: Landlord — 3-Month Rent in Advance (covers May, Jun, Jul 2026 at 15% of 2025 turnover; reverts to 15% of actual turnover from August) | B15: ='Investment Valuation 1'!C27 | N15: ='Investment Valuation 1'!C27
A16: TOTAL ONE-OFF COSTS | B16: =B12+B13+B14+B15 | N16: =N12+N13+N14+N15
A18: MONTHLY OPERATING COSTS (wages + overheads at 2025 base + 10% fixed | rent quarterly in arrears at 15% of prev quarter revenue from August 2026) | B18: May | C18: Jun | D18: Jul | E18: Aug | F18: Sep | G18: Oct | H18: Nov | I18: Dec | J18: Jan | K18: Feb | L18: Mar | M18: Apr | N18: TOTAL
A19: Wages (held at 2025 actuals) | B19: ='Base Case Forecast'!B8 | C19: ='Base Case Forecast'!C8 | D19: ='Base Case Forecast'!D8 | E19: ='Base Case Forecast'!E8 | F19: ='Base Case Forecast'!F8 | G19: ='Base Case Forecast'!G8 | H19: ='Base Case Forecast'!H8 | I19: ='Base Case Forecast'!I8 | ... N19: ='Base Case Forecast'!N8
A20: Director Salary — Elliot Scott (£30,000 pa / £2,500/month) | B20: ='Base Case Forecast'!B12 | C20: ='Base Case Forecast'!C12 | D20: ='Base Case Forecast'!D12 | E20: ='Base Case Forecast'!E12 | F20: ='Base Case Forecast'!F12 | G20: ='Base Case Forecast'!G12 | H20: ='Base Case Forecast'!H12 | I20: ='Base Case Forecast'!I12 | ... N20: ='Base Case Forecast'!N12
A21: Fixed Overheads (2025 base + 10% — energy, insurance, subscriptions, business rates ~£1,800/mo from June) | B21: ='Base Case Forecast'!B9 | C21: ='Base Case Forecast'!C9 | D21: ='Base Case Forecast'!D9 | E21: ='Base Case Forecast'!E9 | F21: ='Base Case Forecast'!F9 | G21: ='Base Case Forecast'!G9 | H21: ='Base Case Forecast'!H9 | I21: ='Base Case Forecast'!I9 | ... N21: ='Base Case Forecast'!N9
A22: Variable Costs (2025 base, capped at 30% of revenue) | B22: ='Base Case Forecast'!B10 | C22: ='Base Case Forecast'!C10 | D22: ='Base Case Forecast'!D10 | E22: ='Base Case Forecast'!E10 | F22: ='Base Case Forecast'!F10 | G22: ='Base Case Forecast'!G10 | H22: ='Base Case Forecast'!H10 | I22: ='Base Case Forecast'!I10 | ... N22: ='Base Case Forecast'!N10
A23: Rent — From August 2026: 15% of prev quarter revenue, paid quarterly in arrears (May–Jul rent prepaid via the £27,078 advance, NOT a refundable deposit) | B23: ='Base Case Forecast'!B13 | C23: ='Base Case Forecast'!C13 | D23: ='Base Case Forecast'!D13 | E23: ='Base Case Forecast'!E13 | F23: ='Base Case Forecast'!F13 | G23: ='Base Case Forecast'!G13 | H23: ='Base Case Forecast'!H13 | I23: ='Base Case Forecast'!I13 | ... N23: ='Base Case Forecast'!N13
A24: VAT Output — Quarterly Payment to HMRC | B24: 0 | C24: 0 | D24: 0 | E24: =MAX(0,ROUND('Base Case Forecast'!B14+'Base Case Forecast'!C14+'Base Case Forecast'!D14,2)-'Cash Flow Forecast'!C8) | F24: 0 | G24: 0 | H24: =ROUND('Base Case Forecast'!E14+'Base Case Forecast'!F14+'Base Case Forecast'!G14,2) | I24: 0 | J24: 0 | K24: =ROUND('Base Case Forecast'!H14+'Base Case Forecast'!I14+'Base Case Forecast'!J14,2) | L24: 0 | M24: 0 | N24: ='Base Case Forecast'!N14
A25: TOTAL MONTHLY COSTS | B25: =B19+B20+B21+B22+B23+B24 | C25: =C19+C20+C21+C22+C23+C24 | D25: =D19+D20+D21+D22+D23+D24 | E25: =E19+E20+E21+E22+E23+E24 | F25: =F19+F20+F21+F22+F23+F24 | G25: =G19+G20+G21+G22+G23+G24 | H25: =H19+H20+H21+H22+H23+H24 | I25: =I19+I20+I21+I22+I23+I24 | ... M25: =M19+M20+M21+M22+M23+M24 | N25: =SUM(B25:M25)
A27: NET CASH FLOW SUMMARY | B27: May | C27: Jun | D27: Jul | E27: Aug | F27: Sep | G27: Oct | H27: Nov | I27: Dec | J27: Jan | K27: Feb | L27: Mar | M27: Apr | N27: TOTAL
A28: TOTAL CASH OUT | B28: =B16+B25 | C28: =C25 | D28: =D25 | E28: =E25 | F28: =F25 | G28: =G25 | H28: =H25 | I28: =I25 | J28: =J25 | ... M28: =M25 | N28: =N16+N25
A29: NET CASH FLOW (In minus Out) | B29: =B9-B28 | C29: =C9-C28 | D29: =D9-D28 | E29: =E9-E28 | F29: =F9-F28 | G29: =G9-G28 | H29: =H9-H28 | I29: =I9-I28 | ... M29: =M9-M28 | N29: =SUM(B29:M29)
A30: CUMULATIVE CASH BALANCE | B30: =B29 | C30: =B30+C29 | D30: =C30+D29 | E30: =D30+E29 | F30: =E30+F29 | G30: =F30+G29 | H30: =G30+H29 | I30: =H30+I29 | J30: =I30+J29 | ... M30: =L30+M29 | N30: =M30
A32: RENT STRUCTURE: £27,078 inc VAT paid in May 2026 covers 3 months of rent IN ADVANCE (May, Jun, Jul). NOT a refundable deposit. From August 2026 rent reverts to the contractual 15% of the prior quarters actual revenue, billed quarterly in arrears.
A33: COST NOTE: December 2026 rent = £0 (paid in November). January 2027 rent = £0 (paid in November). February 2027 rent = £41,968 — this is the largest quarterly payment as it covers Nov+Dec+Jan, which includes the high-revenue Christmas period (Dec 2026 forecast: £144,366). The cumulative balance dips in August, November and February on rent payment months but recovers strongly from trading.
A34: CASH FLOW BALANCE CHECK (Opening + Net = Closing each month)
A35: Monthly balance check (✓=balanced): | B35: =IF(ABS(B29-B30)<0.01,"✓","✗") | C35: =IF(ABS((B30+C29)-C30)<0.01,"✓","✗") | D35: =IF(ABS((C30+D29)-D30)<0.01,"✓","✗") | E35: =IF(ABS((D30+E29)-E30)<0.01,"✓","✗") | F35: =IF(ABS((E30+F29)-F30)<0.01,"✓","✗") | G35: =IF(ABS((F30+G29)-G30)<0.01,"✓","✗") | H35: =IF(ABS((G30+H29)-H30)<0.01,"✓","✗") | I35: =IF(ABS((H30+I29)-I30)<0.01,"✓","✗") | J35: =IF(ABS((I30+J29)-J30)<0.01,"✓","✗") | ... M35: =IF(ABS((L30+M29)-M30)<0.01,"✓","✗") | N35: =IF(COUNTIF(B35:M35,"✓")=12,"✓ ALL OK","✗ "&(12-COUNTIF(B35:M35,"✓"))&" FAIL")
A36: Period
A37: CASH BUFFER ANALYSIS — Liquidity Risk Monitor
A38: Minimum Monthly Cash Balance (worst month) | G38: =MIN(B30:M30) | L38: The lowest the cumulative balance falls across all 12 months. February 2027 (rent month) is typically the trough.
A39: Safety Threshold (recommended minimum) | G39: 30000 | L39: £30,000 = approx 5 weeks of fixed operating costs. Edit this cell to change the threshold.
A40: Cash Buffer Above Safety Threshold | G40: =MIN(B30:M30)-G39 | L40: If this turns negative → the business may need a cash facility or cost reduction.
A41: Month of Minimum Cash Position | G41: {=INDEX({"May","Jun","Jul","Aug","Sep","Oct","Nov","Dec","Jan","Feb","Mar","Apr"},MATCH(MIN(B29:M29),B29:M29,0))} | L41: The month when cash is at its lowest — useful for investor liquidity planning.
A42: Cash Safety Status | G42: =IF(MIN(B30:M30)>=G39,"✓ SAFE — cash stays above threshold","⚠ MONITOR — cash approaches minimum safe level") | L42: Green if always above threshold, amber if it drops below at any point.
A43: Wages | B43: 2025 actual staff wages retained as base. Shown separately from Director Salary below.
A44: Director Salary | B44: £30,000 per annum = £2,500.00 per month, fixed. Paid to Elliot Scott as Managing Director. Shown as a separate cost line for investor clarity. Profit figures above this line are before this salary.
A45: Fixed Overheads | B45: 2025 base + 10% uplift reflecting business rates relief reduction (75%→40% in 2025/26) and energy cost increases from April 2026. First month rates (May, £1,800) prepaid in startup costs to avoid double counting.
A46: Variable Costs | B46: 2025 base, scaled with revenue. Hard cap at 30% of monthly income.
A47: VAT Output | B47: QUARTERLY VAT SCHEDULE (Standard May/Aug/Nov/Feb stagger): Q1 (May–Jul 2026): paid Aug 2026. Startup VAT reclaim ~£6,500 credited against this first return.
A50: DIVIDEND & DISTRIBUTION SUMMARY (from Dividend & Distribution Model — annual totals)
A51: Annual Operating Profit | B51: ='Dividend & Distribution Model'!B18 | C51: =ROUND(B51/12,2) | D51: =ROUND(B51/12,2) | E51: =ROUND(B51/12,2) | F51: =ROUND(B51/12,2) | G51: =ROUND(B51/12,2) | H51: =ROUND(B51/12,2) | I51: =ROUND(B51/12,2) | J51: =ROUND(B51/12,2) | K51: =ROUND(B51/12,2) | L51: =ROUND(B51/12,2) | M51: =ROUND(B51/12,2) | N51: =B51 | O51: BCF N16: profit after wages, overheads, rent, VAT and director salary.
A52: Founder Repayment (Step 2) | B52: ='Dividend & Distribution Model'!B19 | C52: =ROUND(B52/12,2) | D52: =ROUND(B52/12,2) | E52: =ROUND(B52/12,2) | F52: =ROUND(B52/12,2) | G52: =ROUND(B52/12,2) | H52: =ROUND(B52/12,2) | I52: =ROUND(B52/12,2) | J52: =ROUND(B52/12,2) | K52: =ROUND(B52/12,2) | L52: =ROUND(B52/12,2) | M52: =ROUND(B52/12,2) | N52: =B52 | O52: First-priority distribution to founder. Capped at available profit.
A53: Investor Preferred Return | B53: ='Dividend & Distribution Model'!B20 | C53: =ROUND(B53/12,2) | D53: =ROUND(B53/12,2) | E53: =ROUND(B53/12,2) | F53: =ROUND(B53/12,2) | G53: =ROUND(B53/12,2) | H53: =ROUND(B53/12,2) | I53: =ROUND(B53/12,2) | J53: =ROUND(B53/12,2) | K53: =ROUND(B53/12,2) | L53: =ROUND(B53/12,2) | M53: =ROUND(B53/12,2) | N53: =B53 | O53: Distribution model: pure pro-rata on operating profit (no preferred, no priority tiers). See Dividend & Distribution Model.
A54: Investor Pro-Rata Dividend | B54: ='Dividend & Distribution Model'!B22 | C54: =ROUND(B54/12,2) | D54: =ROUND(B54/12,2) | E54: =ROUND(B54/12,2) | F54: =ROUND(B54/12,2) | G54: =ROUND(B54/12,2) | H54: =ROUND(B54/12,2) | I54: =ROUND(B54/12,2) | J54: =ROUND(B54/12,2) | K54: =ROUND(B54/12,2) | L54: =ROUND(B54/12,2) | M54: =ROUND(B54/12,2) | N54: =B54 | O54: Investor share of remaining pool by B-share equity %.
A55: Founder Pro-Rata Dividend | B55: ='Dividend & Distribution Model'!B23 | C55: =ROUND(B55/12,2) | D55: =ROUND(B55/12,2) | E55: =ROUND(B55/12,2) | F55: =ROUND(B55/12,2) | G55: =ROUND(B55/12,2) | H55: =ROUND(B55/12,2) | I55: =ROUND(B55/12,2) | J55: =ROUND(B55/12,2) | K55: =ROUND(B55/12,2) | L55: =ROUND(B55/12,2) | M55: =ROUND(B55/12,2) | N55: =B55 | O55: Founder share of remaining pool by A-share equity %.
A56: Total Distributed | B56: ='Dividend & Distribution Model'!B31 | C56: =ROUND(B56/12,2) | D56: =ROUND(B56/12,2) | E56: =ROUND(B56/12,2) | F56: =ROUND(B56/12,2) | G56: =ROUND(B56/12,2) | H56: =ROUND(B56/12,2) | I56: =ROUND(B56/12,2) | J56: =ROUND(B56/12,2) | K56: =ROUND(B56/12,2) | L56: =ROUND(B56/12,2) | M56: =ROUND(B56/12,2) | N56: =B56 | O56: Must equal operating profit — validated below.
A57: Retained in Business | B57: =MAX('Dividend & Distribution Model'!B18-'Dividend & Distribution Model'!B31,0) | C57: =ROUND(B57/12,2) | D57: =ROUND(B57/12,2) | E57: =ROUND(B57/12,2) | F57: =ROUND(B57/12,2) | G57: =ROUND(B57/12,2) | H57: =ROUND(B57/12,2) | I57: =ROUND(B57/12,2) | J57: =ROUND(B57/12,2) | K57: =ROUND(B57/12,2) | L57: =ROUND(B57/12,2) | M57: =ROUND(B57/12,2) | N57: =B57 | O57: Profit not distributed. Zero when all profit is distributed.
A58: Distribution Validation | B58: =IF(ABS('Dividend & Distribution Model'!B31-'Dividend & Distribution Model'!B18)<0.5,"✓ Balanced — distributions = profit","✗ ERROR — over/under distribution")
A60: 📋 VAT SCHEDULE SUMMARY — Quarterly payments to HMRC (standard May/Aug/Nov/Feb stagger)
A61: Quarter | B61: Period | C61: Output VAT | D61: Input VAT (est.) | E61: Startup Reclaim | F61: Net Payable | G61: Payment Month | H61: Status
A62: Q1 | B62: May–Jul 2026 | C62: =ROUND('Base Case Forecast'!B14+'Base Case Forecast'!C14+'Base Case Forecast'!D14,2) | D62: 15884.94 | E62: 18000 | F62: =MAX(0,C62-D62-E62) | G62: August 2026 | H62: ✓ Refund from HMRC (Q1 < reclaim)
A63: Q2 | B63: Aug–Oct 2026 | C63: =ROUND('Base Case Forecast'!E14+'Base Case Forecast'!F14+'Base Case Forecast'!G14,2) | D63: 15884.94 | F63: =MAX(0,C63-D63-E63) | G63: November 2026 | H63: ✓ Paid — see CF row 24 Nov
A64: Q3 | B64: Nov 2026–Jan 2027 | C64: =ROUND('Base Case Forecast'!H14+'Base Case Forecast'!I14+'Base Case Forecast'!J14,2) | D64: 15884.94 | F64: =MAX(0,C64-D64-E64) | G64: February 2027 | H64: ✓ Paid — see CF row 24 Feb
A65: Q4 | B65: Feb–Apr 2027 | C65: =ROUND('Base Case Forecast'!K14+'Base Case Forecast'!L14+'Base Case Forecast'!M14,2) | D65: 15884.94 | F65: =MAX(0,C65-D65-E65) | G65: May 2027 | H65: ⚠ Outside model year — due May 2027
A66: ANNUAL TOTALS | B66: Full year | C66: =SUM(C62:C65) | D66: =SUM(D62:D65) | E66: 18000 | F66: =SUM(F62:F65) | G66: Q4 in Year 2 | H66: ⚠ Q4 (£18k) payable May 2027 — not in this year's CF
A67: Note on input VAT estimate: Input VAT (£63,540/yr) applies to fixed overheads, variable costs and Google Ads spend. Wages and rent are not subject to VAT. The input VAT estimate is divided equally across quarters as a working assumption. Actual input VAT will vary by quarter based on cost timing. A VAT-registered accountant should confirm the final quarterly return amounts.

Sheet Base Case Forecast
A1: ⚠ EDIT ONLY YELLOW CELLS — ALL OTHER CELLS ARE LOCKED AND PROTECTED
A2: NO DICE BOROUGH — BASE CASE FORECAST | May 2026 – April 2027 | +15% Revenue
A3: Equiv. period base (2025 actuals): £741,644 → Forecast: £852,891 | Costs: 2025 base + 10% fixed | Variable capped @30% | Rent quarterly at 15% of prev quarter
A4: Metric | B4: May 2026 | C4: Jun 2026 | D4: Jul 2026 | E4: Aug 2026 | F4: Sep 2026 | G4: Oct 2026 | H4: Nov 2026 | I4: Dec 2026 | J4: Jan 2027 | K4: Feb 2027 | L4: Mar 2027 | M4: Apr 2027 | N4: PERIOD TOTAL
A5: 2025 EQUIV-MONTH INCOME (base) | B5: ='Monthly Summary'!C7 | C5: ='Monthly Summary'!C8 | D5: ='Monthly Summary'!C9 | E5: ='Monthly Summary'!C10 | F5: ='Monthly Summary'!C11 | G5: ='Monthly Summary'!C12 | H5: ='Monthly Summary'!C13 | I5: ='Monthly Summary'!C14 | J5: ='Monthly Summary'!C3 | K5: ='Monthly Summary'!C4 | L5: ='Monthly Summary'!C5 | M5: ='Monthly Summary'!C6 | N5: =SUM(B5:M5)
A6: 2026/27 FORECAST INCOME (scenario-driven growth, see Inputs) | B6: =ROUND(B5*(1+$B$52)*B60/$B$61,2) | C6: =ROUND(C5*(1+$B$52)*C60/$B$61,2) | D6: =ROUND(D5*(1+$B$52)*D60/$B$61,2) | E6: =ROUND(E5*(1+$B$52)*E60/$B$61,2) | F6: =ROUND(F5*(1+$B$52)*F60/$B$61,2) | G6: =ROUND(G5*(1+$B$52)*G60/$B$61,2) | H6: =ROUND(H5*(1+$B$52)*H60/$B$61,2) | I6: =ROUND(I5*(1+$B$52)*I60/$B$61,2) | ... M6: =ROUND(M5*(1+$B$52)*M60/$B$61,2) | N6: =SUM(B6:M6)
A7: REVENUE UPLIFT | B7: =B6-B5 | C7: =C6-C5 | D7: =D6-D5 | E7: =E6-E5 | F7: =F6-F5 | G7: =G6-G5 | H7: =H6-H5 | I7: =I6-I5 | ... M7: =M6-M5 | N7: =SUM(B7:M7)
A8: WAGES (2025 actuals) | B8: ='Monthly Summary'!G7 | C8: ='Monthly Summary'!G8 | D8: ='Monthly Summary'!G9 | E8: ='Monthly Summary'!G10 | F8: ='Monthly Summary'!G11 | G8: ='Monthly Summary'!G12 | H8: ='Monthly Summary'!G13 | I8: ='Monthly Summary'!G14 | J8: ='Monthly Summary'!G3 | K8: ='Monthly Summary'!G4 | L8: ='Monthly Summary'!G5 | M8: ='Monthly Summary'!G6 | N8: =SUM(B8:M8)
A9: FIXED OVERHEADS (2025 base +10%) | B9: =ROUND('Monthly Summary'!E7*(1+$B$53),2) | C9: =ROUND('Monthly Summary'!E8*(1+$B$53),2) | D9: =ROUND('Monthly Summary'!E9*(1+$B$53),2) | E9: =ROUND('Monthly Summary'!E10*(1+$B$53),2) | F9: =ROUND('Monthly Summary'!E11*(1+$B$53),2) | G9: =ROUND('Monthly Summary'!E12*(1+$B$53),2) | H9: =ROUND('Monthly Summary'!E13*(1+$B$53),2) | I9: =ROUND('Monthly Summary'!E14*(1+$B$53),2) | J9: =ROUND('Monthly Summary'!E3*(1+$B$53),2) | K9: =ROUND('Monthly Summary'!E4*(1+$B$53),2) | L9: =ROUND('Monthly Summary'!E5*(1+$B$53),2) | M9: =ROUND('Monthly Summary'!E6*(1+$B$53),2) | N9: =SUM(B9:M9)
A10: VARIABLE COSTS (capped @30%) | B10: =ROUND(MIN('Monthly Summary'!F7*(B6/'Monthly Summary'!C7),$B$55*B6),2) | C10: =ROUND(MIN('Monthly Summary'!F8*(C6/'Monthly Summary'!C8),$B$55*C6),2) | D10: =ROUND(MIN('Monthly Summary'!F9*(D6/'Monthly Summary'!C9),$B$55*D6),2) | E10: =ROUND(MIN('Monthly Summary'!F10*(E6/'Monthly Summary'!C10),$B$55*E6),2) | F10: =ROUND(MIN('Monthly Summary'!F11*(F6/'Monthly Summary'!C11),$B$55*F6),2) | G10: =ROUND(MIN('Monthly Summary'!F12*(G6/'Monthly Summary'!C12),$B$55*G6),2) | H10: =ROUND(MIN('Monthly Summary'!F13*(H6/'Monthly Summary'!C13),$B$55*H6),2) | I10: =ROUND(MIN('Monthly Summary'!F14*(I6/'Monthly Summary'!C14),$B$55*I6),2) | J10: =ROUND(MIN('Monthly Summary'!F3*(J6/'Monthly Summary'!C3),$B$55*J6),2) | K10: =ROUND(MIN('Monthly Summary'!F4*(K6/'Monthly Summary'!C4),$B$55*K6),2) | L10: =ROUND(MIN('Monthly Summary'!F5*(L6/'Monthly Summary'!C5),$B$55*L6),2) | M10: =ROUND(MIN('Monthly Summary'!F6*(M6/'Monthly Summary'!C6),$B$55*M6),2) | N10: =SUM(B10:M10)
A11: ALL OPERATING COSTS | B11: =B8+B9+B10 | C11: =C8+C9+C10 | D11: =D8+D9+D10 | E11: =E8+E9+E10 | F11: =F8+F9+F10 | G11: =G8+G9+G10 | H11: =H8+H9+H10 | I11: =I8+I9+I10 | ... M11: =M8+M9+M10 | N11: =SUM(B11:M11)
A12: Director Salary — Elliot Scott (£30,000 pa / £2,500/month fixed) | B12: =$B$54/12 | C12: =$B$54/12 | D12: =$B$54/12 | E12: =$B$54/12 | F12: =$B$54/12 | G12: =$B$54/12 | H12: =$B$54/12 | I12: =$B$54/12 | ... M12: =$B$54/12 | N12: =$B$54
A13: RENT (quarterly — Aug, Nov, Feb) | E13: =ROUND($B$56*(B6+C6+D6),2) | H13: =ROUND($B$56*(E6+F6+G6),2) | K13: =ROUND($B$56*(H6+I6+J6),2) | N13: =E13+H13+K13
A14: VAT DIFFERENCE | B14: =ROUND('Monthly Summary'!H7*(B6/'Monthly Summary'!C7),2) | C14: =ROUND('Monthly Summary'!H8*(C6/'Monthly Summary'!C8),2) | D14: =ROUND('Monthly Summary'!H9*(D6/'Monthly Summary'!C9),2) | E14: =ROUND('Monthly Summary'!H10*(E6/'Monthly Summary'!C10),2) | F14: =ROUND('Monthly Summary'!H11*(F6/'Monthly Summary'!C11),2) | G14: =ROUND('Monthly Summary'!H12*(G6/'Monthly Summary'!C12),2) | H14: =ROUND('Monthly Summary'!H13*(H6/'Monthly Summary'!C13),2) | I14: =ROUND('Monthly Summary'!H14*(I6/'Monthly Summary'!C14),2) | J14: =ROUND('Monthly Summary'!H3*(J6/'Monthly Summary'!C3),2) | K14: =ROUND('Monthly Summary'!H4*(K6/'Monthly Summary'!C4),2) | L14: =ROUND('Monthly Summary'!H5*(L6/'Monthly Summary'!C5),2) | M14: =ROUND('Monthly Summary'!H6*(M6/'Monthly Summary'!C6),2) | N14: =SUM(B14:M14)
A15: PROFIT BEFORE DIRECTOR SALARY | B15: =B6-B11-B14 | C15: =C6-C11-C14 | D15: =D6-D11-D14 | E15: =E6-E11-E14 | F15: =F6-F11-F14 | G15: =G6-G11-G14 | H15: =H6-H11-H14 | I15: =I6-I11-I14 | ... M15: =M6-M11-M14 | N15: =SUM(B15:M15)
A16: FORECAST PROFIT (after director salary of £30,000 pa) | B16: =B15-B12 | C16: =C15-C12 | D16: =D15-D12 | E16: =E15-E12 | F16: =F15-F12 | G16: =G15-G12 | H16: =H15-H12 | I16: =I15-I12 | ... M16: =M15-M12 | N16: =SUM(B16:M16)
A17: PROFIT MARGIN % | B17: =IF(B6<>0,B16/B6,0) | C17: =IF(C6<>0,C16/C6,0) | D17: =IF(D6<>0,D16/D6,0) | E17: =IF(E6<>0,E16/E6,0) | F17: =IF(F6<>0,F16/F6,0) | G17: =IF(G6<>0,G16/G6,0) | H17: =IF(H6<>0,H16/H6,0) | I17: =IF(I6<>0,I16/I6,0) | ... N17: =IF(N6<>0,N16/N6,0)
A19: RENT NOTE: Deposit of £27,078 covers months 1–3 (May, Jun, Jul). Rent paid quarterly: Aug 2026 = £25,992 | Nov 2026 = £31,659 | Feb 2027 = £41,968 | Total paid in period: £99,618 | Q4 rent £28,315 due May 2027. Full-year rent obligation (15% of £852,891): £127,934.
A20: PERIOD SUMMARY
A21: Metric | B21: 2025 Equiv Base | F21: 2026/27 Forecast | J21: Change £
A22: Revenue | B22: ='Monthly Summary'!C15 | F22: =N6 | J22: =N6-B22
A23: Operating Costs | B23: ='Monthly Summary'!D15 | F23: =N11 | J23: =N11-B23
A24: Forecast Profit (after director salary) | B24: ='Monthly Summary'!I15 | F24: =N16 | J24: =N16-B24
A28: FORECAST VALIDATION CHECKS — Independent recalculation (Expected ≠ Actual link)
A29: Each Expected value is INDEPENDENTLY recalculated from raw 2025 data and parameter cells. Status flips to ERROR if the model diverges from the formula by more than £1. Assumptions: B51=Growth%, B52=Fixed uplift%, B53=Dir salary, B54=Var cap, B55=Rent%.
A30: Check | B30: Expected (independent recalc) | C30: Actual (model reports) | D30: Δ Diff | E30: Status | F30: Δ Diff | G30: Status
A31: Revenue total — 2025 base × (1+growth%) × SW ÷ WGT | B31: =ROUND(SUMPRODUCT(B5:M5*(1+$B$52)*B60:M60/$B$61),2) | C31: =N6 | D31: =ABS(B31-C31) | E31: =IF(ABS(B31-C31)<1,"✓ OK","✗ ERROR")
A32: Fixed Overheads — 2025 base × (1+fixed uplift%) | B32: =ROUND('Monthly Summary'!E15*(1+$B$53),2) | C32: =N9 | D32: =ABS(B32-C32) | E32: =IF(ABS(B32-C32)<1,"✓ OK","✗ ERROR")
A33: Wages total — must equal 2025 actual wages exactly | B33: ='Monthly Summary'!G15 | C33: =N8 | D33: =ABS(B33-C33) | E33: =IF(ABS(B33-C33)<1,"✓ OK","✗ ERROR")
A34: Variable Costs — 2025 base scaled with revenue, capped | B34: =SUM(ROUND(MIN('Monthly Summary'!F7*(B6/'Monthly Summary'!C7),$B$55*B6),2),ROUND(MIN('Monthly Summary'!F8*(C6/'Monthly Summary'!C8),$B$55*C6),2),ROUND(MIN('Monthly Summary'!F9*(D6/'Monthly Summary'!C9),$B$55*D6),2),ROUND(MIN('Monthly Summary'!F10*(E6/'Monthly Summary'!C10),$B$55*E6),2),ROUND(MIN('Monthly Summary'!F11*(F6/'Monthly Summary'!C11),$B$55*F6),2),ROUND(MIN('Monthly Summary'!F12*(G6/'Monthly Summary'!C12),$B$55*G6),2),ROUND(MIN('Monthly Summary'!F13*(H6/'Monthly Summary'!C13),$B$55*H6),2),ROUND(MIN('Monthly Summary'!F14*(I6/'Monthly Summary'!C14),$B$55*I6),2),ROUND(MIN('Monthly Summary'!F3*(J6/'Monthly Summary'!C3),$B$55*J6),2),ROUND(MIN('Monthly Summary'!F4*(K6/'Monthly Summary'!C4),$B$55*K6),2),ROUND(MIN('Monthly Summary'!F5*(L6/'Monthly Summary'!C5),$B$55*L6),2),ROUND(MIN('Monthly Summary'!F6*(M6/'Monthly Summary'!C6),$B$55*M6),2)) | C34: =N10 | D34: =ABS(B34-C34) | E34: =IF(ABS(B34-C34)<1,"✓ OK","✗ ERROR")
A35: All Operating Costs = Wages + Fixed + Variable | B35: =N8+N9+N10 | C35: =N11 | D35: =ABS(B35-C35) | E35: =IF(ABS(B35-C35)<1,"✓ OK","✗ ERROR")
A36: Director Salary total = annual param | B36: =$B$54 | C36: =N12 | D36: =ABS(B36-C36) | E36: =IF(ABS(B36-C36)<1,"✓ OK","✗ ERROR")
A37: Profit before dir. salary = Revenue − OpCosts − VAT | B37: =N6-N11-N14 | C37: =N15 | D37: =ABS(B37-C37) | E37: =IF(ABS(B37-C37)<1,"✓ OK","✗ ERROR")
A38: Profit after dir. salary = Profit before − Dir Salary | B38: =N15-N12 | C38: =N16 | D38: =ABS(B38-C38) | E38: =IF(ABS(B38-C38)<1,"✓ OK","✗ ERROR")
A39: Rent paid = 15% of Q1+Q2+Q3 revenues | B39: =ROUND($B$56*(B6+C6+D6),2)+ROUND($B$56*(E6+F6+G6),2)+ROUND($B$56*(H6+I6+J6),2) | C39: =N13 | D39: =ABS(B39-C39) | E39: =IF(ABS(B39-C39)<1,"✓ OK","✗ ERROR")
A40: VAT difference — proportional to revenue | B40: =ROUND('Monthly Summary'!H15*(N6/'Monthly Summary'!C15),2) | C40: =N14 | D40: =ABS(B40-C40) | E40: =IF(ABS(B40-C40)<1,"✓ OK","✗ ERROR")
A42: FORMULA CONSISTENCY CHECK — All months must use identical formula structure
A43: Forecast Rev (row 6) | B43: Fixed OH (row 9) | C43: Variable (row 10) | D43: Profit (row 16) | E43: VAT (row 14)
A44: ✓ Consistent | B44: ✓ Consistent | C44: ✓ Consistent | D44: ✓ Consistent | E44: ✓ Consistent
A51: FORECAST ASSUMPTION INPUTS — Edit these cells to update the entire model
A52: Revenue Growth % | B52: =IFERROR(VLOOKUP(Inputs!C6,'Base Case Forecast'!$A$66:$B$68,2,FALSE()),0.15)
A53: Fixed Cost Uplift % (business rates & energy) | B53: 0.1
A54: Director Salary (annual £) | B54: 30000
A55: Variable Cost Cap (% of revenue) | B55: 0.3
A56: Rent % of quarterly revenue | B56: 0.15
A58: SEASONAL WEIGHTS (do not edit — derived from 2025 trading patterns)
B59: May | C59: Jun | D59: Jul | E59: Aug | F59: Sep | G59: Oct | H59: Nov | I59: Dec | J59: Jan | K59: Feb | L59: Mar | M59: Apr
B60: 0.85 | C60: 0.9 | D60: 1.1 | E60: 1.3 | F60: 1.22 | G60: 1.12 | H60: 1.28 | I60: 1.38 | J60: 0.78 | K60: 0.92 | L60: 0.95 | M60: 1.1
A61: Weighted Avg (WGT) | B61: =SUMPRODUCT(B60:M60,B5:M5)/SUM(B5:M5)
A65: SCENARIO GROWTH RATE TABLE (do not edit — drives scenario toggle)
A66: Conservative | B66: ='Scenario Planning'!B93
A67: Base Case | B67: 0.15
A68: Optimistic | B68: ='Scenario Planning'!B95

Sheet Scenario Planning
A1: ⚠ EDIT ONLY YELLOW CELLS — ALL OTHER CELLS ARE LOCKED AND PROTECTED
A2: NO DICE BOROUGH — SCENARIO PLANNING | May 2026 – April 2027
A3: Three revenue scenarios vs 2025 equivalent-month base of £741,644 | Costs: 2025 base + 10% fixed | Variable capped @30% | Rent quarterly in arrears at 15% | Deposit covers May–Jul
A5: HOW PROFIT IS CALCULATED
A6: Component | B6: Equiv Period 2025 | D6: Notes
A7: Total Revenue (May–Apr equiv period 2025) | B7: ='Monthly Summary'!C15 | D7: 12-month equivalent period using 2025 actuals
A8: Less: All Operating Costs | B8: =-'Monthly Summary'!D15 | D8: Wages + fixed overheads + variable costs
A9: Less: VAT Difference (net paid to HMRC) | B9: =-'Monthly Summary'!H15 | D9: Output VAT minus input VAT reclaimed — paid quarterly
A10: PROFIT (equiv period 2025) | B10: =B7+B8+B9 | D10: Base profit before forecast uplift
A12: KEY SEASONAL DRIVERS | May 2026 – April 2027
A13: Month | B13: 2025 Equiv | D13: Season Driver & Key Dates
A14: May 2026 | B14: ='Monthly Summary'!C3 | D14: Grand reopening | Bank hols 4 & 26 May | DJ nights launch | Garden season opens
A15: June 2026 | B15: ='Monthly Summary'!C3 | D15: Corporate Q2 close events | University leavers | Wimbledon late Jun | DJ nights
A16: July 2026 | B16: ='Monthly Summary'!C3 | D16: Schools out ~22 Jul | Families + student events | Weekly DJ nights | World Cup if applicable
A17: August 2026 | B17: ='Monthly Summary'!C3 | D17: ★★★ Peak — school holidays all month | Garden bar | DJ nights | Bank hol 31 Aug
A18: September 2026 | B18: ='Monthly Summary'!C3 | D18: ★★★ University FRESHERS mid-Sep — biggest new-customer window | Leagues restart
A19: October 2026 | B19: ='Monthly Summary'!C3 | D19: ★★ School half term 26–30 Oct | Halloween ticketed events | Corporate Q3 close
A20: November 2026 | B20: ='Monthly Summary'!C3 | D20: ★★★ Christmas corporate season starts | Office parties | DJ nights | Private hires
A21: December 2026 | B21: ='Monthly Summary'!C3 | D21: ★★★ PEAK — Christmas corporate + NYE | Proven £121k base in 2025
A22: January 2027 | B22: ='Monthly Summary'!C15 | D22: ★ Students return ~12 Jan | Post-Xmas quiet | DJ nights | Community leagues
A23: February 2027 | B23: ='Monthly Summary'!C3 | D23: Half term 16–20 Feb | Valentine's events | Q4 rent payment month
A24: March 2027 | B24: ='Monthly Summary'!C3 | D24: Corporate Q1 close events | Spring build | University term
A25: April 2027 | B25: ='Monthly Summary'!C3 | D25: ★ Easter 2–6 Apr | School half term | Last month of trading period
A27: ⚠ CONSERVATIVE — +10% | Target: £815,809 | Profit: £196,417 | Margin: 24.1%
A28: Lower relaunch. DJ programme building. Corporate season partially secured.
A29: =" Revenue Target: "&TEXT(P32,"£#,##0") | D29: =IF(P32>0,"Conservative Revenue: £"&TEXT(P32,"#,##0")&" | Uplift vs 2025: £"&TEXT(P32-'Monthly Summary'!C15,"#,##0"),"") | G29: Operating Costs: £532,309 | J29: Profit after dir. salary: £166,417 | M29: Rent Paid in Period: £95,162
A31: Metric | B31: May 2026 | C31: Jun 2026 | D31: Jul 2026 | E31: Aug 2026 | F31: Sep 2026 | G31: Oct 2026 | H31: Nov 2026 | I31: Dec 2026 | J31: Jan 2027 | K31: Feb 2027 | L31: Mar 2027 | M31: Apr 2027 | P31: TOTAL
A32: 2025 Equiv Revenue | B32: ='Monthly Summary'!C7*(1+$B$93) | C32: ='Monthly Summary'!C8*(1+$B$93) | D32: ='Monthly Summary'!C9*(1+$B$93) | E32: ='Monthly Summary'!C10*(1+$B$93) | F32: ='Monthly Summary'!C11*(1+$B$93) | G32: ='Monthly Summary'!C12*(1+$B$93) | H32: ='Monthly Summary'!C13*(1+$B$93) | I32: ='Monthly Summary'!C14*(1+$B$93) | J32: ='Monthly Summary'!C3*(1+$B$93) | K32: ='Monthly Summary'!C4*(1+$B$93) | L32: ='Monthly Summary'!C5*(1+$B$93) | M32: ='Monthly Summary'!C6*(1+$B$93) | P32: ='Monthly Summary'!C15
A33: +10% Target | B33: =B32 | C33: =C32 | D33: =D32 | E33: =E32 | F33: =F32 | G33: =G32 | H33: =H32 | I33: =I32 | ... M33: =M32 | P33: =SUM(B32:M32)
A34: Revenue Uplift | B34: =B32-B31 | C34: =C32-C31 | D34: =D32-D31 | E34: =E32-E31 | F34: =F32-F31 | G34: =G32-G31 | H34: =H32-H31 | I34: =I32-I31 | ... M34: =M32-M31 | P34: =SUM(B33:M33)
A35: Operating Costs | B35: =ROUND('Monthly Summary'!G7+'Monthly Summary'!E7*(1+$B$96)+MIN('Monthly Summary'!F7*(B32/'Monthly Summary'!C7),$B$97*B32),2) | C35: =ROUND('Monthly Summary'!G8+'Monthly Summary'!E8*(1+$B$96)+MIN('Monthly Summary'!F8*(C32/'Monthly Summary'!C8),$B$97*C32),2) | D35: =ROUND('Monthly Summary'!G9+'Monthly Summary'!E9*(1+$B$96)+MIN('Monthly Summary'!F9*(D32/'Monthly Summary'!C9),$B$97*D32),2) | E35: =ROUND('Monthly Summary'!G10+'Monthly Summary'!E10*(1+$B$96)+MIN('Monthly Summary'!F10*(E32/'Monthly Summary'!C10),$B$97*E32),2) | F35: =ROUND('Monthly Summary'!G11+'Monthly Summary'!E11*(1+$B$96)+MIN('Monthly Summary'!F11*(F32/'Monthly Summary'!C11),$B$97*F32),2) | G35: =ROUND('Monthly Summary'!G12+'Monthly Summary'!E12*(1+$B$96)+MIN('Monthly Summary'!F12*(G32/'Monthly Summary'!C12),$B$97*G32),2) | H35: =ROUND('Monthly Summary'!G13+'Monthly Summary'!E13*(1+$B$96)+MIN('Monthly Summary'!F13*(H32/'Monthly Summary'!C13),$B$97*H32),2) | I35: =ROUND('Monthly Summary'!G14+'Monthly Summary'!E14*(1+$B$96)+MIN('Monthly Summary'!F14*(I32/'Monthly Summary'!C14),$B$97*I32),2) | J35: =ROUND('Monthly Summary'!G3+'Monthly Summary'!E3*(1+$B$96)+MIN('Monthly Summary'!F3*(J32/'Monthly Summary'!C3),$B$97*J32),2) | K35: =ROUND('Monthly Summary'!G4+'Monthly Summary'!E4*(1+$B$96)+MIN('Monthly Summary'!F4*(K32/'Monthly Summary'!C4),$B$97*K32),2) | L35: =ROUND('Monthly Summary'!G5+'Monthly Summary'!E5*(1+$B$96)+MIN('Monthly Summary'!F5*(L32/'Monthly Summary'!C5),$B$97*L32),2) | M35: =ROUND('Monthly Summary'!G6+'Monthly Summary'!E6*(1+$B$96)+MIN('Monthly Summary'!F6*(M32/'Monthly Summary'!C6),$B$97*M32),2) | P35: =SUM(B34:M34)
A36: Director Salary (£30,000 pa / £2,500/month) | B36: =$B$98/12 | C36: =$B$98/12 | D36: =$B$98/12 | E36: =$B$98/12 | F36: =$B$98/12 | G36: =$B$98/12 | H36: =$B$98/12 | I36: =$B$98/12 | ... M36: =$B$98/12 | P36: =$B$98
A37: Rent (quarterly) | E37: =ROUND($B$97*(B32+C32+D32),2) | H37: =ROUND($B$97*(E32+F32+G32),2) | K37: =ROUND($B$97*(H32+I32+J32),2) | P37: =E36+H36+K36
A38: VAT Difference | B38: =ROUND('Monthly Summary'!H7*(B32/'Monthly Summary'!C7),2) | C38: =ROUND('Monthly Summary'!H8*(C32/'Monthly Summary'!C8),2) | D38: =ROUND('Monthly Summary'!H9*(D32/'Monthly Summary'!C9),2) | E38: =ROUND('Monthly Summary'!H10*(E32/'Monthly Summary'!C10),2) | F38: =ROUND('Monthly Summary'!H11*(F32/'Monthly Summary'!C11),2) | G38: =ROUND('Monthly Summary'!H12*(G32/'Monthly Summary'!C12),2) | H38: =ROUND('Monthly Summary'!H13*(H32/'Monthly Summary'!C13),2) | I38: =ROUND('Monthly Summary'!H14*(I32/'Monthly Summary'!C14),2) | J38: =ROUND('Monthly Summary'!H3*(J32/'Monthly Summary'!C3),2) | K38: =ROUND('Monthly Summary'!H4*(K32/'Monthly Summary'!C4),2) | L38: =ROUND('Monthly Summary'!H5*(L32/'Monthly Summary'!C5),2) | M38: =ROUND('Monthly Summary'!H6*(M32/'Monthly Summary'!C6),2) | P38: =SUM(B37:M37)
A39: Forecast Profit (after director salary) | B39: =B32-B34-B35-B37 | C39: =C32-C34-C35-C37 | D39: =D32-D34-D35-D37 | E39: =E32-E34-E35-E37 | F39: =F32-F34-F35-F37 | G39: =G32-G34-G35-G37 | H39: =H32-H34-H35-H37 | I39: =I32-I34-I35-I37 | ... M39: =M32-M34-M35-M37 | P39: =SUM(B38:M38)
A40: Profit Margin % | B40: =IF(B32<>0,B38/B32,0) | C40: =IF(C32<>0,C38/C32,0) | D40: =IF(D32<>0,D38/D32,0) | E40: =IF(E32<>0,E38/E32,0) | F40: =IF(F32<>0,F38/F32,0) | G40: =IF(G32<>0,G38/G32,0) | H40: =IF(H32<>0,H38/H32,0) | I40: =IF(I32<>0,I38/I32,0) | ... M40: =IF(M32<>0,M38/M32,0) | P40: =IF(P32<>0,P38/P32,0)
A41: RENT: Deposit covers May–Jul. Aug 2026=£25,018 Nov 2026=£30,174 Feb 2027=£39,970 (Q4 £27,209 due May 2027)
A44: ✓ BASE CASE — +15% | Target: £852,891 | Profit: £225,277 | Margin: 26.4%
A45: Full DJ schedule. Christmas corporate booked. Freshers drives September surge.
A46: Revenue Target: £852,891 | D46: vs 2025 Base: +£111,247 (+15.0%) | G46: Operating Costs: £536,536 | J46: Profit after dir. salary: £195,277 | M46: Rent Paid in Period: £99,618
A48: Metric | B48: ='Monthly Summary'!C7*(1+$B$94) | C48: ='Monthly Summary'!C8*(1+$B$94) | D48: ='Monthly Summary'!C9*(1+$B$94) | E48: ='Monthly Summary'!C10*(1+$B$94) | F48: ='Monthly Summary'!C11*(1+$B$94) | G48: ='Monthly Summary'!C12*(1+$B$94) | H48: ='Monthly Summary'!C13*(1+$B$94) | I48: ='Monthly Summary'!C14*(1+$B$94) | J48: ='Monthly Summary'!C3*(1+$B$94) | K48: ='Monthly Summary'!C4*(1+$B$94) | L48: ='Monthly Summary'!C5*(1+$B$94) | M48: ='Monthly Summary'!C6*(1+$B$94) | P48: ='Monthly Summary'!C15
A49: 2025 Equiv Revenue | B49: ='Base Case Forecast'!B5 | C49: ='Base Case Forecast'!C5 | D49: ='Base Case Forecast'!D5 | E49: ='Base Case Forecast'!E5 | F49: ='Base Case Forecast'!F5 | G49: ='Base Case Forecast'!G5 | H49: ='Base Case Forecast'!H5 | I49: ='Base Case Forecast'!I5 | ... M49: ='Base Case Forecast'!M5 | P49: ='Base Case Forecast'!N5
A50: +15% Target | B50: =B48-B47 | C50: =C48-C47 | D50: =D48-D47 | E50: =E48-E47 | F50: =F48-F47 | G50: =G48-G47 | H50: =H48-H47 | I50: =I48-I47 | ... M50: =M48-M47 | P50: =SUM(B49:M49)
A51: Operating Costs (Wages+Fixed+Var) | B51: =ROUND('Monthly Summary'!G7+'Monthly Summary'!E7*(1+$B$96)+MIN('Monthly Summary'!F7*(B48/'Monthly Summary'!C7),$B$97*B48),2) | C51: =ROUND('Monthly Summary'!G8+'Monthly Summary'!E8*(1+$B$96)+MIN('Monthly Summary'!F8*(C48/'Monthly Summary'!C8),$B$97*C48),2) | D51: =ROUND('Monthly Summary'!G9+'Monthly Summary'!E9*(1+$B$96)+MIN('Monthly Summary'!F9*(D48/'Monthly Summary'!C9),$B$97*D48),2) | E51: =ROUND('Monthly Summary'!G10+'Monthly Summary'!E10*(1+$B$96)+MIN('Monthly Summary'!F10*(E48/'Monthly Summary'!C10),$B$97*E48),2) | F51: =ROUND('Monthly Summary'!G11+'Monthly Summary'!E11*(1+$B$96)+MIN('Monthly Summary'!F11*(F48/'Monthly Summary'!C11),$B$97*F48),2) | G51: =ROUND('Monthly Summary'!G12+'Monthly Summary'!E12*(1+$B$96)+MIN('Monthly Summary'!F12*(G48/'Monthly Summary'!C12),$B$97*G48),2) | H51: =ROUND('Monthly Summary'!G13+'Monthly Summary'!E13*(1+$B$96)+MIN('Monthly Summary'!F13*(H48/'Monthly Summary'!C13),$B$97*H48),2) | I51: =ROUND('Monthly Summary'!G14+'Monthly Summary'!E14*(1+$B$96)+MIN('Monthly Summary'!F14*(I48/'Monthly Summary'!C14),$B$97*I48),2) | J51: =ROUND('Monthly Summary'!G3+'Monthly Summary'!E3*(1+$B$96)+MIN('Monthly Summary'!F3*(J48/'Monthly Summary'!C3),$B$97*J48),2) | K51: =ROUND('Monthly Summary'!G4+'Monthly Summary'!E4*(1+$B$96)+MIN('Monthly Summary'!F4*(K48/'Monthly Summary'!C4),$B$97*K48),2) | L51: =ROUND('Monthly Summary'!G5+'Monthly Summary'!E5*(1+$B$96)+MIN('Monthly Summary'!F5*(L48/'Monthly Summary'!C5),$B$97*L48),2) | M51: =ROUND('Monthly Summary'!G6+'Monthly Summary'!E6*(1+$B$96)+MIN('Monthly Summary'!F6*(M48/'Monthly Summary'!C6),$B$97*M48),2) | P51: ='Base Case Forecast'!N10
A52: Director Salary | B52: =$B$98/12 | C52: =$B$98/12 | D52: =$B$98/12 | E52: =$B$98/12 | F52: =$B$98/12 | G52: =$B$98/12 | H52: =$B$98/12 | I52: =$B$98/12 | ... M52: =$B$98/12 | P52: =$B$98
A53: Rent (quarterly) | B53: ='Base Case Forecast'!B53/12 | C53: ='Base Case Forecast'!B53/12 | D53: ='Base Case Forecast'!B53/12 | E53: =ROUND($B$97*(B48+C48+D48),2) | F53: ='Base Case Forecast'!B53/12 | G53: ='Base Case Forecast'!B53/12 | H53: =ROUND($B$97*(E48+F48+G48),2) | I53: ='Base Case Forecast'!B53/12 | J53: ='Base Case Forecast'!B53/12 | K53: =ROUND($B$97*(H48+I48+J48),2) | L53: ='Base Case Forecast'!B53/12 | M53: ='Base Case Forecast'!B53/12 | P53: =E52+H52+K52
A54: Rent (quarterly) | B54: =ROUND('Monthly Summary'!H7*(B48/'Monthly Summary'!C7),2) | C54: =ROUND('Monthly Summary'!H8*(C48/'Monthly Summary'!C8),2) | D54: =ROUND('Monthly Summary'!H9*(D48/'Monthly Summary'!C9),2) | E54: =ROUND('Monthly Summary'!H10*(E48/'Monthly Summary'!C10),2) | F54: =ROUND('Monthly Summary'!H11*(F48/'Monthly Summary'!C11),2) | G54: =ROUND('Monthly Summary'!H12*(G48/'Monthly Summary'!C12),2) | H54: =ROUND('Monthly Summary'!H13*(H48/'Monthly Summary'!C13),2) | I54: =ROUND('Monthly Summary'!H14*(I48/'Monthly Summary'!C14),2) | J54: =ROUND('Monthly Summary'!H3*(J48/'Monthly Summary'!C3),2) | K54: =ROUND('Monthly Summary'!H4*(K48/'Monthly Summary'!C4),2) | L54: =ROUND('Monthly Summary'!H5*(L48/'Monthly Summary'!C5),2) | M54: =ROUND('Monthly Summary'!H6*(M48/'Monthly Summary'!C6),2) | P54: ='Base Case Forecast'!N13
A55: VAT Difference | B55: =B48-B50-B51-B53 | C55: =C48-C50-C51-C53 | D55: =D48-D50-D51-D53 | E55: =E48-E50-E51-E53 | F55: =F48-F50-F51-F53 | G55: =G48-G50-G51-G53 | H55: =H48-H50-H51-H53 | I55: =I48-I50-I51-I53 | ... M55: =M48-M50-M51-M53 | P55: =SUM(B54:M54)
A56: Forecast Profit (after director salary)
A57: Profit Margin % | B57: =IF(B48<>0,B54/B48,0) | C57: =IF(C48<>0,C54/C48,0) | D57: =IF(D48<>0,D54/D48,0) | E57: =IF(E48<>0,E54/E48,0) | F57: =IF(F48<>0,F54/F48,0) | G57: =IF(G48<>0,G54/G48,0) | H57: =IF(H48<>0,H54/H48,0) | I57: =IF(I48<>0,I54/I48,0) | ... M57: =IF(M48<>0,M54/M48,0) | P57: =IF(P48<>0,P54/P48,0)
A58: RENT: Deposit covers May–Jul. Aug 2026=£25,992 Nov 2026=£31,659 Feb 2027=£41,968 (Q4 £28,315 due May 2027)
A61: ★ OPTIMISTIC — +20% | Target: £889,973 | Profit: £254,137 | Margin: 28.6%
A62: Every driver at capacity. November–December at full corporate hire. All peaks maximised. | B62: ='Monthly Summary'!C7*(1+$B$95) | C62: ='Monthly Summary'!C8*(1+$B$95) | D62: ='Monthly Summary'!C9*(1+$B$95) | E62: ='Monthly Summary'!C10*(1+$B$95) | F62: ='Monthly Summary'!C11*(1+$B$95) | G62: ='Monthly Summary'!C12*(1+$B$95) | H62: ='Monthly Summary'!C13*(1+$B$95) | I62: ='Monthly Summary'!C14*(1+$B$95) | J62: ='Monthly Summary'!C3*(1+$B$95) | K62: ='Monthly Summary'!C4*(1+$B$95) | L62: ='Monthly Summary'!C5*(1+$B$95) | M62: ='Monthly Summary'!C6*(1+$B$95) | P62: ='Monthly Summary'!C15
A63: Revenue Target: £889,973 | B63: =B62 | C63: =C62 | D63: =D62 | E63: =E62 | F63: =F62 | G63: =G62 | H63: =H62 | I63: =I62 | ... M63: =M62 | P63: =SUM(B62:M62)
B64: =B62-B61 | C64: =C62-C61 | D64: =D62-D61 | E64: =E62-E61 | F64: =F62-F61 | G64: =G62-G61 | H64: =H62-H61 | I64: =I62-I61 | ... M64: =M62-M61 | P64: =SUM(B63:M63)
A65: Metric | B65: =ROUND('Monthly Summary'!G7+'Monthly Summary'!E7*(1+$B$96)+MIN('Monthly Summary'!F7*(B62/'Monthly Summary'!C7),$B$97*B62),2) | C65: =ROUND('Monthly Summary'!G8+'Monthly Summary'!E8*(1+$B$96)+MIN('Monthly Summary'!F8*(C62/'Monthly Summary'!C8),$B$97*C62),2) | D65: =ROUND('Monthly Summary'!G9+'Monthly Summary'!E9*(1+$B$96)+MIN('Monthly Summary'!F9*(D62/'Monthly Summary'!C9),$B$97*D62),2) | E65: =ROUND('Monthly Summary'!G10+'Monthly Summary'!E10*(1+$B$96)+MIN('Monthly Summary'!F10*(E62/'Monthly Summary'!C10),$B$97*E62),2) | F65: =ROUND('Monthly Summary'!G11+'Monthly Summary'!E11*(1+$B$96)+MIN('Monthly Summary'!F11*(F62/'Monthly Summary'!C11),$B$97*F62),2) | G65: =ROUND('Monthly Summary'!G12+'Monthly Summary'!E12*(1+$B$96)+MIN('Monthly Summary'!F12*(G62/'Monthly Summary'!C12),$B$97*G62),2) | H65: =ROUND('Monthly Summary'!G13+'Monthly Summary'!E13*(1+$B$96)+MIN('Monthly Summary'!F13*(H62/'Monthly Summary'!C13),$B$97*H62),2) | I65: =ROUND('Monthly Summary'!G14+'Monthly Summary'!E14*(1+$B$96)+MIN('Monthly Summary'!F14*(I62/'Monthly Summary'!C14),$B$97*I62),2) | J65: =ROUND('Monthly Summary'!G3+'Monthly Summary'!E3*(1+$B$96)+MIN('Monthly Summary'!F3*(J62/'Monthly Summary'!C3),$B$97*J62),2) | K65: =ROUND('Monthly Summary'!G4+'Monthly Summary'!E4*(1+$B$96)+MIN('Monthly Summary'!F4*(K62/'Monthly Summary'!C4),$B$97*K62),2) | L65: =ROUND('Monthly Summary'!G5+'Monthly Summary'!E5*(1+$B$96)+MIN('Monthly Summary'!F5*(L62/'Monthly Summary'!C5),$B$97*L62),2) | M65: =ROUND('Monthly Summary'!G6+'Monthly Summary'!E6*(1+$B$96)+MIN('Monthly Summary'!F6*(M62/'Monthly Summary'!C6),$B$97*M62),2) | P65: =SUM(B64:M64)
A66: 2025 Equiv Revenue | B66: =$B$98/12 | C66: =$B$98/12 | D66: =$B$98/12 | E66: =$B$98/12 | F66: =$B$98/12 | G66: =$B$98/12 | H66: =$B$98/12 | I66: =$B$98/12 | ... M66: =$B$98/12 | P66: =$B$98
A67: +20% Target | E67: =ROUND($B$97*(B62+C62+D62),2) | H67: =ROUND($B$97*(E62+F62+G62),2) | K67: =ROUND($B$97*(H62+I62+J62),2) | P67: =E66+H66+K66
A68: Revenue Uplift | B68: =ROUND('Monthly Summary'!H7*(B62/'Monthly Summary'!C7),2) | C68: =ROUND('Monthly Summary'!H8*(C62/'Monthly Summary'!C8),2) | D68: =ROUND('Monthly Summary'!H9*(D62/'Monthly Summary'!C9),2) | E68: =ROUND('Monthly Summary'!H10*(E62/'Monthly Summary'!C10),2) | F68: =ROUND('Monthly Summary'!H11*(F62/'Monthly Summary'!C11),2) | G68: =ROUND('Monthly Summary'!H12*(G62/'Monthly Summary'!C12),2) | H68: =ROUND('Monthly Summary'!H13*(H62/'Monthly Summary'!C13),2) | I68: =ROUND('Monthly Summary'!H14*(I62/'Monthly Summary'!C14),2) | J68: =ROUND('Monthly Summary'!H3*(J62/'Monthly Summary'!C3),2) | K68: =ROUND('Monthly Summary'!H4*(K62/'Monthly Summary'!C4),2) | L68: =ROUND('Monthly Summary'!H5*(L62/'Monthly Summary'!C5),2) | M68: =ROUND('Monthly Summary'!H6*(M62/'Monthly Summary'!C6),2) | P68: =SUM(B67:M67)
A69: Operating Costs | B69: =B62-B64-B65-B67 | C69: =C62-C64-C65-C67 | D69: =D62-D64-D65-D67 | E69: =E62-E64-E65-E67 | F69: =F62-F64-F65-F67 | G69: =G62-G64-G65-G67 | H69: =H62-H64-H65-H67 | I69: =I62-I64-I65-I67 | ... M69: =M62-M64-M65-M67 | P69: =SUM(B68:M68)
A70: Director Salary (£30,000 pa / £2,500/month) | B70: =IF(B62<>0,B68/B62,0) | C70: =IF(C62<>0,C68/C62,0) | D70: =IF(D62<>0,D68/D62,0) | E70: =IF(E62<>0,E68/E62,0) | F70: =IF(F62<>0,F68/F62,0) | G70: =IF(G62<>0,G68/G62,0) | H70: =IF(H62<>0,H68/H62,0) | I70: =IF(I62<>0,I68/I62,0) | ... M70: =IF(M62<>0,M68/M62,0) | P70: =IF(P62<>0,P68/P62,0)
A71: Rent (quarterly) | E71: =ROUND(0.15*(B62+C62+D62),2) | H71: =ROUND(0.15*(E62+F62+G62),2) | K71: =ROUND(0.15*(H62+I62+J62),2) | P71: =E70+H70+K70
A72: VAT Difference | B72: =ROUND('Monthly Summary'!H7*(B62/'Monthly Summary'!C7),2) | C72: =ROUND('Monthly Summary'!H8*(C62/'Monthly Summary'!C8),2) | D72: =ROUND('Monthly Summary'!H9*(D62/'Monthly Summary'!C9),2) | E72: =ROUND('Monthly Summary'!H10*(E62/'Monthly Summary'!C10),2) | F72: =ROUND('Monthly Summary'!H11*(F62/'Monthly Summary'!C11),2) | G72: =ROUND('Monthly Summary'!H12*(G62/'Monthly Summary'!C12),2) | H72: =ROUND('Monthly Summary'!H13*(H62/'Monthly Summary'!C13),2) | I72: =ROUND('Monthly Summary'!H14*(I62/'Monthly Summary'!C14),2) | J72: =ROUND('Monthly Summary'!H3*(J62/'Monthly Summary'!C3),2) | K72: =ROUND('Monthly Summary'!H4*(K62/'Monthly Summary'!C4),2) | L72: =ROUND('Monthly Summary'!H5*(L62/'Monthly Summary'!C5),2) | M72: =ROUND('Monthly Summary'!H6*(M62/'Monthly Summary'!C6),2) | P72: =SUM(B71:M71)
A73: Forecast Profit (after director salary) | B73: =B62-B64-B65-B71 | C73: =C62-C64-C65-C71 | D73: =D62-D64-D65-D71 | E73: =E62-E64-E65-E71 | F73: =F62-F64-F65-F71 | G73: =G62-G64-G65-G71 | H73: =H62-H64-H65-H71 | I73: =I62-I64-I65-I71 | ... M73: =M62-M64-M65-M71 | P73: =SUM(B72:M72)
A74: Profit Margin % | B74: =IF(B62<>0,B72/B62,0) | C74: =IF(C62<>0,C72/C62,0) | D74: =IF(D62<>0,D72/D62,0) | E74: =IF(E62<>0,E72/E62,0) | F74: =IF(F62<>0,F72/F62,0) | G74: =IF(G62<>0,G72/G62,0) | H74: =IF(H62<>0,H72/H62,0) | I74: =IF(I62<>0,I72/I62,0) | ... M74: =IF(M62<>0,M72/M62,0) | P74: =IF(P62<>0,P72/P62,0)
A75: RENT: Deposit covers May–Jul. Aug 2026=£26,965 Nov 2026=£33,143 Feb 2027=£43,966 (Q4 £29,421 due May 2027)
A78: SCENARIO COMPARISON — Period May 2026 – April 2027
A79: Metric | B79: Conservative +10% | E79: Base Case +15% | H79: Optimistic +20%
A80: Revenue Target | B80: =P32 | E80: =P48 | H80: =P62
A81: Revenue Uplift | B81: =P33 | E81: =P49 | H81: =P63
A82: Operating Costs | B82: =P34 | E82: =P50 | H82: =P64
A83: Director Salary (£30,000 pa / £2,500/month) | B83: ='Base Case Forecast'!B53 | E83: ='Base Case Forecast'!B53 | H83: ='Base Case Forecast'!B53 | K83: ='Base Case Forecast'!B53 | L83: ='Base Case Forecast'!B53 | M83: ='Base Case Forecast'!B53 | P83: ='Base Case Forecast'!B53
A84: Rent Paid in Period | B84: =P36 | E84: =P52 | H84: =P66
A85: Rent Deferred (May 27) | B85: =ROUND(0.15*(K32+L32+M32),2) | E85: =ROUND(0.15*(K48+L48+M48),2) | H85: =ROUND(0.15*(K62+L62+M62),2)
A86: Forecast Profit (after director salary) | B86: =P38 | E86: =P54 | H86: =P72
A87: Profit Margin | B87: =IF(P32<>0,P38/P32,0) | E87: =IF(P48<>0,P54/P48,0) | H87: =IF(P62<>0,P72/P62,0)
A88: All scenarios use 2025 equivalent-month actuals as base. Fixed costs uplifted +10%. Variable capped at 30%. Rent deposit (£27,078) covers May–Jul. Quarterly rent in Aug, Nov, Feb at 15% of previous quarter revenue.
A92: SCENARIO GROWTH RATES — Used in revenue formulas above
A93: Conservative Revenue Growth | B93: 0.1 | C93: SP row 32 formulas reference this
A94: Base Case Revenue Growth | B94: ='Base Case Forecast'!$B$52 | C94: SP rows 48 formulas reference this (matches BCF B51)
A95: Optimistic Revenue Growth | B95: 0.2 | C95: SP row 62 formulas reference this
A96: Fixed Cost Uplift % | B96: ='Base Case Forecast'!$B$53 | C96: Links to BCF param — do not edit
A97: Variable Cost Cap % | B97: ='Base Case Forecast'!$B$55 | C97: Links to BCF param — do not edit
A98: Rent % of quarterly revenue | B98: ='Base Case Forecast'!$B$56 | C98: Links to BCF param — do not edit
A99: Director Salary (annual £) | B99: ='Base Case Forecast'!$B$54 | C99: Links to BCF param — do not edit

Sheet Downside Scenario
A1: ⚠ EDIT ONLY YELLOW CELLS — ALL OTHER CELLS ARE LOCKED AND PROTECTED
A2: NO DICE BOROUGH LTD — DOWNSIDE SCENARIO | Revenue -10% vs 2025 Actuals
A3: ⚠ Stress test: What if revenue is 10% BELOW 2025 actuals? | Wages and fixed costs remain fixed. Variable costs scale with revenue. Rent = 15% of quarterly revenue (also falls). | Does the business remain profitable and cash-positive?
A5: Metric | B5: Wks | C5: May 26 | D5: Jun 26 | E5: Jul 26 | F5: Aug 26 | G5: Sep 26 | H5: Oct 26 | I5: Nov 26 | J5: Dec 26 | K5: Jan 27 | L5: Feb 27 | M5: Mar 27 | N5: Apr 27 | O5: ANNUAL TOTAL
A6: 2025 Base Revenue | C6: ='Monthly Summary'!C7 | D6: ='Monthly Summary'!C8 | E6: ='Monthly Summary'!C9 | F6: ='Monthly Summary'!C10 | G6: ='Monthly Summary'!C11 | H6: ='Monthly Summary'!C12 | I6: ='Monthly Summary'!C13 | J6: ='Monthly Summary'!C14 | K6: ='Monthly Summary'!C3 | L6: ='Monthly Summary'!C4 | M6: ='Monthly Summary'!C5 | N6: ='Monthly Summary'!C6 | O6: ='Monthly Summary'!C15
A7: Downside Revenue (-10%) | C7: =ROUND(C6*(1+$B$51),2) | D7: =ROUND(D6*(1+$B$51),2) | E7: =ROUND(E6*(1+$B$51),2) | F7: =ROUND(F6*(1+$B$51),2) | G7: =ROUND(G6*(1+$B$51),2) | H7: =ROUND(H6*(1+$B$51),2) | I7: =ROUND(I6*(1+$B$51),2) | J7: =ROUND(J6*(1+$B$51),2) | ... N7: =ROUND(N6*(1+$B$51),2) | O7: =SUM(C7:N7)
A8: Revenue vs Base | C8: =C7-C6 | D8: =D7-D6 | E8: =E7-E6 | F8: =F7-F6 | G8: =G7-G6 | H8: =H7-H6 | I8: =I7-I6 | J8: =J7-J6 | ... N8: =N7-N6 | O8: =SUM(C8:N8)
A9: Staff Wages (fixed) | C9: ='Monthly Summary'!G7 | D9: ='Monthly Summary'!G8 | E9: ='Monthly Summary'!G9 | F9: ='Monthly Summary'!G10 | G9: ='Monthly Summary'!G11 | H9: ='Monthly Summary'!G12 | I9: ='Monthly Summary'!G13 | J9: ='Monthly Summary'!G14 | K9: ='Monthly Summary'!G3 | L9: ='Monthly Summary'!G4 | M9: ='Monthly Summary'!G5 | N9: ='Monthly Summary'!G6 | O9: ='Monthly Summary'!G15
A10: Fixed Overheads | C10: ='Monthly Summary'!E7 | D10: ='Monthly Summary'!E8 | E10: ='Monthly Summary'!E9 | F10: ='Monthly Summary'!E10 | G10: ='Monthly Summary'!E11 | H10: ='Monthly Summary'!E12 | I10: ='Monthly Summary'!E13 | J10: ='Monthly Summary'!E14 | K10: ='Monthly Summary'!E3 | L10: ='Monthly Summary'!E4 | M10: ='Monthly Summary'!E5 | N10: ='Monthly Summary'!E6 | O10: ='Monthly Summary'!E15
A11: Variable Costs | C11: =ROUND(MIN('Monthly Summary'!F7*(C7/'Monthly Summary'!C7),$B$52*C7),2) | D11: =ROUND(MIN('Monthly Summary'!F8*(D7/'Monthly Summary'!C8),$B$52*D7),2) | E11: =ROUND(MIN('Monthly Summary'!F9*(E7/'Monthly Summary'!C9),$B$52*E7),2) | F11: =ROUND(MIN('Monthly Summary'!F10*(F7/'Monthly Summary'!C10),$B$52*F7),2) | G11: =ROUND(MIN('Monthly Summary'!F11*(G7/'Monthly Summary'!C11),$B$52*G7),2) | H11: =ROUND(MIN('Monthly Summary'!F12*(H7/'Monthly Summary'!C12),$B$52*H7),2) | I11: =ROUND(MIN('Monthly Summary'!F13*(I7/'Monthly Summary'!C13),$B$52*I7),2) | J11: =ROUND(MIN('Monthly Summary'!F14*(J7/'Monthly Summary'!C14),$B$52*J7),2) | K11: =ROUND(MIN('Monthly Summary'!F3*(K7/'Monthly Summary'!C3),$B$52*K7),2) | L11: =ROUND(MIN('Monthly Summary'!F4*(L7/'Monthly Summary'!C4),$B$52*L7),2) | M11: =ROUND(MIN('Monthly Summary'!F5*(M7/'Monthly Summary'!C5),$B$52*M7),2) | N11: =ROUND(MIN('Monthly Summary'!F6*(N7/'Monthly Summary'!C6),$B$52*N7),2) | O11: =SUM(C11:N11)
A12: All Operating Costs | C12: =C9+C10+C11 | D12: =D9+D10+D11 | E12: =E9+E10+E11 | F12: =F9+F10+F11 | G12: =G9+G10+G11 | H12: =H9+H10+H11 | I12: =I9+I10+I11 | J12: =J9+J10+J11 | ... N12: =N9+N10+N11 | O12: =SUM(C12:N12)
A13: Rent (quarterly) | F13: =ROUND($B$53*(C7+D7+E7),2) | I13: =ROUND($B$53*(F7+G7+H7),2) | L13: =ROUND($B$53*(I7+J7+K7),2) | O13: =F13+I13+L13
A14: VAT Difference | C14: =ROUND('Monthly Summary'!H7*(C7/'Monthly Summary'!C7),2) | D14: =ROUND('Monthly Summary'!H8*(D7/'Monthly Summary'!C8),2) | E14: =ROUND('Monthly Summary'!H9*(E7/'Monthly Summary'!C9),2) | F14: =ROUND('Monthly Summary'!H10*(F7/'Monthly Summary'!C10),2) | G14: =ROUND('Monthly Summary'!H11*(G7/'Monthly Summary'!C11),2) | H14: =ROUND('Monthly Summary'!H12*(H7/'Monthly Summary'!C12),2) | I14: =ROUND('Monthly Summary'!H13*(I7/'Monthly Summary'!C13),2) | J14: =ROUND('Monthly Summary'!H14*(J7/'Monthly Summary'!C14),2) | K14: =ROUND('Monthly Summary'!H3*(K7/'Monthly Summary'!C3),2) | L14: =ROUND('Monthly Summary'!H4*(L7/'Monthly Summary'!C4),2) | M14: =ROUND('Monthly Summary'!H5*(M7/'Monthly Summary'!C5),2) | N14: =ROUND('Monthly Summary'!H6*(N7/'Monthly Summary'!C6),2) | O14: =SUM(C14:N14)
A15: Director Salary | C15: =$B$54/12 | D15: =$B$54/12 | E15: =$B$54/12 | F15: =$B$54/12 | G15: =$B$54/12 | H15: =$B$54/12 | I15: =$B$54/12 | J15: =$B$54/12 | ... N15: =$B$54/12 | O15: =$B$54
A16: PROFIT / (LOSS) | C16: =C7-C12-C13-C14 | D16: =D7-D12-D13-D14 | E16: =E7-E12-E13-E14 | F16: =F7-F12-F13-F14 | G16: =G7-G12-G13-G14 | H16: =H7-H12-H13-H14 | I16: =I7-I12-I13-I14 | J16: =J7-J12-J13-J14 | ... N16: =N7-N12-N13-N14 | O16: =SUM(C16:N16)
A17: Profit Margin % | C17: =IF(C7<>0,C16/C7,0) | D17: =IF(D7<>0,D16/D7,0) | E17: =IF(E7<>0,E16/E7,0) | F17: =IF(F7<>0,F16/F7,0) | G17: =IF(G7<>0,G16/G7,0) | H17: =IF(H7<>0,H16/H7,0) | I17: =IF(I7<>0,I16/I7,0) | J17: =IF(J7<>0,J16/J7,0) | ... O17: =IF(O7<>0,O16/O7,0)
A19: DOWNSIDE KEY FINDINGS
A20: Annual Downside Revenue (−10%) | F20: =O7
A21: Annual Operating Costs | F21: =O12
A22: Annual Director Salary | F22: =O15
A23: Annual VAT | F23: =O14
A24: Rent Paid in Period | F24: =F13+I13+L13
A25: ANNUAL PROFIT (DOWNSIDE) | F25: =O16
A26: Profit Margin | F26: =O17
A27: Business Remains Profitable? | F27: =IF(O16>0,"YES ✓ — Loss-resistant business","NO — Review cost structure")
A28: Cash Buffer vs Safety Threshold | F28: =MIN('Cash Flow Forecast'!B30:M30)-'Cash Flow Forecast'!G39
A51: DOWNSIDE ASSUMPTION INPUTS
A52: Revenue Change vs 2025 | B52: -0.1
A53: Variable Cost Cap % | B53: 0.3
A54: Rent % of quarterly revenue | B54: 0.15
A55: Director Salary (annual £) | B55: ='Base Case Forecast'!B54

Sheet Marketing Budget
A1: ⚠ EDIT ONLY YELLOW CELLS — ALL OTHER CELLS ARE LOCKED AND PROTECTED
A2: NO DICE BOROUGH — MARKETING BUDGET | May 2026 – April 2027 | £500/week Social Media
A3: Additional social media spend: £500/week × 52 weeks = £26,000/year | Budgeted separately from existing 2025 Google spend (already in operating costs) | Shown in parallel with the 6 growth drivers across 3 scenarios
A5: BUDGET OVERVIEW — What £500/week buys and what we expect in return
A6: Weekly Spend | D6: Annual Spend | G6: Conservative ROAS | J6: Base Case ROAS | M6: Optimistic ROAS
A7: £500 | D7: £26,000 | G7: 3.0× | J7: 5.0× | M7: 8.0×
A9: CHANNEL ALLOCATION — How the £500/week is split across platforms
A10: Channel | B10: % of Budget | C10: Weekly | D10: Monthly Avg | E10: Annual | F10: Target Audience & Strategy
A11: Instagram & Facebook Ads | B11: 0.45 | C11: =B11*$C$16 | D11: =C11*52/12 | E11: =C11*52 | F11: Story ads and feed placements targeting Borough within 3-mile radius. Promotes DJ nights, events, gaming packages and seasonal offers.
A12: TikTok Promoted Content | B12: 0.25 | C12: =B12*$C$16 | D12: =C12*52/12 | E12: =C12*52 | F12: Short-form video content targeting 18-30 demographic. Freshers season, DJ nights and gaming highlights. High organic reach multiplier.
A13: Google Display / Search ← REMOVED (covered in Google Budget sheet) | F13: "Bars in Borough", "things to do Borough", "mini golf London" search capture. High intent — visitors actively searching.
A14: Email & WhatsApp Retargeting | B14: 0.1 | C14: =B14*$C$16 | D14: =C14*52/12 | E14: =C14*52 | F14: Re-engagement of existing customer list. Seasonal promotions, event invites and loyalty offers. Lowest cost per conversion.
A15: Influencer / Content Creation | B15: 0.05 | C15: =B15*$C$16 | D15: =C15*52/12 | E15: =C15*52 | F15: Monthly micro-influencer post (10k-50k following). Venue photography and video content for organic and paid use.
A16: TOTAL ANNUAL MARKETING SPEND | B16: =SUM(B10:B11)+SUM(B13:B14) | C16: =500 | D16: =C16*52/12 | E16: =C16*52
A18: MONTHLY MARKETING SPEND & REVENUE RETURN BY SCENARIO
A19: Month | B19: Wks | C19: Mktg Spend | D19: ⚠ Cons Revenue | E19: ⚠ Cons Net | F19: ✓ Base Revenue | G19: ✓ Base Net | H19: ★ Opt Revenue | I19: ★ Opt Net | J19: Cons ROAS | K19: Base ROAS | L19: Opt ROAS
A20: May 2026 | B20: 5 | C20: =$C$16*B20 | D20: =E20-C20 | E20: 4250 | F20: 11250 | G20: =C20*F20 | H20: =G20-C20 | I20: 15500 | J20: 2.7 | K20: =C20*J20 | L20: =K20-C20
A21: June 2026 | B21: 4 | C21: =$C$16*B21 | D21: =E21-C21 | E21: 2800 | F21: 8000 | G21: =C21*F21 | H21: =G21-C21 | I21: 10800 | J21: 2.4 | K21: =C21*J21 | L21: =K21-C21
A22: July 2026 | B22: 4 | C22: =$C$16*B22 | D22: =E22-C22 | E22: 4000 | F22: 10000 | G22: =C22*F22 | H22: =G22-C22 | I22: 14000 | J22: 3 | K22: =C22*J22 | L22: =K22-C22
A23: August 2026 | B23: 5 | C23: =$C$16*B23 | D23: =E23-C23 | E23: 7250 | F23: 16250 | G23: =C23*F23 | H23: =G23-C23 | I23: 23500 | J23: 3.9 | K23: =C23*J23 | L23: =K23-C23
A24: September 2026 | B24: 4 | C24: 2000 | D24: 7800 | E24: 5800 | F24: 13000 | G24: 11000 | H24: 20800 | I24: 18800 | J24: 3.9 | K24: 6.5 | L24: 10.4
A25: October 2026 | B25: 4 | C25: 2000 | D25: 6600 | E25: 4600 | F25: 11000 | G25: 9000 | H25: 17600 | I25: 15600 | J25: 3.3 | K25: 5.5 | L25: 8.8
A26: November 2026 | B26: 5 | C26: 2500 | D26: 10500 | E26: 8000 | F26: 17500 | G26: 15000 | H26: 28000 | I26: 25500 | J26: 4.2 | K26: 7 | L26: 11.2
A27: December 2026 | B27: 4 | C27: 2000 | D27: 8400 | E27: 6400 | F27: 14000 | G27: 12000 | H27: 22400 | I27: 20400 | J27: 4.2 | K27: 7 | L27: 11.2
A28: January 2027 | B28: 4 | C28: 2000 | D28: 4800 | E28: 2800 | F28: 8000 | G28: 6000 | H28: 12800 | I28: 10800 | J28: 2.4 | K28: 4 | L28: 6.4
A29: February 2027 | B29: 4 | C29: 2000 | D29: 5400 | E29: 3400 | F29: 9000 | G29: 7000 | H29: 14400 | I29: 12400 | J29: 2.7 | K29: 4.5 | L29: 7.2
A30: March 2027 | B30: 5 | C30: 2500 | D30: 6750 | E30: 4250 | F30: 11250 | G30: 8750 | H30: 18000 | I30: 15500 | J30: 2.7 | K30: 4.5 | L30: 7.2
A31: April 2027 | B31: 4 | C31: 2000 | D31: 6600 | E31: 4600 | F31: 11000 | G31: 9000 | H31: 17600 | I31: 15600 | J31: 3.3 | K31: 5.5 | L31: 8.8
A32: ANNUAL TOTAL | B32: 52 | C32: 26000 | D32: 84150 | E32: 58150 | F32: 140250 | G32: 114250 | H32: 224400 | I32: 198400 | J32: 3.2 | K32: 5.4 | L32: 8.6
A34: GROWTH DRIVERS ↔ MARKETING SUPPORT — How marketing amplifies each driver
A35: Growth Driver | B35: % of Rev Uplift | C35: Cons £ Target | D35: Base £ Target | E35: Opt £ Target | F35: Key Marketing Channel | I35: How Social Media Amplifies This Driver | M35: Season Peak
A36: Weekly DJ Nights (Fri & Sat) | B36: 0.28 | C36: 20766 | D36: 31149 | E36: 41532 | F36: Instagram & TikTok | I36: Instagram Stories and TikTok clips from DJ nights. £150/wk of budget peaks Nov–Dec and Aug. "Book a table" link in bio drives direct reservations. | M36: Nov,Dec,Aug,Jul
A37: Christmas Corporate Season | B37: 0.26 | C37: 19283 | D37: 28924 | E37: 38566 | F37: Facebook & Email | I37: LinkedIn-targeted Facebook ads + email retargeting to previous customers. Corporate decision-makers respond to early-booking incentives and packages. | M37: Nov,Dec
A38: School Holiday & Family Gaming | B38: 0.18 | C38: 13350 | D38: 20024 | E38: 26699 | F38: Facebook & Google | I38: Facebook family-interest targeting during holiday windows. Google search captures "things to do with kids London" intent. Boosted posts during half terms. | M38: Aug,Apr,Oct
A39: University Freshers & Term Events | B39: 0.14 | C39: 10383 | D39: 15575 | E39: 20766 | F39: TikTok & Instagram | I39: TikTok is dominant in 18-25 demographic. Freshers content goes viral organically. £125/wk of budget concentrated Sep–Oct on student audiences. | M39: Sep,Oct,Jan
A40: Corporate Q-End Private Hire | B40: 0.1 | C40: 7416 | D40: 11125 | E40: 14833 | F40: LinkedIn & Google | I40: Google search for "private hire London bar" and "team night out Borough". LinkedIn ad targeting by company size and job title. Direct booking enquiry capture. | M40: Mar,Jun,Sep
A41: Community Gaming Leagues | B41: 0.04 | C41: 2967 | D41: 4450 | E41: 5933 | F41: Instagram & Email | I41: Instagram content showing league nights. Email newsletter to league members. Referral mechanic — share to unlock free game. | M41: Sep,Jan,Oct
A43: COMBINED P&L — Trading Revenue + Marketing-Generated Revenue vs Operating Costs
A44: Shows each scenario's trading revenue PLUS the additional revenue attributable to the social media marketing budget. Marketing cost (£500/wk) is shown as a separate cost line. Net impact = marketing revenue minus marketing spend.
A45: ⚠ CONSERVATIVE (+10% trading) + MARKETING | Marketing Spend: £26,000 | Marketing Revenue: £84,150 | Net Marketing Contribution: £58,150 | Profit with Marketing: £224,567
A46: Metric | B46: May 2026 | C46: Jun 2026 | D46: Jul 2026 | E46: Aug 2026 | F46: Sep 2026 | G46: Oct 2026 | H46: Nov 2026 | I46: Dec 2026 | J46: Jan 2027 | K46: Feb 2027 | L46: Mar 2027 | M46: Apr 2027 | N46: TOTAL
A47: Trading Revenue (+10%) | B47: 64108 | C47: 51518 | D47: 51159 | E47: 73801 | F47: 62522 | G47: 64838 | H47: 82207 | I47: 136830 | J47: 47429 | K47: 58882 | L47: 65970 | M47: 56544 | N47: 815809
A48: Marketing-Generated Revenue | B48: 6750 | C48: 4800 | D48: 6000 | E48: 9750 | F48: 7800 | G48: 6600 | H48: 10500 | I48: 8400 | J48: 4800 | K48: 5400 | L48: 6750 | M48: 6600 | N48: 84150
A49: COMBINED TOTAL REVENUE | B49: 70858 | C49: 56318 | D49: 57159 | E49: 83551 | F49: 70322 | G49: 71438 | H49: 92707 | I49: 145230 | J49: 52229 | K49: 64282 | L49: 72720 | M49: 63144 | N49: 899959
A50: Marketing Cost (£500/week) | B50: -2500 | C50: -2000 | D50: -2000 | E50: -2500 | F50: -2000 | G50: -2000 | H50: -2500 | I50: -2000 | J50: -2000 | K50: -2000 | L50: -2500 | M50: -2000 | N50: -26000
A51: Net Marketing Contribution | B51: 4250 | C51: 2800 | D51: 4000 | E51: 7250 | F51: 5800 | G51: 4600 | H51: 8000 | I51: 6400 | J51: 2800 | K51: 3400 | L51: 4250 | M51: 4600 | N51: 58150
A52: Profit Before Marketing | N52: 166417
A53: Profit WITH Marketing (after dir. salary) | N53: 224567
A56: ✓ BASE CASE (+15% trading) + MARKETING | Marketing Spend: £26,000 | Marketing Revenue: £140,250 | Net Marketing Contribution: £114,250 | Profit with Marketing: £309,527
A57: Metric | B57: May 2026 | C57: Jun 2026 | D57: Jul 2026 | E57: Aug 2026 | F57: Sep 2026 | G57: Oct 2026 | H57: Nov 2026 | I57: Dec 2026 | J57: Jan 2027 | K57: Feb 2027 | L57: Mar 2027 | M57: Apr 2027 | N57: TOTAL
A58: Trading Revenue (+15%) | B58: 66379 | C58: 53442 | D58: 53456 | E58: 77655 | F58: 65606 | G58: 67798 | H58: 86440 | I58: 144366 | J58: 48980 | K58: 61127 | L58: 68560 | M58: 59083 | N58: 852891
A59: Marketing-Generated Revenue | B59: 11250 | C59: 8000 | D59: 10000 | E59: 16250 | F59: 13000 | G59: 11000 | H59: 17500 | I59: 14000 | J59: 8000 | K59: 9000 | L59: 11250 | M59: 11000 | N59: 140250
A60: COMBINED TOTAL REVENUE | B60: 77629 | C60: 61442 | D60: 63456 | E60: 93905 | F60: 78606 | G60: 78798 | H60: 103940 | I60: 158366 | J60: 56980 | K60: 70127 | L60: 79810 | M60: 70083 | N60: 993141
A61: Marketing Cost (£500/week) | B61: -2500 | C61: -2000 | D61: -2000 | E61: -2500 | F61: -2000 | G61: -2000 | H61: -2500 | I61: -2000 | J61: -2000 | K61: -2000 | L61: -2500 | M61: -2000 | N61: -26000
A62: Net Marketing Contribution | B62: 8750 | C62: 6000 | D62: 8000 | E62: 13750 | F62: 11000 | G62: 9000 | H62: 15000 | I62: 12000 | J62: 6000 | K62: 7000 | L62: 8750 | M62: 9000 | N62: 114250
A63: Profit Before Marketing | N63: 195277
A64: Profit WITH Marketing (after dir. salary) | N64: 309527
A67: ★ OPTIMISTIC (+20% trading) + MARKETING | Marketing Spend: £26,000 | Marketing Revenue: £224,400 | Net Marketing Contribution: £198,400 | Profit with Marketing: £422,537
A68: Metric | B68: May 2026 | C68: Jun 2026 | D68: Jul 2026 | E68: Aug 2026 | F68: Sep 2026 | G68: Oct 2026 | H68: Nov 2026 | I68: Dec 2026 | J68: Jan 2027 | K68: Feb 2027 | L68: Mar 2027 | M68: Apr 2027 | N68: TOTAL
A69: Trading Revenue (+20%) | B69: 68650 | C69: 55366 | D69: 55753 | E69: 81508 | F69: 68689 | G69: 70757 | H69: 90673 | I69: 151902 | J69: 50531 | K69: 63371 | L69: 71150 | M69: 61622 | N69: 889973
A70: Marketing-Generated Revenue | B70: 18000 | C70: 12800 | D70: 16000 | E70: 26000 | F70: 20800 | G70: 17600 | H70: 28000 | I70: 22400 | J70: 12800 | K70: 14400 | L70: 18000 | M70: 17600 | N70: 224400
A71: COMBINED TOTAL REVENUE | B71: 86650 | C71: 68166 | D71: 71753 | E71: 107508 | F71: 89489 | G71: 88357 | H71: 118673 | I71: 174302 | J71: 63331 | K71: 77771 | L71: 89150 | M71: 79222 | N71: 1114373
A72: Marketing Cost (£500/week) | B72: -2500 | C72: -2000 | D72: -2000 | E72: -2500 | F72: -2000 | G72: -2000 | H72: -2500 | I72: -2000 | J72: -2000 | K72: -2000 | L72: -2500 | M72: -2000 | N72: -26000
A73: Net Marketing Contribution | B73: 15500 | C73: 10800 | D73: 14000 | E73: 23500 | F73: 18800 | G73: 15600 | H73: 25500 | I73: 20400 | J73: 10800 | K73: 12400 | L73: 15500 | M73: 15600 | N73: 198400
A74: Profit Before Marketing | N74: 224137
A75: Profit WITH Marketing (after dir. salary) | N75: 422537
A78: SCENARIO COMPARISON — Without vs With Marketing Budget
A79: Metric | B79: Conservative +10% | E79: Base Case +15% | H79: Optimistic +20%
A80: Trading Revenue Target | B80: 815809 | E80: 852891 | H80: 889973
A81: Marketing Revenue Generated | B81: 84150 | E81: 140250 | H81: 224400
A82: Combined Revenue | B82: 899959 | E82: 956059 | H82: 1040209
A83: Marketing Spend | B83: -26000 | E83: -26000 | H83: -26000
A84: Net Marketing Contribution | B84: 58150 | E84: 114250 | H84: 198400
A85: Profit WITHOUT Marketing | B85: 166417 | E85: 195277 | H85: 224137
A86: Profit WITH Marketing | B86: 224567 | E86: 309527 | H86: 422537
A87: Marketing ROAS | B87: 3 | E87: 5 | H87: 8
A89: ROAS (Return on Ad Spend): Conservative = 3× (cautious targeting, build phase) | Base Case = 5× (good creative, established audience) | Optimistic = 8× (strong seasonal peaks, viral content, proven channels). Marketing spend of £26,000/year treated as additional cost separate from existing Google spend in 2025 operating base.

Sheet Google Budget
A1: NO DICE BOROUGH — GOOGLE ANALYTICS 4 DATA | Plonk Golf (GA4) | Jan–Dec 2025
A2: Source: Windsor.ai / GA4 Property ID 386818810 (Plonk Golf) | Period: 1 Jan 2025 – 12 Dec 2025 | v2.0 / 14-Apr-2026
A4: SECTION 1 — SITE-WIDE TRAFFIC (All channels, monthly overview)
A5: Metric | B5: Jan | C5: Feb | D5: Mar | E5: Apr | F5: May | G5: Jun | H5: Jul | I5: Aug | J5: Sep | K5: Oct | L5: Nov | M5: Dec* | N5: Full Year
A6: Sessions | B6: 16042 | C6: 16199 | D6: 13490 | E6: 10510 | F6: 9362 | G6: 8401 | H6: 9577 | I6: 10561 | J6: 9196 | K6: 11343 | L6: 12303 | M6: 3789 | N6: =SUM(B6:M6)
A7: Active Users | B7: 8450 | C7: 8184 | D7: 6737 | E7: 6584 | F7: 6644 | G7: 6014 | H7: 6623 | I7: 7595 | J7: 6325 | K7: 8073 | L7: 8914 | M7: 2785 | N7: =SUM(B7:M7)
A8: New Users | B8: 8147 | C8: 7846 | D8: 6434 | E8: 6263 | F8: 6258 | G8: 5741 | H8: 6356 | I8: 7251 | J8: 6027 | K8: 7792 | L8: 8565 | M8: 2620 | N8: =SUM(B8:M8)
A9: Engaged Sessions | B9: 7632 | C9: 7416 | D9: 6240 | E9: 5700 | F9: 5726 | G9: 5105 | H9: 5826 | I9: 6600 | J9: 5436 | K9: 6973 | L9: 6752 | M9: 2232 | N9: =SUM(B9:M9)
A10: Engagement Rate | B10: 0.4758 | C10: 0.4578 | D10: 0.4626 | E10: 0.5423 | F10: 0.6116 | G10: 0.6077 | H10: 0.6083 | I10: 0.6249 | J10: 0.5911 | K10: 0.6147 | L10: 0.5488 | M10: 0.5891 | N10: =AVERAGE(B10:M10)
A11: Avg Session Duration (s) | B11: 180 | C11: 176 | D11: 174 | E11: 187 | F11: 170 | G11: 190 | H11: 171 | I11: 173 | J11: 163 | K11: 174 | L11: 158 | M11: 182 | N11: =SUM(B11:M11)
A12: Total Page Views | B12: 26187 | C12: 26234 | D12: 21643 | E12: 19563 | F12: 19979 | G12: 17314 | H12: 19516 | I12: 22949 | J12: 18985 | K12: 24494 | L12: 25100 | M12: 7951 | N12: =SUM(B12:M12)
A14: SECTION 2 — CHANNEL BREAKDOWN (Annual sessions, Jan–Dec 2025)
A15: Channel | B15: Annual Sessions | C15: % of Total | D15: Annual Users | E15: New Users | F15: Key Finding
A16: Organic Search | B16: 75366 | C16: 0.58 | D16: 51964 | E16: 49166 | F16: ★ Primary traffic driver. 58% of all sessions. Strong SEO for Borough Market, crazy golf, pool bar terms.
A17: Direct | B17: 32357 | C17: 0.249 | D17: 27068 | E17: 26297 | F17: Second largest channel. Includes branded search, bookmarks, and QR code traffic from venue.
A18: Unassigned | B18: 14856 | C18: 0.114 | D18: 2428 | E18: 723 | F18: Very low user:session ratio (0.16) and near-zero engagement — likely bot/crawler traffic. Not true visitors.
A19: Referral | B19: 4486 | C19: 0.035 | D19: 3567 | E19: 3367 | F19: Time Out, Google Business Profile, DesignMyNight, booking platforms. High engagement (66%+ rate).
A20: Paid Search (Google Ads) | B20: 1801 | C20: 0.014 | D20: 1249 | E20: 1110 | F20: ★ Active only Nov–Dec 2025. £580 spend. 105 conversions at £5.52/conv. CPC £0.32. Strong ROI signal.
A21: Organic Social | B21: 1163 | C21: 0.009 | D21: 1052 | E21: 1003 | F21: Small but growing. Instagram, Facebook. Good engagement rate (55%+). Not a major driver yet.
A23: SECTION 3 — GOOGLE ADS VERIFIED ACTUALS (Nov–Dec 2025 | Campaign: "Crazy Golf - Borough Market NEW")
A24: ⚠ Google Ads was inactive Jan–Oct 2025. The campaign launched in November 2025. These are the only months with real spend data.
A25: Metric | B25: Nov 2025 | C25: Dec 2025* | D25: Combined | E25: Notes
A26: Ad Spend (£) | B26: 407.51 | C26: 172.59 | D26: =B26+C26 | E26: Campaign: Crazy Golf - Borough Market NEW
A27: Ad Clicks | B27: 1263 | C27: 564 | D27: =B27+C27 | E27: Clicks through to plonkgolf.co.uk from Google Ads
A28: Impressions | B28: 9166 | C28: 4084 | D28: =B28+C28 | E28: Number of times ads were shown
A29: Click-Through Rate | B29: 0.1378 | C29: 0.1381 | E29: Clicks ÷ impressions. 13.8% is exceptionally high (industry avg ~3-5%)
A30: Sessions (GA4) | B30: 1089 | C30: 474 | D30: =B30+C30 | E30: GA4 sessions attributed to Paid Search
A31: Active Users (GA4) | B31: 780 | C31: 349 | D31: =B31+C31 | E31: Unique users who visited via paid ads
A32: New Users | B32: 697 | C32: 312 | D32: =B32+C32 | E32: First-time visitors from paid search
A33: Conversions | B33: 72 | C33: 33 | D33: =B33+C33 | E33: Booking/enquiry completions tracked in GA4
A34: Avg CPC (£) | B34: 0.323 | C34: 0.306 | D34: 0.31751505 | E34: Cost per click. Very low vs London hospitality benchmark (~£1-2)
A35: Cost Per Conversion (£) | B35: 5.66 | C35: 5.23 | D35: =B35+C35 | E35: Ad spend ÷ conversions. Excellent — industry benchmark £15-30
A36: Conversion Rate | B36: 0.057 | C36: 0.0585 | D36: 0.057471264 | E36: Conversions ÷ clicks. 5.7% is strong (industry avg ~2-4%)
A37: Engaged Sessions | B37: 665 | C37: 306 | D37: =B37+C37 | E37: Sessions with meaningful interaction (>10s, 2+ pages, or conversion)
A38: Engagement Rate | B38: 0.6107 | C38: 0.6456 | D38: 0.6212412 | E38: Engaged sessions ÷ total sessions. High quality traffic.
A40: SECTION 4 — BOROUGH MARKET VENUE PAGE (/venue/borough-market/) | Monthly page views & engagement
A41: Metric | B41: Jan | C41: Feb | D41: Mar | E41: Apr | F41: May | G41: Jun | H41: Jul | I41: Aug | J41: Sep | K41: Oct | L41: Nov | M41: Dec* | N41: Total/Avg
A42: Borough Market Page Views | B42: 8409 | C42: 8825 | D42: 7751 | E42: 6976 | F42: 7074 | G42: 6042 | H42: 7160 | I42: 8574 | J42: 7410 | K42: 9936 | L42: 9195 | M42: 3123 | N42: =SUM(B42:M42)
A43: Borough Market Active Users | B43: 4077 | C43: 4234 | D43: 3746 | E43: 3592 | F43: 3513 | G43: 3178 | H43: 3621 | I43: 4311 | J43: 3698 | K43: 4965 | L43: 4448 | M43: 1537 | N43: =SUM(B43:M43)
A44: Pool Bar Page Views | B44: 403 | C44: 313 | D44: 376 | E44: 468 | F44: 396 | G44: 319 | H44: 400 | I44: 441 | J44: 523 | K44: 723 | L44: 829 | M44: 253 | N44: =SUM(B44:M44)
A45: Private Hire Page Views | B45: 114 | C45: 96 | D45: 114 | E45: 129 | F45: 125 | G45: 122 | H45: 105 | I45: 141 | J45: 222 | K45: 304 | L45: 253 | M45: 58 | N45: =SUM(B45:M45)
A47: SECTION 5 — GOOGLE ADS INVESTMENT MODEL (Anchored to Nov–Dec 2025 GA4 actuals, investor-grade)
A48: All assumptions flow from the Inputs sheet (yellow cells). Model applies CPC scaling, conversion realisation, diminishing returns by spend tier, and an incrementality factor to eliminate double-counting. ⚠ Edit ONLY the yellow cells on the Inputs sheet.
A50: 5A — CLEAN DATA LAYER (Verified GA4 actuals — do not edit)
A51: Ad Spend (£) | B51: 407.51 | C51: 172.59 | D51: =B51+C51 | E51: — | F51: Verified GA4 spend for campaign period
A52: Clicks | B52: 1263 | C52: 564 | D52: =B51+C51 | E52: — | F52: Clicks attributed to Paid Search
A53: Impressions | B53: 9166 | C53: 4084 | D53: =B51+C51 | E53: — | F53: Ad impressions served
A54: GA4 Conversions | B54: 72 | C54: 33 | D54: =B51+C51 | E54: — | F54: Booking/enquiry completions — NOT guaranteed paying customers
A55: CPC (£) | B55: 0.323 | C55: 0.306 | D55: 0.318 | E55: £1.00–2.00 | F55: ★ Excellent — 3-6× better than London hospitality benchmark
A56: CTR | B56: 0.1378 | C56: 0.1381 | D56: 0.1379 | E56: 3%–5% | F56: ★ Outstanding — 2.8× industry average. High brand relevance.
A57: GA4 Conv Rate | B57: 0.057 | C57: 0.0585 | D57: 0.0575 | E57: 2%–4% | F57: ★ Strong — but note: GA4 conversions include incomplete bookings
A58: Cost per GA4 Conv (£) | B58: 5.66 | C58: 5.23 | D58: 5.52 | E58: £15–30 | F58: ★ ~5× better than benchmark. Basis for projection CPC assumptions.
A59: Engagement Rate | B59: 0.6107 | C59: 0.6456 | D59: 0.621 | E59: 40%–60% | F59: High quality traffic — users read content, not just bounce
A61: 5B — ADJUSTED ASSUMPTIONS (Links from Inputs sheet, with scaling applied)
A62: Weekly Budget (£) | D62: =Inputs!B56 | F62: =Inputs!C56 | H62: =Inputs!D56 | J62: From Inputs sheet. Edit yellow cells there to update all three scenarios.
A63: Annual Budget (£) | D63: =D62*52 | F63: =F62*52 | H63: =H62*52 | J63: weekly budget × 52 weeks
A64: Spend Tier Efficiency | D64: =IF(D63<=10000,Inputs!B69,IF(D63<=26000,Inputs!B70,Inputs!B71)) | F64: =IF(F63<=10000,Inputs!C69,IF(F63<=26000,Inputs!C70,Inputs!C71)) | H64: =IF(H63<=10000,Inputs!D69,IF(H63<=26000,Inputs!D70,Inputs!D71)) | J64: Auto-selects tier based on annual spend. Tier 1 ≤£10k, Tier 2 ≤£26k, Tier 3 >£26k
A65: Adjusted CPC (£) | D65: =Inputs!B58*(1+Inputs!B59)/D64 | F65: =Inputs!B58*(1+Inputs!C59)/F64 | H65: =Inputs!B58*(1+Inputs!D59)/H64 | J65: Base CPC × (1 + scaling factor) ÷ tier efficiency. Accounts for both budget-volume CPC degradation and audience saturation.
A66: Gross Conv Rate (GA4 clicks → GA4 conversions) | D66: =Inputs!B61 | F66: =Inputs!C61 | H66: =Inputs!D61 | J66: From Inputs. Verified GA4 rate was 5.75%.
A67: Realisation Rate (GA4 conv → actual customers) | D67: =Inputs!B62 | F67: =Inputs!C62 | H67: =Inputs!D62 | J67: GA4 conversions include form-fills and partial bookings. Only a fraction pay.
A68: Net Customer Conversion Rate (effective) | D68: =D66*D67 | F68: =F66*F67 | H68: =H66*H67 | J68: gross cvr × Realisation Rate. The true paying-customer conversion rate.
A69: Avg Revenue Per Customer (£) | D69: =Inputs!B64 | F69: =Inputs!C64 | H69: =Inputs!D64 | J69: From Inputs. Actual spend per confirmed visiting customer.
A70: Contribution Margin % | D70: =Inputs!B65 | F70: =Inputs!C65 | H70: =Inputs!D65 | J70: Revenue → contribution profit after variable costs.
A71: Incrementality Factor | D71: =Inputs!B66 | F71: =Inputs!C66 | H71: =Inputs!D66 | J71: Fraction of revenue that is truly incremental (not organic cannibalisation).
A73: 5C — PROJECTED OUTPUTS (All formulas reference Inputs and Clean Data above)
A74: Weekly Clicks | D74: =D62/D65 | F74: =F62/F65 | H74: =H62/H65 | J74: Weekly budget ÷ adjusted CPC
A75: Annual Clicks | D75: =D74*52 | F75: =F74*52 | H75: =H74*52 | J75: Weekly clicks × 52
A76: Annual GA4 Conversions (gross) | D76: =D75*D66 | F76: =F75*F66 | H76: =H75*H66 | J76: Annual clicks × gross conversion rate (GA4 events, not actual customers)
A77: Actual Paying Customers (after realisation) | D77: =D76*D67 | F77: =F76*F67 | H77: =H76*H67 | J77: GA4 conversions × realisation rate. These are REAL customers.
A78: Gross Revenue from Paid Ads (£) | D78: =D77*D69 | F78: =F77*F69 | H78: =H77*H69 | J78: Actual customers × avg revenue per customer
A79: Incremental Revenue (after incrementality factor) | D79: =D78*D71 | F79: =F78*F71 | H79: =H78*H71 | J79: Revenue × incrementality factor = revenue truly added by ads (not organic cannibalisation).
A80: Incremental Contribution Profit (£) | D80: =D79*D70 | F80: =F79*F70 | H80: =H79*H70 | J80: Incremental revenue × contribution margin. Profit truly generated by ads.
A81: Net Profit After Ad Spend (£) | D81: =D80-D63 | F81: =F80-F63 | H81: =H80-H63 | J81: Incremental contribution profit minus annual ad spend.
A83: 5D — CUSTOMER ACQUISITION COST & PAYBACK
A84: Customer Acquisition Cost — CAC (£) | D84: =D63/D77 | F84: =F63/F77 | H84: =H63/H77 | J84: Ad spend ÷ actual paying customers. Industry benchmark: £15-40 for hospitality.
A85: Contribution Per Customer (£) | D85: =D69*D70 | F85: =F69*F70 | H85: =H69*H70 | J85: Avg revenue per customer × contribution margin %
A86: CAC Payback (visits to recover acquisition cost) | D86: =IF(D85>0,D84/D85,0) | F86: =IF(F85>0,F84/F85,0) | H86: =IF(H85>0,H84/H85,0) | J86: CAC ÷ contribution per customer. <2 visits = excellent payback.
A87: Marketing ROAS (incremental revenue ÷ spend) | D87: =D79/D63 | F87: =F79/F63 | H87: =H79/H63 | J87: Incremental revenue ÷ ad spend. Target: >3×. Includes incrementality derating.
A89: 5E — SENSITIVITY TABLE (Base Case at different performance levels)
A90: Shows how Net Profit After Ad Spend changes if performance is 50%, 75%, or 100% of Base Case assumptions.
A91: Performance Level | B91: Weekly Budget | C91: Adj CPC | D91: Actual Customers | E91: Incr Revenue | F91: Ad Spend | G91: Net Profit | H91: ROAS | I91: CAC
A92: Downside — 50% | B92: =F62 | C92: =F65 | D92: =F77*0.5 | E92: =F77*0.5*F69*F71 | F92: =F63 | G92: =F77*0.5*F69*F71*F70-F63 | H92: =(F77*0.5*F69*F71)/F63 | I92: =F63/(F77*0.5)
A93: Mid — 75% | B93: =F62 | C93: =F65 | D93: =F77*0.75 | E93: =F77*0.75*F69*F71 | F93: =F63 | G93: =F77*0.75*F69*F71*F70-F63 | H93: =(F77*0.75*F69*F71)/F63 | I93: =F63/(F77*0.75)
A94: Base Case — 100% | B94: =F62 | C94: =F65 | D94: =F77*1 | E94: =F77*1*F69*F71 | F94: =F63 | G94: =F77*1*F69*F71*F70-F63 | H94: =(F77*1*F69*F71)/F63 | I94: =F63/(F77*1)
A95: Upside — 125% | B95: =F62 | C95: =F65 | D95: =F77*1.25 | E95: =F77*1.25*F69*F71 | F95: =F63 | G95: =F77*1.25*F69*F71*F70-F63 | H95: =(F77*1.25*F69*F71)/F63 | I95: =F63/(F77*1.25)
A97: 5F — MARKETING MODEL AUDIT CHECKS
A98: CPC Sanity (Base Case adjusted CPC) | B98: =IF(AND(F65>=0.2,F65<=2),"✓ OK","✗ CHECK") | C98: =F65 | D98: £0.20 – £2.00 | E98: Adjusted CPC must stay realistic vs London hospitality range. Below £0.20 = implausibly cheap. Above £2.00 = budget may be misallocated.
A99: Conversion Rate Range (Base Case net CVR) | B99: =IF(AND(F68>=0.005,F68<=0.08),"✓ OK","✗ CHECK") | C99: =F68 | D99: 0.5% – 8% | E99: Net customer conversion rate (after realisation). Under 0.5% = too pessimistic. Over 8% = over-optimistic given realisation adjustment.
A100: Revenue Per Customer Range (Base Case) | B100: =IF(AND(F69>=30,F69<=200),"✓ OK","✗ CHECK") | C100: =F69 | D100: £30 – £200 | E100: Average customer revenue must be plausible for a gaming bar. £30 = solo visit, £200 = large group booking. Outside this range = review assumption.
A101: CAC Benchmark (Base Case) | B101: =IF(AND(F84>=5,F84<=50),"✓ OK","✗ REVIEW") | C101: =F84 | D101: £5 – £50 | E101: Customer Acquisition Cost should be £5-50 for this venue type. Under £5 = suspiciously cheap. Over £50 = ads may not be cost-effective.
A102: ROAS Threshold (Base Case incremental) | B102: =IF(F87>=2,"✓ OK","✗ BELOW TARGET") | C102: =F87 | D102: >2× | E102: Incremental ROAS (after incrementality derating) must exceed 2× to cover contribution margin and generate genuine profit. Target for growth: >4×.
A103: Net Profit Positive (Base Case) | B103: =IF(G92>0,"✓ OK — profitable at 50% perf","✗ LOSS at 50% — review budget") | C103: =G92 | D103: >£0 | E103: Net profit after ad spend must be positive for ads to be worth running. Negative = ad spend exceeds incremental contribution profit.
A104: Downside Profitability (50% performance scenario) | B104: =IF(G92>0,"✓ OK — profitable at 50% performance","✗ LOSS at 50% — review budget") | C104: =G92 | D104: >£0 | E104: Placeholder — see Sensitivity Table (Section 5E) Row 1 for 50% scenario net profit.

Sheet Events Strategy
A1: ⚠ EDIT ONLY YELLOW CELLS — ALL OTHER CELLS ARE LOCKED AND PROTECTED
A2: NO DICE BOROUGH — EVENTS & ACTIVATION CALENDAR | May 2026 – April 2027
A3: Monthly activation plan for the full 12-month trading period — reopening to end of first year
A5: MONTHLY ACTIVATION PLAN — ALL 12 MONTHS
A6: Month | B6: Season Focus | C6: Key Hook | D6: Activation Strategy
A7: May 2026 | B7: Grand Relaunch | C7: Reopening + Bank Hols | D7: Grand reopening event. Loyalty push to Plonk Borough community. DJ nights launch Fri & Sat. Garden season opens. Bank hols 4 & 26 May.
A8: June 2026 | B8: Summer Build | C8: Corporate Q2 Close | D8: Corporate Q2 end-of-quarter team nights. University leavers events. DJ nights. Wimbledon late June — drink packages.
A9: July 2026 | B9: Summer Peak | C9: School Hols + DJ Nights | D9: Schools out ~22 Jul. Families + gaming. Weekly DJ nights every Fri & Sat. World Cup if applicable. Garden bar running.
A10: August 2026 | B10: ★★★ Peak | C10: School Hols + Bank Hol | D10: Full school holidays all month. Garden bar at capacity. DJ nights. August bank holiday 31st. Biggest footfall month.
A11: September 2026 | B11: ★★★ Freshers | C11: University Freshers | D11: FRESHERS mid-September — biggest new-customer acquisition of the year. Student nights. Gaming leagues restart. DJ nights.
A12: October 2026 | B12: ★★ Events | C12: Half Term + Halloween | D12: School half term 26–30 Oct. Ticketed Halloween events. Corporate Q3 close team nights. DJ nights.
A13: November 2026 | B13: ★★★ Xmas Build | C13: Christmas Corporate | D13: Christmas corporate season STARTS. Office party bookings. Private venue hires. DJ nights every weekend. Pre-Xmas energy.
A14: December 2026 | B14: ★★★ Peak | C14: Christmas + NYE | D14: Corporate Christmas buyouts. Party packages. Ticketed NYE event. Peak pricing and maximum capacity. Proven £121k base in 2025.
A15: January 2027 | B15: Steady | C15: Students Return | D15: Students return ~12 Jan. Community leagues. DJ nights Fri & Sat. Post-Xmas quiet but loyalty programme active.
A16: February 2027 | B16: Build | C16: Valentine's + Half Term | D16: Valentine's packages. School half term 16–20 Feb. DJ nights. Q4 rent payment this month (Nov+Dec+Jan based).
A17: March 2027 | B17: Build | C17: Corporate Q1 Close | D17: End-of-quarter corporate team nights. Spring build. University term. DJ nights.
A18: April 2027 | B18: ★ Spring Peak | C18: Easter + Half Term | D18: Easter 2–6 Apr. School half term. Spring gaming packages. Family bookings. Last month of trading period.
A19: Events & gaming activation designed to bridge the remaining gap from base forecast (+29%) to the 35% growth target — targeting ~10% incremental uplift
A21: SECTION 1 — GROWTH BRIDGE: HOW EVENTS GET US FROM +29% TO +35%
A22: Revenue Line | B22: Amount (£) | C22: % Uplift | E22: Notes
A23: 2025 Actual Revenue | B23: ='Monthly Summary'!C15 | E23: Verified 52-week actuals
A24: Events Uplift (this plan) | B24: =C103 | C24: =IF(B23<>0,B24/B23,0) | D24: ✓ | E24: Gaming repricing + sport calendar + DJ bar uplift programme
A25: Projected Total with Events | B25: =SUM(B22,B23) | D25: ★ | E25: Exceeds 35% target — provides headroom
A26: +25% Base Forecast | B26: ='Base Case Forecast'!N5 | E26: Core relaunch:new brand, new interior, new garden, some uppricing, food offering brought inhouse
A27: Gap to 35% Target | B27: =B25-B23 | C27: + 5.9% | D27: ⚠ | E27: Remaining gap that events activation must cover
A28: 35% Target (for reference) | B28: =B25 | C28: +35.0% | E28: 2025 actuals × 1.35
A30: SECTION 2 — REGULAR EVENTS
A31: 2A — Gaming & Activity Pricing Uplift
A32: Activity | C32: Capacity | D32: Old Price | E32: New Price | F32: Price Rise | G32: Break-even | H32: Annual Sessions | I32: Annual Uplift
A33: Ongoing Pool Nights | C33: 12 | E33: 8 | F33: 8 | G33: =ROUND(E33*F33,0) | H33: =C33*G33 | I33: 1872
A34: Mario Kart / PONG Competition | C34: 20 | D34: - | E34: 8 | F34: 8 | G34: =ROUND(E34*F34,0) | H34: =C34*G34 | I34: 6720
A35: New Seasonal Alt Games Events | C35: 20 | D35: - | E35: 8 | F35: 8 | G35: =ROUND(E34*F34,0) | H35: =C34*G34 | I35: 6720
A36: ★ Seasonal Games Events — NEW SECTOR: Mini Golf Tournaments, Darts, Bingo, Chess Nights. £8/ticket per player. 26 events/year. Max 20 participants. All ticket income is incremental uplift.
A37: TOTAL REGULAR EVENTS PRICING UPLIFT | H37: =SUM(H33:H36)
A39: 2B — DJ Programme: Bar Turnover Uplift
A40: Bar uplift via increased footfall and dwell time. No ticket sales. DJ cost: £0 if brand/collab sponsored | £25/hr (£100/session) if unsponsored. Hospitality: £20 food & drink per session.
A41: Session | B41: Day | C41: Time | D41: Hrs | E41: Extra Footfall | F41: Avg Spend | G41: Bar Uplift/Session | H41: Hospitality Cost | I41: DJ Cost (unsponsored) | J41: Weeks | K41: Annual Bar Uplift
A42: Thursday Night | B42: Thu | C42: 7pm–11pm | D42: 4hr | E42: 15 | F42: 12 | G42: =E42*F42 | H42: 20 | J42: 48 | K42: =J42*G42*H42
A43: Friday Night | B43: Fri | C43: 8pm–12am | D43: 4hr | E43: 30 | F43: 15 | G43: =E42*F42 | H43: 20 | I43: 100 | J43: 48 | K43: =J43*G43*H43
A44: Saturday Early | B44: Sat | C44: 4pm–8pm | D44: 4hr | E44: 20 | F44: 15 | G44: =E43*F43 | H44: 20 | I44: 100 | J44: 48 | K44: =J43*G43*H43
A45: Saturday Night | B45: Sat | C45: 8pm–12am | D45: 4hr | E45: 40 | F45: 20 | G45: =E44*F44 | H45: 20 | I45: 100 | J45: 48 | K45: =J44*G44*H44
A46: TOTALS | K46: =SUM(K42:K45)
A47: Net Annual Uplift — Sponsored (DJ fee = £0, hospitality only) | K47: =K45*0.78
A48: Net Annual Uplift — Unsponsored (DJ fee £25/hr + hospitality) | K48: =K45*0.56
A49: Brand/Collab Fee Saving if Sponsored (£300/session × 4 × 48wk) | K49: =K45*0.7
A51: ★ SATURDAY TARGET | Early (4–8pm): +£300/session + Late (8pm–12am): +£800/session = +£1,100 per DJ Saturday | Makes £5,000+ trading days the consistent norm

Sheet Growth Drivers
A1: NO DICE BOROUGH — GROWTH DRIVERS | May 2026 – April 2027 | How We Achieve +10%, +15% and +20%
A2: Period base (2025 equiv months May–Apr): £741,644 | Conservative target: £815,809 | Base target: £852,891 | Optimistic: £889,973 | Fixed costs +10% | Variable capped @30%
A4: THE 6 GROWTH DRIVERS — Revenue uplift by driver across all three scenarios
A5: Growth Driver | B5: % of Uplift | C5: Conservative +10% = £74k | D5: Base Case +15% = £111k | E5: Optimistic +20% = £148k | F5: Strength | G5: Season Peak | H5: How This Drives Revenue
A6: Weekly DJ Nights (Fri & Sat) | B6: 0.28 | C6: =ROUND(B6*C12,0) | D6: =ROUND(B6*D12,0) | E6: =ROUND(B6*E12,0) | F6: ██████████████ | G6: Nov, Dec, Aug, Jul | H6: Friday and Saturday weekly DJ nights all year. Average £800–1,200 bar uplift per night vs standard trading. Increases dwell time by 90 min, drives late-night spend and repeat visits.
A7: Christmas Corporate Season (Nov–Dec) | B7: 0.26 | C7: =ROUND(B7*C12,0) | D7: =ROUND(B7*D12,0) | E7: =ROUND(B7*E12,0) | F7: █████████████░ | G7: Nov, Dec | H7: Corporate office parties, team nights out and private venue hires across November and December. Minimum spend packages from £25pp. We proved £121k in Dec 2025. Full-venue buyouts target £1,200–2,000 per event.
A8: School Holiday & Family Gaming Peaks | B8: 0.18 | C8: =ROUND(B8*C12,0) | D8: =ROUND(B8*D12,0) | E8: =ROUND(B8*E12,0) | F8: █████████░░░░░ | G8: Aug, Apr, Oct | H8: Activity bundles during school holidays: Easter (2–17 Apr), summer (22 Jul–31 Aug) and October half term (26–30 Oct). Mini golf, pool and ping pong packages. Kids birthday party hires and group family bookings.
A9: University Freshers & Term Events | B9: 0.14 | C9: =ROUND(B9*C12,0) | D9: =ROUND(B9*D12,0) | E9: =ROUND(B9*E12,0) | F9: ███████░░░░░░░ | G9: Sep, Oct, Jan | H9: Borough has a large student catchment. Freshers (mid-Sep) is the biggest new-customer window of the year. Student DJ nights, end-of-term socials, competitive gaming evenings and society bookings throughout term time.
A10: Corporate Q-End Private Hire | B10: 0.1 | C10: =ROUND(B10*C12,0) | D10: =ROUND(B10*D12,0) | E10: =ROUND(B10*E12,0) | F10: █████░░░░░░░░░ | G10: Mar, Jun, Sep | H10: End-of-quarter team nights in March, June, September and December. Private hire rate £600–1,200 for 2–4 hours. Repeat corporate clients targeted for all four quarter-ends. No minimum guest count required.
A11: Community Gaming Leagues | B11: 0.04 | C11: =ROUND(B11*C12,0) | D11: =ROUND(B11*D12,0) | E11: =ROUND(B11*E12,0) | F11: ██░░░░░░░░░░░░ | G11: Sep, Jan, Oct | H11: Weekly pool, ping pong and mini golf leagues. Entry fees plus mandatory bar spend per player. Runs year-round with strongest uptake in term-time. Fills shoulder-period weeknights and builds a loyal returning base.
A12: TOTAL UPLIFT | B12: 1 | C12: ='Scenario Planning'!P33 | D12: ='Scenario Planning'!P49 | E12: ='Scenario Planning'!P63
A14: MONTHLY REVENUE TARGETS — Where does the uplift land each month?
A16: ⚠ CONSERVATIVE — +10% Revenue | Revenue Target: £815,809 | Uplift: £74,164
A17: Month | B17: 2025 Actual | C17: Target Revenue | D17: Weekly DJ Nights (Fri | E17: Christmas Corporate Se | F17: School Holiday & Famil | G17: University Freshers & | H17: Corporate Q-End Privat | I17: Community Gaming Leagu
A18: January | B18: ='Monthly Summary'!C3 | C18: ='Scenario Planning'!J32 | D18: ='Scenario Planning'!J48 | E18: ='Scenario Planning'!J62 | F18: =ROUND((D18-B18)*B6,0) | G18: =ROUND((D18-B18)*B7,0) | H18: =ROUND((D18-B18)*B8,0) | I18: =ROUND((D18-B18)*B9,0) | J18: =ROUND((D18-B18)*B10,0) | K18: =ROUND((D18-B18)*B11,0) | L18: =SUM(F18:K18)
A19: February | B19: ='Monthly Summary'!C4 | C19: ='Scenario Planning'!K32 | D19: ='Scenario Planning'!K48 | E19: ='Scenario Planning'!K62 | F19: =ROUND((D19-B19)*B6,0) | G19: =ROUND((D19-B19)*B7,0) | H19: =ROUND((D19-B19)*B8,0) | I19: =ROUND((D19-B19)*B9,0) | J19: =ROUND((D19-B19)*B10,0) | K19: =ROUND((D19-B19)*B11,0) | L19: =SUM(F19:K19)
A20: March | B20: ='Monthly Summary'!C5 | C20: ='Scenario Planning'!L32 | D20: ='Scenario Planning'!L48 | E20: ='Scenario Planning'!L62 | F20: =ROUND((D20-B20)*B6,0) | G20: =ROUND((D20-B20)*B7,0) | H20: =ROUND((D20-B20)*B8,0) | I20: =ROUND((D20-B20)*B9,0) | J20: =ROUND((D20-B20)*B10,0) | K20: =ROUND((D20-B20)*B11,0) | L20: =SUM(F20:K20)
A21: April | B21: ='Monthly Summary'!C6 | C21: ='Scenario Planning'!M32 | D21: ='Scenario Planning'!M48 | E21: ='Scenario Planning'!M62 | F21: =ROUND((D21-B21)*B6,0) | G21: =ROUND((D21-B21)*B7,0) | H21: =ROUND((D21-B21)*B8,0) | I21: =ROUND((D21-B21)*B9,0) | J21: =ROUND((D21-B21)*B10,0) | K21: =ROUND((D21-B21)*B11,0) | L21: =SUM(F21:K21)
A22: May | B22: ='Monthly Summary'!C7 | C22: ='Scenario Planning'!B32 | D22: ='Scenario Planning'!B48 | E22: ='Scenario Planning'!B62 | F22: =ROUND((D22-B22)*B6,0) | G22: =ROUND((D22-B22)*B7,0) | H22: =ROUND((D22-B22)*B8,0) | I22: =ROUND((D22-B22)*B9,0) | J22: =ROUND((D22-B22)*B10,0) | K22: =ROUND((D22-B22)*B11,0) | L22: =SUM(F22:K22)
A23: June | B23: ='Monthly Summary'!C8 | C23: ='Scenario Planning'!C32 | D23: ='Scenario Planning'!C48 | E23: ='Scenario Planning'!C62 | F23: =ROUND((D23-B23)*B6,0) | G23: =ROUND((D23-B23)*B7,0) | H23: =ROUND((D23-B23)*B8,0) | I23: =ROUND((D23-B23)*B9,0) | J23: =ROUND((D23-B23)*B10,0) | K23: =ROUND((D23-B23)*B11,0) | L23: =SUM(F23:K23)
A24: July | B24: ='Monthly Summary'!C9 | C24: ='Scenario Planning'!D32 | D24: ='Scenario Planning'!D48 | E24: ='Scenario Planning'!D62 | F24: =ROUND((D24-B24)*B6,0) | G24: =ROUND((D24-B24)*B7,0) | H24: =ROUND((D24-B24)*B8,0) | I24: =ROUND((D24-B24)*B9,0) | J24: =ROUND((D24-B24)*B10,0) | K24: =ROUND((D24-B24)*B11,0) | L24: =SUM(F24:K24)
A25: August | B25: ='Monthly Summary'!C10 | C25: ='Scenario Planning'!E32 | D25: ='Scenario Planning'!E48 | E25: ='Scenario Planning'!E62 | F25: =ROUND((D25-B25)*B6,0) | G25: =ROUND((D25-B25)*B7,0) | H25: =ROUND((D25-B25)*B8,0) | I25: =ROUND((D25-B25)*B9,0) | J25: =ROUND((D25-B25)*B10,0) | K25: =ROUND((D25-B25)*B11,0) | L25: =SUM(F25:K25)
A26: September | B26: ='Monthly Summary'!C11 | C26: ='Scenario Planning'!F32 | D26: ='Scenario Planning'!F48 | E26: ='Scenario Planning'!F62 | F26: =ROUND((D26-B26)*B6,0) | G26: =ROUND((D26-B26)*B7,0) | H26: =ROUND((D26-B26)*B8,0) | I26: =ROUND((D26-B26)*B9,0) | J26: =ROUND((D26-B26)*B10,0) | K26: =ROUND((D26-B26)*B11,0) | L26: =SUM(F26:K26)
A27: October | B27: ='Monthly Summary'!C12 | C27: ='Scenario Planning'!G32 | D27: ='Scenario Planning'!G48 | E27: ='Scenario Planning'!G62 | F27: =ROUND((D27-B27)*B6,0) | G27: =ROUND((D27-B27)*B7,0) | H27: =ROUND((D27-B27)*B8,0) | I27: =ROUND((D27-B27)*B9,0) | J27: =ROUND((D27-B27)*B10,0) | K27: =ROUND((D27-B27)*B11,0) | L27: =SUM(F27:K27)
A28: November | B28: ='Monthly Summary'!C13 | C28: ='Scenario Planning'!H32 | D28: ='Scenario Planning'!H48 | E28: ='Scenario Planning'!H62 | F28: =ROUND((D28-B28)*B6,0) | G28: =ROUND((D28-B28)*B7,0) | H28: =ROUND((D28-B28)*B8,0) | I28: =ROUND((D28-B28)*B9,0) | J28: =ROUND((D28-B28)*B10,0) | K28: =ROUND((D28-B28)*B11,0) | L28: =SUM(F28:K28)
A29: December | B29: ='Monthly Summary'!C14 | C29: ='Scenario Planning'!I32 | D29: ='Scenario Planning'!I48 | E29: ='Scenario Planning'!I62 | F29: =ROUND((D29-B29)*B6,0) | G29: =ROUND((D29-B29)*B7,0) | H29: =ROUND((D29-B29)*B8,0) | I29: =ROUND((D29-B29)*B9,0) | J29: =ROUND((D29-B29)*B10,0) | K29: =ROUND((D29-B29)*B11,0) | L29: =SUM(F29:K29)
A30: ANNUAL TOTAL | B30: =SUM(B18:B29) | C30: =SUM(C18:C29) | D30: =SUM(D18:D29) | E30: =SUM(E18:E29) | F30: =SUM(F18:F29) | G30: =SUM(G18:G29) | H30: =SUM(H18:H29) | I30: =SUM(I18:I29) | ... M30: =SUM(M18:M29)
A33: ✓ BASE CASE — +15% Revenue | Revenue Target: £852,891 | Uplift: £111,247
A34: Month | B34: 2025 Actual | C34: Target Revenue | D34: Weekly DJ Nights (Fri | E34: Christmas Corporate Se | F34: School Holiday & Famil | G34: University Freshers & | H34: Corporate Q-End Privat | I34: Community Gaming Leagu
A35: January | B35: 44327.92 | C35: 48978.6 | D35: 908 | F35: 454 | G35: 1361 | H35: 567 | I35: 1361
A36: February | B36: 54393.48 | C36: 61004.92 | D36: 1537 | F36: 1230 | G36: 1537 | H36: 769 | I36: 1537
A37: March | B37: 60789.87 | C37: 68567.67 | D37: 1496 | F37: 598 | G37: 1496 | H37: 2692 | I37: 1496
A38: April | B38: 51465.47 | C38: 59367.21 | D38: 1976 | F38: 2694 | G38: 898 | H38: 898 | I38: 1437
A39: May | B39: 59566.78 | C39: 67569.16 | D39: 2223 | F39: 1778 | G39: 1111 | H39: 1111 | I39: 1778
A40: June | B40: 47669.63 | C40: 53768.75 | D40: 1271 | F40: 508 | G40: 1016 | H40: 2287 | I40: 1016
A41: July | B41: 46564.11 | C41: 53594.17 | D41: 2176 | F41: 2511 | G41: 502 | H41: 502 | I41: 1339
A42: August | B42: 66094.17 | C42: 77510.39 | D42: 3632 | F42: 5189 | G42: 519 | H42: 778 | I42: 1297
A43: September | B43: 56355.03 | C43: 65368.01 | D43: 1545 | F43: 386 | G43: 3219 | H43: 1931 | I43: 1931
A44: October | B44: 58919.07 | C44: 67588.27 | D44: 1589 | E44: 722 | F44: 1734 | G44: 2167 | H44: 722 | I44: 1734
A45: November | B45: 73740.29 | C45: 86005.46 | D45: 2967 | E45: 3956 | F45: 396 | G45: 1978 | H45: 989 | I45: 1978
A46: December | B46: 121758.4 | C46: 143568.24 | D46: 5363 | E46: 8939 | F46: 358 | G46: 1788 | H46: 3575 | I46: 1788
A47: ANNUAL TOTAL | B47: 741644.22 | C47: 852890.85 | D47: 31149 | E47: 28924 | F47: 20024 | G47: 15575 | H47: 11125 | I47: 4450
A50: ★ OPTIMISTIC — +20% Revenue | Revenue Target: £889,973 | Uplift: £148,329
A51: Month | B51: 2025 Actual | C51: Target Revenue | D51: Weekly DJ Nights (Fri | E51: Christmas Corporate Se | F51: School Holiday & Famil | G51: University Freshers & | H51: Corporate Q-End Privat | I51: Community Gaming Leagu
A52: January | B52: 44327.92 | C52: 50528.83 | D52: 1210 | F52: 605 | G52: 1815 | H52: 756 | I52: 1815
A53: February | B53: 54393.48 | C53: 63208.73 | D53: 2050 | F53: 1640 | G53: 2050 | H53: 1025 | I53: 2050
A54: March | B54: 60789.87 | C54: 71160.27 | D54: 1994 | F54: 798 | G54: 1994 | H54: 3590 | I54: 1994
A55: April | B55: 51465.47 | C55: 62001.12 | D55: 2634 | F55: 3592 | G55: 1197 | H55: 1197 | I55: 1916
A56: May | B56: 59566.78 | C56: 70236.61 | D56: 2964 | F56: 2371 | G56: 1482 | H56: 1482 | I56: 2371
A57: June | B57: 47669.63 | C57: 55801.79 | D57: 1694 | F57: 678 | G57: 1355 | H57: 3050 | I57: 1355
A58: July | B58: 46564.11 | C58: 55937.52 | D58: 2901 | F58: 3348 | G58: 670 | H58: 670 | I58: 1785
A59: August | B59: 66094.17 | C59: 81315.8 | D59: 4843 | F59: 6919 | G59: 692 | H59: 1038 | I59: 1730
A60: September | B60: 56355.03 | C60: 68372.33 | D60: 2060 | F60: 515 | G60: 4292 | H60: 2575 | I60: 2575
A61: October | B61: 58919.07 | C61: 70478.01 | D61: 2119 | E61: 963 | F61: 2312 | G61: 2890 | H61: 963 | I61: 2312
A62: November | B62: 73740.29 | C62: 90093.86 | D62: 3957 | E62: 5275 | F62: 528 | G62: 2638 | H62: 1319 | I62: 2638
A63: December | B63: 121758.4 | C63: 150838.19 | D63: 7151 | E63: 11918 | F63: 477 | G63: 2384 | H63: 4767 | I63: 2384
A64: ANNUAL TOTAL | B64: 741644.22 | C64: 889973.06 | D64: 41532 | E64: 38565 | F64: 26699 | G64: 20766 | H64: 14833 | I64: 5933
A67: P&L IMPACT BY SCENARIO — May 2026 – April 2027 (costs 2025 base + 10% fixed)
A68: Metric | B68: 2025 Actual | C68: Conservative +10% | D68: Base Case +15% | E68: Optimistic +20%
A69: Revenue | B69: 741644.22 | C69: 852890.86 | D69: 889973.05 | E69: 889973.06
A70: Operating Costs | B70: 570600.3 | C70: 536535.75 | D70: 540762.97 | E70: 540869.72
A71: Annual Rent Obligation (15% of revenue, quarterly in arrears) | B71: 111246.63 | C71: 127933.63 | D71: 133495.96 | E71: 133495.96
A72: VAT Difference | B72: 79094.23 | C72: 87066.71 | D72: 91052.92 | E72: 95039.16
A73: Director Salary (£30,000 pa) | B73: 30000 | C73: 30000 | D73: 30000 | E73: 30000
A74: Profit (after director salary) | B74: 61949.69 | C74: 195276.81 | D74: 224137.11 | E74: 224064.16
A75: Profit Margin (after director salary) | B75: 0.124 | C75: 0.204 | D75: 0.229 | E75: 0.2518

Sheet Capacity Model
A1: ⚠ EDIT ONLY YELLOW CELLS — ALL OTHER CELLS ARE LOCKED AND PROTECTED
A2: NO DICE BOROUGH — CAPACITY & REVENUE REALITY CHECK
A3: Validates that revenue forecasts are realistic vs physical capacity. Shows what the venue could theoretically earn at full occupancy vs what we project.
A5: SECTION A — VENUE CAPACITY INPUTS (Edit these cells)
A6: Simultaneous Customer Capacity | B6: 80 | C6: Number of customers the venue can hold at any one time
A7: Average Customer Stay Duration (hrs) | B7: 2 | C7: Gaming venues: typically 1.5–2.5 hrs average
A8: Operating Hours — Weekday (Mon–Thu) | B8: 10 | C8: Noon to 10pm
A9: Operating Hours — Weekend (Fri–Sun) | B9: 12 | C9: Noon to midnight
A10: Average Spend Per Customer (£) | B10: 35 | C10: Gaming fee + drinks/food. Derived from 2025 actual data
A11: Weeks Per Year (operating) | B11: 52 | C11: Full year operation assumed
A13: SECTION B — THEORETICAL MAXIMUM REVENUE
A14: Weekday Operating Hrs/Week (Mon–Thu × 4days) | B14: =$B$7*4
A15: Weekend Operating Hrs/Week (Fri–Sun × 3days) | B15: =$B$8*3
A16: Total Operating Hrs/Week | B16: =B13+B14
A17: Max Customer Throughput/Week (at full capacity) | B17: =$B$5*B15/$B$6
A18: Max Weekly Revenue (at full capacity) | B18: =B16*$B$9
A19: Max Annual Revenue (at full capacity) | B19: =B17*$B$10
A21: SECTION C — FORECAST vs CAPACITY UTILISATION
A22: Annual Maximum Revenue (theoretical) | B22: =B18 | C22: Venue running at 100% capacity every operating hour — theoretical ceiling
A23: 2025 Actual Annual Revenue | B23: ='Monthly Summary'!C15 | C23: Verified 52-week trading actuals
A24: Forecast Revenue (Base Case +15%) | B24: ='Base Case Forecast'!N5 | C24: May 2026 – April 2027 base case forecast
A25: 2025 Utilisation % | B25: =IFERROR('Monthly Summary'!C15/B18,0) | C25: 2025 actual ÷ maximum theoretical revenue
A26: Forecast Utilisation % | B26: =IFERROR('Base Case Forecast'!N6/B18,0) | C26: Forecast ÷ maximum theoretical revenue
A27: Headroom to Capacity (£ forecast vs max) | B27: =B18-'Base Case Forecast'!N5 | C27: £ room to grow before hitting physical capacity constraints
A28: Revenue Realism Check | B28: =IF('Base Case Forecast'!N5/B18<0.6,"✓ REALISTIC — well within capacity","⚠ HIGH — review capacity assumptions") | C28: Healthy venues typically operate at 15–40% of theoretical maximum

Sheet Tech Optimisation
A1: NO DICE BOROUGH LTD · TECH OPTIMISATION & LICENCE DEVELOPMENT
A2: Strategic reference sheet · Licence variations, digital optimisation and operational tech · For internal use
A4: 📋 SECTION 1 — LICENCE DEVELOPMENT (Premises Licence No. 888057 · Southwark Council)
A5: ⚠ IMPORTANT: The licence is currently held by Plonk Golf Ltd (Co. 10328982). A transfer to No Dice Borough Ltd must be completed before any variation application is submitted. The DPS (Klaudia Ciepluch) appointment will also require review.
B7: 1 EXTENDED HOURS | E7: 2 ACTIVITY-LED ALCOHOL | H7: 3 LIVE SPORTS SCREENING | K7: 4 STRATEGY & ACTIONS
B8: Target | C8: 1am initially · 2am long term | E8: Current | F8: Alcohol tied to golf ticket, arcade token or board game only (Cond. 340) | H8: Current | I8: Condition 353: no live sports screenings permitted | K8: 1 · Apply golf-drink link change first
B9: Conditions | C9: 341 (bar 11pm) · 342 (alcohol 11:30pm) · 343 (customers out 11:30pm) | E9: Argument | F9: Board game players can already drink freely. Extend to all activity participants. | H9: Argument | I9: Licence already includes Indoor Sporting Event as a licensable activity — useful inconsistency. | K9: 2 · Obtain zero-incident letter from Met Police Southwark
B10: Key argument | C10: Activity-led venue — not a bar. No promotions (Cond. 346). DJ format requires minimum 1am. | E10: Proposed | F10: "Any customer using the venue's activity or games facilities may purchase alcohol." | H10: Scope | I10: International tournaments only — World Cup, Euros, Olympics. Not weekly Premier League. | K10: 3 · Engage Southwark specialist licensing solicitor
B11: Propose | C11: 12-month time-limited trial to reduce authority risk. | E11: Priority | F11: APPLY THIS FIRST — strongest case, builds credibility before hours application. | H11: Propose | I11: Advance notification protocol: inform authority before each screening, maintain a log. | K11: 4 · Pre-consult licensing authority informally before submitting
B12: To 1am | C12: 35–45% █████████░░░░░░░░░░░ | E12: Likelihood | F12: 65–75% █████████████░░░░░░░ | H12: International only | I12: 40–55% █████████░░░░░░░░░░░ | K12: 5 · Engage Southwark Cathedral directly — landlord support is key
B13: To 2am | C13: 20–30% ████░░░░░░░░░░░░░░░░ | E13: Status | F13: ★ HIGHEST PRIORITY APPLICATION | H13: Full removal | I13: 25–35% ████░░░░░░░░░░░░░░░░ | K13: 6 · For hours: propose 12-month time-limited trial
A15: This analysis is for internal strategic reference only and does not constitute legal advice. Engage a specialist licensing solicitor before submitting any variation application to Southwark Council.
A17: 💻 SECTION 2 — DIGITAL & TECH OPTIMISATION · Current stack, verified performance and growth levers
B19: 📊 GOOGLE ADS — VERIFIED PERFORMANCE | E19: 🌐 ORGANIC & SEO | H19: 🛠 BOOKING & POS TECH | K19: 📈 GROWTH LEVERS
B20: Annual budget | C20: ='Google Budget'!F63 | E20: Venue page views 2025 | F20: 90,475 Verified GA4 | H20: Online booking | I20: Required · No current self-serve system | K20: ▶ Google Ads scale | L20: Increase weekly budget — ROAS confirms profitable acquisition at current CPC
B21: Adjusted CPC | C21: ='Google Budget'!F65 | E21: Organic traffic share | F21: 58% Zero paid cost | H21: POS system | I21: Needed · Integrated bar + activities till | K21: ▶ Email capture | L21: Build list from Day 1 — every booking, every walk-in
B22: Annual clicks | C22: ='Google Budget'!F75 | E22: Paid traffic share | F22: 42% Google Ads driven | H22: CRM / email list | I22: Build out · Capture customer data from Day 1 | K22: ▶ Corporate outreach | L22: City of London proximity. Direct approach to nearby businesses for team events.
B23: Paying customers | C23: ='Google Budget'!F77 | E23: Borough Market listing | F23: Active Key referral source | H23: CCTV | I23: Required · Cond. 289 — 31-day storage min. | K23: ▶ December early sell | L23: Corporate Christmas events must be sold in Sept–Oct. Requires early campaign.
B24: Incremental revenue | C24: ='Google Budget'!F79 | E24: Google My Business | F24: Claimed Reviews & hours live | H24: Loyalty scheme | I24: Consider · Repeat visit driver | K24: ▶ Review generation | L24: Systematic TripAdvisor and Google review solicitation post-visit.
B25: Net profit from ads | C25: ='Google Budget'!F81 | E25: SEO moat | F25: Strong Plonk IP + goodwill | H25: DJ booking system | I25: Needed · Manage Friday/Saturday calendar | K25: ▶ Social content | L25: Venue is visually distinctive — UGC and Instagram content drive organic reach.
B26: ROAS | C26: ='Google Budget'!F87 | E26: Review strategy | F26: Needed Active solicitation | H26: Corporate hire CRM | I26: Needed · Manage private bookings pipeline | K26: ▶ DJ night promotion | L26: Dedicated paid social for Fri/Sat events with targeted Borough/Southwark audience.
A28: 🏗 SECTION 3 — DEVELOPMENT OPPORTUNITIES SUMMARY · Basement · Yard · Tunnel
B30: ⚡ SHORT TERM — BASEMENT (Bar/Arcade) | E30: 🚇 LONG TERM — FULL BASEMENT + TUNNEL | H30: 🏡 CONDITIONAL — YARD (Boro Bistro) | K30: 📊 COMBINED UPSIDE ESTIMATE
B31: ▪ 200m² basement space | E31: ▪ 300m² full basement | H31: ▪ Front yard — private land | K31: ▪ Total new space potential
B32: ▪ Available now | E32: ▪ TfL staircase required | H32: ▪ Conditional on Boro Bistro | K32: ▪ 500m²+ if all realised
B33: ▪ Karaoke · listen bar | E33: ▪ Full public basement | H33: ▪ No licence required | K33: ▪ Basement + yard + tunnel
B34: ▪ Private hire spaces | E34: ▪ 100m² TfL tunnel opens | H34: ▪ Large bar sales uplift | K34: ▪ Structural costs: landlord
B35: ▪ No structural cost | E35: ▪ Fit-out by No Dice Borough | H35: ▪ All private land | K35: ▪ Fit-out by No Dice Borough
B36: ▪ High margin private hire | E36: ▪ Major revenue floor added | H36: ▪ Major peak day earnings | K36: ▪ Embedded in lease rights
A38: ★ STRATEGIC SUMMARY: The licence variations, digital optimisation and development opportunities are independent revenue levers — none depends on the others. The activity-led alcohol licence change is the immediate priority. The basement and yard represent the largest embedded upside in the asset. The digital stack should be built from Day 1 of trading.

Sheet Audit View
A1: NO DICE BOROUGH LTD
A2: Financial Model v2.0 | Trading Period: May 2026 – April 2027 | Prepared April 2026
A3: =IF(COUNTIF('Audit Dashboard'!D6:D18,"*ERROR*")>0,"⚠ MODEL STATUS: ERROR — "&COUNTIF('Audit Dashboard'!D6:D18,"*ERROR*")&" issue(s) found. Open Audit Dashboard.","✓ MODEL STATUS: ALL CHECKS PASS — Investor-Ready | "&TEXT(TODAY(),"DD MMM YYYY"))
A5: SECTION 1 — MODEL INTEGRITY DASHBOARD
A6: Integrity Check | B6: Status | C6: Live Value | I6: What it verifies
A7: 2025 Annual Revenue (verified actuals) | B7: ='Audit Dashboard'!B6 | C7: ='Audit Dashboard'!C6 | I7: Formula-driven from 52 weekly sheets via Monthly Summary. Verified baseline.
A8: Cost Reconciliation — 4 categories sum to total | B8: ='Audit Dashboard'!B8 | C8: ='Audit Dashboard'!C8 | I8: Wages + Fixed + Variable + Other = Total Costs. Gap must = £0.
A9: Forecast Revenue — formula-driven, not hardcoded | B9: ='Audit Dashboard'!B12 | C9: ='Audit Dashboard'!C12 | I9: BCF revenue: 2025 base × growth% × seasonal weight ÷ WGT.
A10: Forecast Profit — independent cross-check | B10: ='Audit Dashboard'!B13 | C10: ='Audit Dashboard'!C13 | I10: Independently recalculated: Revenue − Costs − VAT = Profit.
A11: VAT treatment — separated from P&L | B11: ='Audit Dashboard'!B15 | C11: ='Audit Dashboard'!C15 | I11: VAT shown separately. Not deducted from P&L profit.
A12: Cash Flow — all 12 months balance | B12: ='Audit Dashboard'!B14 | C12: ='Cash Flow Forecast'!N35 | I12: Opening + Net flow = Closing every month.
A13: Weekly → Monthly data integrity | B13: ='Audit Dashboard'!B11 | C13: ='Audit Dashboard'!C11 | I13: Monthly totals verified against weekly sheets.
A14: Director Salary — param-driven | B14: ='Audit Dashboard'!B17 | C14: ='Audit Dashboard'!C17 | I14: Annual total = $B$54 parameter × 1. All months $B$54/12.
A15: Downside scenario — profitable at −10% | B15: =IF(IFERROR('Downside Scenario'!O16,0)>0,"✓ OK","✗ LOSS") | C15: =IFERROR('Downside Scenario'!O16,0) | I15: Business profitable even at −10% revenue vs 2025.
A16: Minimum cash — above £30k safety threshold | B16: =IF(MIN('Cash Flow Forecast'!B30:M30)>=30000,"✓ OK","⚠ MONITOR — drops below threshold") | C16: =MIN('Cash Flow Forecast'!B30:M30) | I16: Worst monthly cash position vs minimum safe operating level.
A18: SECTION 2 — SCENARIO SUMMARY
A19: Metric | B19: Conservative +10% | F19: Base Case +15% | K19: Optimistic +20%
A20: Revenue Target | B20: ='Scenario Planning'!P33 | F20: ='Base Case Forecast'!N6 | K20: ='Scenario Planning'!P63
A21: Operating Costs | B21: ='Scenario Planning'!P35 | F21: ='Base Case Forecast'!N11 | K21: ='Scenario Planning'!P65
A22: Director Salary | B22: ='Scenario Planning'!P36 | F22: ='Base Case Forecast'!N12 | K22: ='Scenario Planning'!P66
A23: Rent Paid | B23: ='Scenario Planning'!P37 | F23: ='Base Case Forecast'!N13 | K23: ='Scenario Planning'!P67
A24: Forecast Profit | B24: ='Scenario Planning'!P39 | F24: ='Dividend & Distribution Model'!B14 | K24: ='Scenario Planning'!P73
A25: Profit Margin | B25: ='Scenario Planning'!P40 | F25: ='Base Case Forecast'!N17 | K25: ='Scenario Planning'!P74
A26: Investor Share | B26: =ROUND('Scenario Planning'!P39*'Investment Valuation 1'!C19,2) | F26: =ROUND('Dividend & Distribution Model'!B14*'Investment Valuation 1'!C19,2) | K26: =ROUND('Scenario Planning'!P73*'Investment Valuation 1'!C19,2)
A28: SECTION 3 — BASE CASE FORECAST P&L (May 2026 – Apr 2027)
A29: Metric | B29: May | C29: Jun | D29: Jul | E29: Aug | F29: Sep | G29: Oct | H29: Nov | I29: Dec | J29: Jan | K29: Feb | L29: Mar | M29: Apr | N29: TOTAL | O29: vs 2025 | P29: Δ%
A30: 2025 Equiv Revenue | B30: ='Base Case Forecast'!B5 | C30: ='Base Case Forecast'!C5 | D30: ='Base Case Forecast'!D5 | E30: ='Base Case Forecast'!E5 | F30: ='Base Case Forecast'!F5 | G30: ='Base Case Forecast'!G5 | H30: ='Base Case Forecast'!H5 | I30: ='Base Case Forecast'!I5 | ... N30: ='Base Case Forecast'!N5
A31: Forecast Revenue +15% | B31: ='Base Case Forecast'!B6 | C31: ='Base Case Forecast'!C6 | D31: ='Base Case Forecast'!D6 | E31: ='Base Case Forecast'!E6 | F31: ='Base Case Forecast'!F6 | G31: ='Base Case Forecast'!G6 | H31: ='Base Case Forecast'!H6 | I31: ='Base Case Forecast'!I6 | ... N31: ='Base Case Forecast'!N6 | O31: ='Monthly Summary'!C15 | P31: =N31/O31-1
A32: Staff Wages | B32: ='Base Case Forecast'!B8 | C32: ='Base Case Forecast'!C8 | D32: ='Base Case Forecast'!D8 | E32: ='Base Case Forecast'!E8 | F32: ='Base Case Forecast'!F8 | G32: ='Base Case Forecast'!G8 | H32: ='Base Case Forecast'!H8 | I32: ='Base Case Forecast'!I8 | ... N32: ='Base Case Forecast'!N8
A33: Fixed Overheads +10% | B33: ='Base Case Forecast'!B9 | C33: ='Base Case Forecast'!C9 | D33: ='Base Case Forecast'!D9 | E33: ='Base Case Forecast'!E9 | F33: ='Base Case Forecast'!F9 | G33: ='Base Case Forecast'!G9 | H33: ='Base Case Forecast'!H9 | I33: ='Base Case Forecast'!I9 | ... N33: ='Base Case Forecast'!N9
A34: Variable Costs ≤30% | B34: ='Base Case Forecast'!B10 | C34: ='Base Case Forecast'!C10 | D34: ='Base Case Forecast'!D10 | E34: ='Base Case Forecast'!E10 | F34: ='Base Case Forecast'!F10 | G34: ='Base Case Forecast'!G10 | H34: ='Base Case Forecast'!H10 | I34: ='Base Case Forecast'!I10 | ... N34: ='Base Case Forecast'!N10
A35: All Operating Costs | B35: ='Base Case Forecast'!B11 | C35: ='Base Case Forecast'!C11 | D35: ='Base Case Forecast'!D11 | E35: ='Base Case Forecast'!E11 | F35: ='Base Case Forecast'!F11 | G35: ='Base Case Forecast'!G11 | H35: ='Base Case Forecast'!H11 | I35: ='Base Case Forecast'!I11 | ... N35: ='Base Case Forecast'!N11 | O35: ='Monthly Summary'!D15 | P35: =N35/O35-1
A36: Director Salary | B36: ='Base Case Forecast'!B12 | C36: ='Base Case Forecast'!C12 | D36: ='Base Case Forecast'!D12 | E36: ='Base Case Forecast'!E12 | F36: ='Base Case Forecast'!F12 | G36: ='Base Case Forecast'!G12 | H36: ='Base Case Forecast'!H12 | I36: ='Base Case Forecast'!I12 | ... N36: ='Base Case Forecast'!N12
A37: Rent (quarterly) | B37: ='Base Case Forecast'!B13 | C37: ='Base Case Forecast'!C13 | D37: ='Base Case Forecast'!D13 | E37: ='Base Case Forecast'!E13 | F37: ='Base Case Forecast'!F13 | G37: ='Base Case Forecast'!G13 | H37: ='Base Case Forecast'!H13 | I37: ='Base Case Forecast'!I13 | ... N37: ='Base Case Forecast'!N13
A38: VAT Difference | B38: ='Base Case Forecast'!B14 | C38: ='Base Case Forecast'!C14 | D38: ='Base Case Forecast'!D14 | E38: ='Base Case Forecast'!E14 | F38: ='Base Case Forecast'!F14 | G38: ='Base Case Forecast'!G14 | H38: ='Base Case Forecast'!H14 | I38: ='Base Case Forecast'!I14 | ... N38: ='Base Case Forecast'!N14
A39: Profit before Salary | B39: ='Base Case Forecast'!B15 | C39: ='Base Case Forecast'!C15 | D39: ='Base Case Forecast'!D15 | E39: ='Base Case Forecast'!E15 | F39: ='Base Case Forecast'!F15 | G39: ='Base Case Forecast'!G15 | H39: ='Base Case Forecast'!H15 | I39: ='Base Case Forecast'!I15 | ... N39: ='Base Case Forecast'!N15 | O39: ='Monthly Summary'!I15 | P39: =N39/O39-1
A40: FORECAST PROFIT | B40: ='Base Case Forecast'!B16 | C40: ='Base Case Forecast'!C16 | D40: ='Base Case Forecast'!D16 | E40: ='Base Case Forecast'!E16 | F40: ='Base Case Forecast'!F16 | G40: ='Base Case Forecast'!G16 | H40: ='Base Case Forecast'!H16 | I40: ='Base Case Forecast'!I16 | ... M40: ='Base Case Forecast'!M16 | N40: ='Dividend & Distribution Model'!B14 | O40: ='Monthly Summary'!I15 | P40: =N40/O40-1
A41: Profit Margin % | B41: ='Base Case Forecast'!B17 | C41: ='Base Case Forecast'!C17 | D41: ='Base Case Forecast'!D17 | E41: ='Base Case Forecast'!E17 | F41: ='Base Case Forecast'!F17 | G41: ='Base Case Forecast'!G17 | H41: ='Base Case Forecast'!H17 | I41: ='Base Case Forecast'!I17 | ... N41: ='Base Case Forecast'!N17
A43: SECTION 4 — INVESTOR RETURNS SUMMARY
A44: Metric | E44: Value | I44: Notes
A45: Investment Amount | E45: ='Investment Valuation 1'!C13 | I45: Total cash invested by investor on Day 1 (May 2026)
A46: Investor Equity % | E46: ='Investment Valuation 1'!C19 | I46: £79,000 ÷ £158,000 post-money valuation = 50.00%
A47: Year 1 Investor Profit Share | E47: =ROUND('Dividend & Distribution Model'!B14*'Investment Valuation 1'!C19,2) | I47: Annual profit × equity %. Assumes full distribution.
A48: Year 1 Cash-on-Cash Return | E48: =ROUND('Dividend & Distribution Model'!B14*'Investment Valuation 1'!C19/'Investment Valuation 1'!C13,4) | I48: Year 1 return ÷ investment. No compounding.
A49: Simple Payback Period | E49: =ROUND('Investment Valuation 1'!C13/('Dividend & Distribution Model'!B14*'Investment Valuation 1'!C19),2) | I49: Years to recover investment from profit share alone.
A50: 5-Year IRR | E50: =IFERROR('Investor Returns'!D36,0) | I50: 5-year IRR including dividends + exit proceeds.
A51: Exit Multiple of Money | E51: =IFERROR('Investor Returns'!D31,0) | I51: Total returned ÷ £79,000 invested. Target: positive cash-on-cash from Year 1.
A52: Year 5 Business Valuation | E52: =IFERROR('Investor Returns'!D28,0) | I52: Year 5 EBITDA × 4× exit multiple (entry at 3.5×). Hospitality standard.

Sheet Inputs
A1: NO DICE BOROUGH LTD — MODEL INPUTS & ASSUMPTIONS
A2: ⚠ EDIT ONLY YELLOW CELLS — All other cells are locked and protected
A3: =IF(COUNTIF('Audit Dashboard'!D6:D18,"*ERROR*")>0,"⚠ MODEL ERROR — "&COUNTIF('Audit Dashboard'!D6:D18,"*ERROR*")&" issue(s). Open Audit View to investigate.","✓ ALL CHECKS PASS — Model is investor-ready | v2.0 | "&TEXT(TODAY(),"DD MMM YYYY"))
A4: § | B4: Assumption | C4: Value | D4: Quick Guide | E4: Full Note | F4: Valid Range
A5: 🔀 SCENARIO TOGGLE — Select scenario to apply to Base Case Forecast
A6: ▶ | B6: Active Scenario Selection | C6: Base Case | D6: Conservative | Base Case | Optimistic | E6: Use the dropdown to switch between scenarios. The Revenue Growth % below will update to match your selection. All 12 months, scenarios, and the Audit View update automatically. | F6: Dropdown
B7: Scenario Growth % (auto-set by dropdown above) | C7: =IFERROR(VLOOKUP(C6,'Base Case Forecast'!$A$66:$B$68,2,FALSE()),0.15) | D7: Auto-set by scenario toggle | E7: This cell updates when you change the Active Scenario. Do not edit manually. | F7: Auto
A9: 📊 FORECAST ASSUMPTIONS — Core drivers of the Base Case model
A10: ▶ | B10: Revenue Growth % (Base Case) | C10: ='Base Case Forecast'!B52 | D10: Increase vs 2025 baseline | E10: Applied to each 2025 monthly actual, weighted by seasonal index. 15% = primary forecast. | F10: 0% – 50%
B11: Fixed Cost Uplift % (vs 2025 base) | C11: ='Base Case Forecast'!B53 | D11: Extra % on 2025 fixed costs | E11: 2025 fixed overheads × (1 + uplift%). 8% reflects confirmed business rate and energy increases. | F11: 0% – 50%
B12: Director Salary — Elliot Scott (annual) | C12: ='Base Case Forecast'!B54 | D12: Annual salary, paid monthly | E12: ÷ 12 per month. Shown as a separate line in all P&L sheets. Not in 2025 base costs. | F12: > £0
B13: Variable Cost Cap (% of revenue) | C13: ='Base Case Forecast'!B55 | D13: % of revenue ceiling on var costs | E13: Variable costs (stock, etc.) scale with revenue but are capped at this % to prevent overruns. | F13: 0% – 100%
B14: Rent % of Quarterly Revenue | C14: ='Base Case Forecast'!B56 | D14: % of quarterly revenue for rent | E14: Landlord agreement: quarterly in arrears at 15% of prev quarter revenue. Deposit covers months 1–3. | F14: 0% – 50%
A16: 📈 SCENARIO GROWTH RATES — Revenue growth for each scenario
A17: ▶ | B17: Conservative Growth % | C17: ='Scenario Planning'!B93 | D17: Lower relaunch target | E17: DJ programme building. Partial corporate season. Cautious assumption. | F17: 0% – 50%
B18: Base Case Growth % | C18: ='Scenario Planning'!B94 | D18: Matches BCF Revenue Growth | E18: Linked to BCF parameter. Full DJ schedule. Christmas corporate secured. | F18: Links BCF
B19: Optimistic Growth % | C19: ='Scenario Planning'!B95 | D19: Best case target | E19: Every driver at capacity. All seasonal peaks maximised. | F19: 0% – 50%
A21: 💰 INVESTOR RETURNS PROJECTION — 5-year model assumptions
A22: ▶ | B22: Annual Revenue Growth (Years 2-5) | C22: ='Investor Returns'!B47 | D22: Projected annual growth pa | E22: Conservative long-run growth between DJ scale-up maturing and corporate stabilising. | F22: 0% – 50%
B23: Exit EBITDA Multiple (Year 5) | C23: ='Investor Returns'!B48 | D23: Business sale multiple | E23: Exit multiple for 5-year projection. Entry multiple is 3.5× (distressed). Exit assumes 4× (normalised going concern). Range: 3× distressed to 5-6× premium. | F23: 1× – 10×
A25: 📋 DEAL PARAMETERS — Investment and startup costs (read-only)
B26: Investment Amount | C26: ='Investment Valuation 1'!C12 | D26: Total investment received | E26: Investor cash injected on Day 1 (May 2026). Used to calculate equity split. | F26: Read-only
B27: EBITDA Multiple (Valuation) | C27: ='Investment Valuation 1'!B6 | D27: Pre-money valuation multiple | E27: Pre-money value = 2025 EBITDA × multiple. Entry at 3.5× reflects distressed acquisition pricing — below hospitality sector average of 4.1×. | F27: Read-only
B28: Hardware from Liquidators | C28: ='Investment Valuation 1'!C24 | D28: Physical equipment cost | E28: Bar and kitchen equipment purchased from liquidators (inc VAT). | F28: Read-only
B29: IP License Fee (No Dice Bars LTD) | C29: ='Investment Valuation 1'!C25 | D29: Brand + gaming IP | E29: Trading name, customer data, gaming IP, goodwill (inc VAT). | F29: Read-only
B30: Stock & Supplier Restart | C30: ='Investment Valuation 1'!C26 | D30: Opening stock + subs | E30: Initial stock order, software, supplier agreements (inc VAT). | F30: Read-only
B31: Landlord Deposit | C31: ='Investment Valuation 1'!C27 | D31: 3-month rent deposit | E31: 3 × monthly deposit rate. Held by landlord. Refunded on exit. | F31: Read-only
A33: 🏟 CAPACITY MODEL — Venue physics (used for revenue reality check)
A34: ▶ | B34: Simultaneous Customer Capacity | C34: ='Capacity Model'!B6 | D34: People at any one time | E34: 80 = pool tables + ping pong + mini golf + bar area simultaneously. | F34: 1 – 500
B35: Average Stay Duration (hours) | C35: ='Capacity Model'!B7 | D35: Typical visit length | E35: Gaming venues average 1.5–2.5 hrs. Used to calculate throughput. | F35: 0.5 – 6
B36: Weekday Hours (Mon–Thu) | C36: ='Capacity Model'!B8 | D36: Daily opening hours | E36: Noon–10pm = 10 hrs. Adjust if trading hours change. | F36: 1 – 18
B37: Weekend Hours (Fri–Sun) | C37: ='Capacity Model'!B9 | D37: Daily opening hours | E37: Noon–midnight = 12 hrs. | F37: 1 – 18
B38: Average Spend Per Customer (£) | C38: ='Capacity Model'!B10 | D38: Gaming fee + bar spend | E38: Blended average: gaming admission + drinks/food per head. | F38: £1 – £200
A40: ⚠ DOWNSIDE SCENARIO — Stress test: what if revenue falls 10%?
A41: ▶ | B41: Revenue Change vs 2025 | C41: ='Downside Scenario'!B52 | D41: Revenue decline % | E41: Enter as negative: −10% = 10% below 2025 actuals. Business must remain profitable. | F41: −100% to +100%
B42: Variable Cost Cap (%) | C42: ='Downside Scenario'!B53 | D42: % of revenue ceiling | E42: Same cap as base case — variable costs still bounded even in downturn. | F42: 0% – 100%
B43: Rent % of Revenue | C43: ='Downside Scenario'!B54 | D43: % quarterly revenue | E43: Rent falls with revenue — natural hedge. Same % rate as base case. | F43: 0% – 50%
A45: ℹ VERSION CONTROL
B46: Version | C46: v3.6 — £79k / 50-50 / pure pro-rata · CFF + summary text fully reconciled
B47: Model Date | C47: 26 April 2026
B48: Built by | C48: No Dice Borough LTD
B49: Scope | C49: May 2026 – April 2027 trading period · 0.86× EBITDA entry · pure pro-rata
B50: Password | C50: NoDice2026 (required to edit locked cells)
A53: 📊 GOOGLE ADS MODEL ASSUMPTIONS — All marketing model inputs centralised here
A54: Parameter | B54: Conservative | C54: Base Case | D54: Optimistic | E54: Unit | F54: Notes
A55: BUDGET
A56: Weekly Ad Budget (£) | B56: 500 | C56: 500 | D56: 500 | E56: £/week | F56: Total Google Ads spend per week. Edit per scenario.
A57: CPC & SCALING
A58: Base CPC — verified (£) | B58: 0.32 | C58: 0.32 | D58: 0.32 | E58: £/click | F58: GA4 verified Nov-Dec 2025: £0.318. Locked across scenarios as anchor.
A59: CPC Scaling Factor (budget uplift) | B59: 0.35 | C59: 0.25 | D59: 0.15 | E59: multiplier | F59: CPC degrades as budget scales. Formula: CPC_adj = Base × (1 + Factor). Con=+35% at scale, Base=+25%, Opt=+15% (less degradation with better optimisation).
A60: CONVERSION & REALISATION
A61: Gross Conversion Rate (GA4) | B61: 0.04 | C61: 0.052 | D61: 0.065 | E61: conv/click | F61: GA4 verified: 5.8%. Conservative applies degradation at scale. This is the raw GA4 "conversion" event rate.
A62: Realisation Rate | B62: 0.55 | C62: 0.7 | D62: 0.82 | E62: % | F62: GA4 conversions ≠ actual paying customers. Form fills, partial bookings, and abandonments mean only a fraction become real revenue. Con=55% realisation (cautious), Base=70%, Opt=82%.
A63: REVENUE ASSUMPTIONS
A64: Avg Revenue Per Customer (£) | B64: 65 | C64: 90 | D64: 120 | E64: £ | F64: Actual spend per confirmed customer (gaming + bar). Lower than "per booking" — accounts for no-shows, split parties, and lower-spend visits.
A65: Avg Contribution Margin % | B65: 0.55 | C65: 0.6 | D65: 0.65 | E65: % | F65: Revenue that flows to profit after variable costs (bar stock, staffing uplift). 55-65% is realistic for gaming+bar venues.
A66: Incrementality Factor | B66: 0.68 | C66: 0.78 | D66: 0.85 | E66: % | F66: Fraction of ad-driven revenue that is truly incremental (would NOT have happened organically). Accounts for cannabilisation of organic traffic. Con=68%, Base=78%, Opt=85%. Industry benchmark: 60-80%.
A67: DIMINISHING RETURNS — SPEND TIER EFFICIENCY
A68: At higher spend levels, conversion efficiency degrades. Tier 1 = first £10k/yr (near-actual performance). Tier 2 = £10-26k. Tier 3 = £26k+.
A69: Tier 1 efficiency (£0 – £10k/yr) | B69: 1 | C69: 1 | D69: 1 | E69: multiplier | F69: First £10k at near-verified CPC/CVR. Anchored to actual data.
A70: Tier 2 efficiency (£10k – £26k/yr) | B70: 0.85 | C70: 0.88 | D70: 0.92 | E70: multiplier | F70: Efficiency drops as budget scales — audience saturation, less precise targeting.
A71: Tier 3 efficiency (£26k+/yr) | B71: 0.7 | C71: 0.76 | D71: 0.82 | E71: multiplier | F71: Significant diminishing returns at high volume. Conservative derating.

Sheet Audit Dashboard
A1: NO DICE BOROUGH LTD — FINANCIAL MODEL AUDIT DASHBOARD
A2: v2.0 | Built 14-Apr-2026 | No Dice Borough LTD | Password: NoDice2026 | All checks must show ✓ OK before presenting to investors
A3: OVERALL MODEL STATUS — must show ALL OK before investor presentation: | B3: =IF(COUNTIF(D6:D18,"*ERROR*")>0,"✗ "&COUNTIF(D6:D18,"*ERROR*")&" ERROR(S) — INVESTIGATE BEFORE PRESENTING","✓ ALL CHECKS PASS — INVESTOR READY")
A4: SECTION A — OVERALL MODEL STATUS
A5: Check | B5: Result | C5: Value | D5: Notes
A6: 2025 Annual Revenue | B6: =IF(ABS('Monthly Summary'!C15-741644.22)<1,"✓ OK","✗ CHANGED — verify source data") | C6: ='Monthly Summary'!C15 | D6: Formula-driven from Monthly Summary C15 → weekly sheets. Changes trigger ERROR.
A7: 2025 Annual All Costs | B7: =IF(ABS('Monthly Summary'!D15-570600.3)<1,"✓ OK","✗ CHANGED — verify source data") | C7: ='Monthly Summary'!D15 | D7: Formula-driven from Monthly Summary D15 → weekly sheets. Changes trigger ERROR.
A8: Cost Reconciliation (W+F+V+Other = Total) | B8: =IF(ABS('Monthly Summary'!G15+'Monthly Summary'!E15+'Monthly Summary'!F15+('Monthly Summary'!D15-'Monthly Summary'!G15-'Monthly Summary'!E15-'Monthly Summary'!F15)-'Monthly Summary'!D15)<0.02,"✓ OK","✗ ERROR — cost gap detected") | C8: ='Monthly Summary'!G15+'Monthly Summary'!E15+'Monthly Summary'!F15+('Monthly Summary'!D15-'Monthly Summary'!G15-'Monthly Summary'!E15-'Monthly Summary'!F15)-'Monthly Summary'!D15 | D8: Must equal £0. Any non-zero value means a cost category is missing or double-counted.
A9: 2025 Annual VAT Difference | B9: =IF(ABS('Monthly Summary'!H15-79094.23)<1,"✓ OK","✗ CHANGED — verify VAT calculation") | C9: ='Monthly Summary'!H15 | D9: Formula-driven from Monthly Summary H15. VAT separated from profit correctly.
A10: 2025 Annual Profit (Revenue − Costs − VAT) | B10: =IF(ABS('Monthly Summary'!C15-'Monthly Summary'!D15-'Monthly Summary'!H15-'Monthly Summary'!I15)<0.05,"✓ OK","✗ ERROR — profit formula mismatch") | C10: ='Monthly Summary'!C15-'Monthly Summary'!D15-'Monthly Summary'!H15 | D10: Independently recalculated: Revenue − All Costs − VAT = Profit. Must match I15.
A11: Weekly → Monthly Integrity (all 12 months) | B11: =IF('Monthly Summary'!J32="✓ ALL MATCH","✓ OK","✗ ERROR — weekly/monthly mismatch") | C11: ='Monthly Summary'!J152 | D11: Checks all 12 months: weekly sheet total = Monthly Summary total.
A12: Forecast Revenue Formula Integrity | B12: =IF(AND(ISNUMBER('Base Case Forecast'!N6),'Base Case Forecast'!N6>700000),"✓ OK","✗ ERROR — check BCF row 6") | C12: ='Base Case Forecast'!N6 | D12: Forecast total links live to BCF N5. Must be a number > £700k.
A13: Forecast Profit Check (Inc − Costs − VAT = Profit) | B13: =IF(ABS(ROUND('Base Case Forecast'!N6-'Base Case Forecast'!N8-'Base Case Forecast'!N9-'Base Case Forecast'!N10-'Base Case Forecast'!N14,2)-'Base Case Forecast'!N15)<1,"✓ OK","✗ ERROR — profit formula mismatch") | C13: =ROUND('Base Case Forecast'!N6-'Base Case Forecast'!N8-'Base Case Forecast'!N9-'Base Case Forecast'!N10-'Base Case Forecast'!N14,2) | D13: Independently recalculated profit vs what BCF N14 reports. Must agree.
A14: Cash Flow Balance (all 12 months balanced) | B14: =IF(COUNTIF('Cash Flow Forecast'!B35:M35,"✓")=12,"✓ OK","✗ ERROR — "&(12-COUNTIF('Cash Flow Forecast'!B35:M35,"✓"))&" month(s) unbalanced") | C14: =COUNTIF('Cash Flow Forecast'!B35:M35,"✓") | D14: Each month: opening + net flow = closing balance. All 12 must balance.
A15: VAT Treatment (formula-driven, separated from profit) | B15: =IF(ISNUMBER('Monthly Summary'!H15),"✓ OK","✗ ERROR") | C15: ='Monthly Summary'!H15 | D15: VAT difference formula-driven from Monthly Summary. Not deducted from P&L profit.
A16: No Circular References (all formulas one-directional) | B16: =IF(ISNUMBER('Dividend & Distribution Model'!B14),"✓ OK","✗ ERROR — check formula chain") | C16: ='Dividend & Distribution Model'!B14 | D16: If circular ref exists, BCF N15 returns #REF or 0. Non-zero number confirms clean chain.
A17: Director Salary (£30,000 pa, formula-driven) | B17: =IF('Base Case Forecast'!N12='Base Case Forecast'!B54,"✓ OK","✗ ERROR — salary param mismatch") | C17: ='Base Case Forecast'!B54 | D17: Director salary annual total must equal B53 × 1. All months use $B$53/12.
A18: Rent Treatment (cashflow only, not in P&L profit) | B18: =IF(ISNUMBER('Base Case Forecast'!N13),"✓ OK","✗ ERROR") | C18: ='Base Case Forecast'!N13 | D18: Rent is cashflow-only. P&L profit (N14) = Revenue − OpCosts − VAT (no rent deducted).
A19: ⚑ OTHER COSTS — Action Required | B19: ⚑ ACTION | C19: £61,151.58 | D19: 10.7% of costs unclassified. Verified real cost. Source breakdown needed from original bookkeeper records.
A21: SECTION B — COST STRUCTURE (2025 ACTUALS)
A22: Cost Category | B22: Annual £ | C22: % Revenue | D22: % Total Costs
A23: Staff Wages | B23: ='Monthly Summary'!G15 | C23: =B23/'Monthly Summary'!C15 | D23: =B23/B27
A24: Fixed Overheads | B24: ='Monthly Summary'!E15 | C24: =B24/'Monthly Summary'!C15 | D24: =B24/B27
A25: Variable Costs | B25: ='Monthly Summary'!F15 | C25: =B25/'Monthly Summary'!C15 | D25: =B25/B27
A26: Other Operating Costs | B26: ='Monthly Summary'!D15-'Monthly Summary'!G15-'Monthly Summary'!E15-'Monthly Summary'!F15 | C26: =B26/'Monthly Summary'!C15 | D26: =B26/B27
A27: TOTAL | B27: ='Monthly Summary'!D15 | C27: =B27/'Monthly Summary'!C15 | D27: =1
A28: Reconciliation check (must = £0) | B28: =B23+B24+B25+B26-B27 | C28: ✓ RECONCILED — no unexplained costs
A30: SECTION C — FORECAST ASSUMPTIONS (May 2026 – April 2027)
A31: Revenue uplift | B31: +15% on 2025 equivalent-month actuals
A32: Formula | B32: Revenue = 2025 base × 1.15 × seasonal weight ÷ weighted avg (1.1148)
A33: Wages | B33: 2025 actuals held flat — no increase assumed
A34: Fixed overheads | B34: 2025 base × 1.08 (business rates & energy confirmed uplift)
A35: Variable costs | B35: 2025 base scaled with revenue, hard-capped at 30% of monthly income
A36: Other costs | B36: NOT included in 2026/27 forecast — requires clarification from bookkeeper
A37: VAT | B37: Scales proportionally with revenue. Separated from P&L profit.
A38: Rent | B38: 15% of revenue, quarterly in arrears. Deposit covers May–Jul. Cash only.
A39: Director salary | B39: £30,000 pa (£2,500/month). Shown separately. Not in 2025 base.
A40: Investment | B40: £79,000 received May 2026. Startup costs £67,978 inc VAT (Hardware £24k + IP £12k + Stock & Setup £4,900 + Rent in Advance £27,078). Working Capital residual £11,022.
A42: ⚑ ACTION REQUIRED: "Other Operating Costs" (£61,152 in 2025) needs classification from original bookkeeper records before this model is presented to investors. It is a real verified cost (residual from weekly data audit), not an error. It must be named and explained. | B42: ='Monthly Summary'!D15-'Monthly Summary'!G15-'Monthly Summary'!E15-'Monthly Summary'!F15 | C42: =B42/'Monthly Summary'!C15 | D42: =B42/B27
A45: SECTION D — LIVE FORMULA-DRIVEN AUDIT CHECKS (Auto-update)
A46: These checks recalculate every time the workbook updates. Any ✗ ERROR must be investigated before presenting to investors.
A47: Check | C47: Live Value | D47: Status
A48: Annual Revenue (formula-driven from weekly data) | C48: ='Monthly Summary'!C15 | D48: =IF(ABS('Monthly Summary'!C15-741644.22)<1,"✓ OK — matches verified base","✗ ERROR — revenue has changed")
A49: Cost Reconciliation (Wages+Fixed+Var+Other = Total) | C49: ='Monthly Summary'!G15+'Monthly Summary'!E15+'Monthly Summary'!F15+('Monthly Summary'!D15-'Monthly Summary'!G15-'Monthly Summary'!E15-'Monthly Summary'!F15)-'Monthly Summary'!D15 | D49: =IF(ABS('Monthly Summary'!G15+'Monthly Summary'!E15+'Monthly Summary'!F15+('Monthly Summary'!D15-'Monthly Summary'!G15-'Monthly Summary'!E15-'Monthly Summary'!F15)-'Monthly Summary'!D15)<0.02,"✓ OK — reconciles to £0","✗ ERROR — cost gap detected")
A50: Weekly → Monthly Integrity | C50: ='Monthly Summary'!J152 | D50: =IF('Monthly Summary'!J152="✓ ALL MATCH","✓ OK — all 12 months verified","✗ ERROR — weekly/monthly mismatch")
A51: Forecast Revenue (formula-driven) | C51: ='Base Case Forecast'!N5 | D51: =IF(ISNUMBER('Base Case Forecast'!N5),"✓ OK — formula-driven","✗ ERROR — check BCF row 5")
A52: Forecast Profit Check (Inc - Costs - VAT = Profit) | C52: ='Base Case Forecast'!N6-'Base Case Forecast'!N8-'Base Case Forecast'!N9-'Base Case Forecast'!N10-'Base Case Forecast'!N14 | D52: =IF(ABS(('Base Case Forecast'!N6-'Base Case Forecast'!N8-'Base Case Forecast'!N9-'Base Case Forecast'!N10-'Base Case Forecast'!N14)-'Base Case Forecast'!N15)<1,"✓ OK — profit formula correct","✗ ERROR — profit mismatch")
A53: Cash Flow Balance (opening + net = closing) | C53: =COUNTIF('Cash Flow Forecast'!B35:M35,"✓") | D53: =IF(COUNTIF('Cash Flow Forecast'!B35:M35,"✓")=12,"✓ OK — all 12 months balance","✗ ERROR — "&(12-COUNTIF('Cash Flow Forecast'!B35:M35,"✓"))&" months unbalanced")
A54: VAT Reconciliation | C54: ='Monthly Summary'!H15 | D54: =IF(ISNUMBER('Monthly Summary'!H15),"✓ OK — VAT separated and formula-driven","✗ ERROR")
A55: Minimum Cash Position vs Safety Threshold | C55: =MIN('Cash Flow Forecast'!B30:M30) | D55: =IF(MIN('Cash Flow Forecast'!B30:M30)>=30000,"✓ OK — cash stays above £30k threshold","⚠ MONITOR — cash approaches minimum safe level")
A56: Investor Returns Sheet Integrity | C56: =IFERROR('Investor Returns'!B47,0) | D56: =IF(ISNUMBER(IFERROR('Investor Returns'!B47,FALSE())),"✓ OK — Investor Returns sheet formula-driven","✗ ERROR — check Investor Returns")
A57: Downside Scenario (profitable at -10%?) | C57: =IFERROR('Downside Scenario'!O16,0) | D57: =IF(IFERROR('Downside Scenario'!O16,0)>0,"✓ OK — profitable at −10%","✗ LOSS at −10% — review")
A60: DISTRIBUTION INTEGRITY CHECKS
A61: Distributions do not exceed profit | B61: =IF(ABS('Dividend & Distribution Model'!B31-'Dividend & Distribution Model'!B18)<0.5,"✓ OK","✗ ERROR — distributions exceed profit") | C61: =ROUND('Dividend & Distribution Model'!B31-'Dividend & Distribution Model'!B18,2) | D61: < £0.50
A62: No distribution is negative | B62: =IF(MIN('Dividend & Distribution Model'!B19,'Dividend & Distribution Model'!B20,'Dividend & Distribution Model'!B22,'Dividend & Distribution Model'!B23)>=0,"✓ OK","✗ NEGATIVE DISTRIBUTION") | C62: =MIN('Dividend & Distribution Model'!B19,'Dividend & Distribution Model'!B20,'Dividend & Distribution Model'!B22,'Dividend & Distribution Model'!B23) | D62: ≥ £0
A63: Founder repayment ≤ profit | B63: =IF('Dividend & Distribution Model'!B19<='Dividend & Distribution Model'!B18+0.01,"✓ OK","✗ EXCEEDS PROFIT") | C63: ='Dividend & Distribution Model'!B18-'Dividend & Distribution Model'!B19 | D63: ≥ £0
A64: Investor % applied to remaining pool only | B64: =IF(ABS('Dividend & Distribution Model'!B30-ROUND('Dividend & Distribution Model'!B29*'Dividend & Distribution Model'!B21,2))<0.5,"✓ OK","✗ INVESTOR % MISCALCULATED") | C64: ='Dividend & Distribution Model'!B22 | D64: Remaining × investor %

Sheet Annual Overview
A1: Borough Bar — Annual Overview 2025
A2: Metric | B2: Jan | C2: Feb | D2: Mar | E2: Apr | F2: May | G2: Jun | H2: Jul | I2: Aug | J2: Sep | K2: Oct | L2: Nov | M2: Dec | N2: ANNUAL TOTAL
A3: INCOME | B3: ='Monthly Summary'!C3 | C3: ='Monthly Summary'!C4 | D3: ='Monthly Summary'!C5 | E3: ='Monthly Summary'!C6 | F3: ='Monthly Summary'!C7 | G3: ='Monthly Summary'!C8 | H3: ='Monthly Summary'!C9 | I3: ='Monthly Summary'!C10 | J3: ='Monthly Summary'!C11 | K3: ='Monthly Summary'!C12 | L3: ='Monthly Summary'!C13 | M3: ='Monthly Summary'!C14 | N3: ='Monthly Summary'!C15
A4: ALL COSTS | B4: ='Monthly Summary'!D3 | C4: ='Monthly Summary'!D4 | D4: ='Monthly Summary'!D5 | E4: ='Monthly Summary'!D6 | F4: ='Monthly Summary'!D7 | G4: ='Monthly Summary'!D8 | H4: ='Monthly Summary'!D9 | I4: ='Monthly Summary'!D10 | J4: ='Monthly Summary'!D11 | K4: ='Monthly Summary'!D12 | L4: ='Monthly Summary'!D13 | M4: ='Monthly Summary'!D14 | N4: =SUM(B4:M4)
A5: FIXED COSTS | B5: ='Monthly Summary'!E3 | C5: ='Monthly Summary'!E4 | D5: ='Monthly Summary'!E5 | E5: ='Monthly Summary'!E6 | F5: ='Monthly Summary'!E7 | G5: ='Monthly Summary'!E8 | H5: ='Monthly Summary'!E9 | I5: ='Monthly Summary'!E10 | J5: ='Monthly Summary'!E11 | K5: ='Monthly Summary'!E12 | L5: ='Monthly Summary'!E13 | M5: ='Monthly Summary'!E14 | N5: =SUM(B5:M5)
A6: VARIABLE COSTS | B6: ='Monthly Summary'!F3 | C6: ='Monthly Summary'!F4 | D6: ='Monthly Summary'!F5 | E6: ='Monthly Summary'!F6 | F6: ='Monthly Summary'!F7 | G6: ='Monthly Summary'!F8 | H6: ='Monthly Summary'!F9 | I6: ='Monthly Summary'!F10 | J6: ='Monthly Summary'!F11 | K6: ='Monthly Summary'!F12 | L6: ='Monthly Summary'!F13 | M6: ='Monthly Summary'!F14 | N6: =SUM(B6:M6)
A7: WAGES | B7: ='Monthly Summary'!G3 | C7: ='Monthly Summary'!G4 | D7: ='Monthly Summary'!G5 | E7: ='Monthly Summary'!G6 | F7: ='Monthly Summary'!G7 | G7: ='Monthly Summary'!G8 | H7: ='Monthly Summary'!G9 | I7: ='Monthly Summary'!G10 | J7: ='Monthly Summary'!G11 | K7: ='Monthly Summary'!G12 | L7: ='Monthly Summary'!G13 | M7: ='Monthly Summary'!G14 | N7: =SUM(B7:M7)
A8: VAT DIFF | B8: ='Monthly Summary'!H3 | C8: ='Monthly Summary'!H4 | D8: ='Monthly Summary'!H5 | E8: ='Monthly Summary'!H6 | F8: ='Monthly Summary'!H7 | G8: ='Monthly Summary'!H8 | H8: ='Monthly Summary'!H9 | I8: ='Monthly Summary'!H10 | J8: ='Monthly Summary'!H11 | K8: ='Monthly Summary'!H12 | L8: ='Monthly Summary'!H13 | M8: ='Monthly Summary'!H14 | N8: =SUM(B8:M8)
A9: PROFIT | B9: ='Monthly Summary'!I3 | C9: ='Monthly Summary'!I4 | D9: ='Monthly Summary'!I5 | E9: ='Monthly Summary'!I6 | F9: ='Monthly Summary'!I7 | G9: ='Monthly Summary'!I8 | H9: ='Monthly Summary'!I9 | I9: ='Monthly Summary'!I10 | J9: ='Monthly Summary'!I11 | K9: ='Monthly Summary'!I12 | L9: ='Monthly Summary'!I13 | M9: ='Monthly Summary'!I14 | N9: =SUM(B9:M9)
A10: PROFIT + COSTS AFTER VAT | B10: ='Monthly Summary'!J3 | C10: ='Monthly Summary'!J4 | D10: ='Monthly Summary'!J5 | E10: ='Monthly Summary'!J6 | F10: ='Monthly Summary'!J7 | G10: ='Monthly Summary'!J8 | H10: ='Monthly Summary'!J9 | I10: ='Monthly Summary'!J10 | J10: ='Monthly Summary'!J11 | K10: ='Monthly Summary'!J12 | L10: ='Monthly Summary'!J13 | M10: ='Monthly Summary'!J14 | N10: =SUM(B10:M10)
A11: WEEKS | B11: ='Monthly Summary'!B3 | C11: ='Monthly Summary'!B4 | D11: ='Monthly Summary'!B5 | E11: ='Monthly Summary'!B6 | F11: ='Monthly Summary'!B7 | G11: ='Monthly Summary'!B8 | H11: ='Monthly Summary'!B9 | I11: ='Monthly Summary'!B10 | J11: ='Monthly Summary'!B11 | K11: ='Monthly Summary'!B12 | L11: ='Monthly Summary'!B13 | M11: ='Monthly Summary'!B14 | N11: =SUM(B11:M11)
A14: COST STRUCTURE — 2025 ACTUALS | Reconciliation & Transparency
A15: All Costs = Staff Wages + Fixed Overheads + Variable Costs + Other Operating Costs. Other Operating Costs = verified residual from weekly data (avg 10.7% of total costs — non-VAT miscellaneous items).
A16: Cost Category | D16: Annual £ | F16: % of Revenue | H16: % of Total Costs | J16: Notes
A17: Staff Wages | D17: ='Monthly Summary'!G15 | F17: =D17/'Monthly Summary'!C15 | H17: =D17/D21 | J17: 2025 actual payroll — held as base for 2026/27 forecast
A18: Fixed Overheads | D18: ='Monthly Summary'!E15 | F18: =D18/'Monthly Summary'!C15 | H18: =D18/D21 | J18: Rent (historical fixed), rates, utilities, insurance, subscriptions
A19: Variable Costs | D19: ='Monthly Summary'!F15 | F19: =D19/'Monthly Summary'!C15 | H19: =D19/D21 | J19: Cost of goods, stock — avg 11.7% of revenue. Capped at 30% in forecast
A20: Other Operating Costs | D20: ='Monthly Summary'!D15-D17-D18-D19 | F20: =D20/'Monthly Summary'!C15 | H20: =D20/D21 | J20: ⚑ Verified residual (non-VAT items). ~10.7% of total costs. Requires breakdown from source data
A21: TOTAL OPERATING COSTS | D21: ='Monthly Summary'!D15 | F21: =D21/'Monthly Summary'!C15 | H21: =1 | J21: Fixed + Variable + Wages + Other = Total. Reconciliation check: £0
A22: RECONCILIATION CHECK (must = £0) | D22: =D17+D18+D19+D20-D21 | F22: =IF(ABS(D22)<0.01,"✓ RECONCILED — Total Costs = Sum of all visible cost lines","✗ MISMATCH — investigate")
A24: VAT RECONCILIATION — 2025 Actuals
A25: Total Revenue (inc VAT on bar/gaming) | F25: ='Monthly Summary'!C15
A26: Less: VAT Difference paid to HMRC | F26: =-'Monthly Summary'!H15
A27: Net Revenue (ex-VAT profit base) | F27: =F25+F26
A28: Less: All Operating Costs | F28: =-'Monthly Summary'!D15
A29: NET PROFIT | F29: =F27+F28 | J29: Confirmed £91,949.67 ✓

Sheet Performance Charts
